Workbook
Name AWCurrentRel: 'Automated View'!$P$2
Name AWLookup: Table3[]
Name AWRelease: 'Automated View'!$A$1
Name AWReleaseEntered: 'Automated View'!$A$1
Name AWReleaseNum: 'Automated View'!$M$2
Name MinVerInfo: Table1[]
Name TcBaseVer: 'Automated View'!$O$2
Name TcLookup: Table2[]
Name TcRelease: 'Automated View'!$A$2
Name TcReleaseNum: 'Automated View'!$N$2

Sheet Automated View
A1: 2606 | B1: <-- Select your Active Workspace version here | E1: =CONCATENATE(COUNTIF(L4:L8460,"Available")," of ",(COUNTIF(L4:L8460,"Available")+COUNTIF(L4:L8460,"Not Supported"))," features supported") -> 2665 of 2665 features supported | M1: AW Version | N1: TC Version | O1: TC Base | P1: AW Future
A2: 2606 | B2: <-- Select your Teamcenter version here | M2: =VLOOKUP(AWRelease,AWLookup,2,FALSE) -> 2606 | N2: =VLOOKUP(TcRelease,TcLookup,3,FALSE) -> 2606 | O2: =IFERROR(VLOOKUP(TcRelease,Table2[#All],2,FALSE),0) -> 2606 | P2: 2612
A3: Active Workspace Release | B3: Category | C3: Area | D3: Topic | E3: Feature | F3: Teamcenter Prior Release Minimum | G3: Teamcenter Current Release Minimum | H3: Minimum Version on Teamcenter 11 | I3: Minimum Version on Teamcenter 12 | J3: Minimum Version on Teamcenter 13 | K3: Minimum Version on Teamcenter 14 | L3: Feature Availability | M3: AW Version Okay | N3: TC Version In Range | O3: TC Version Okay | P3: TC Ver 2 Check | Q3: Combo Okay | R3: Future | S3: Link to What's New Material | T3: Link String for What's New Material | U3: URL to What's New Material
A4: =IF(OR('Raw Data'!A2=0,'Raw Data'!A2="Delete"),"",'Raw Data'!A2) -> 2 | B4: =IF(OR('Raw Data'!B2=0,'Raw Data'!B2="Delete"),"",'Raw Data'!B2) -> Foundation | C4: =IF(OR('Raw Data'!C2=0,'Raw Data'!C2="Delete"),"",'Raw Data'!C2) -> Connectivity | D4: =IF(OR('Raw Data'!D2=0,'Raw Data'!D2="Delete"),"",'Raw Data'!D2) -> Active Integration | E4: =IF(OR('Raw Data'!E2=0,'Raw Data'!E2="Delete"),"",'Raw Data'!E2) -> Open basic documents and models in appropriate application | F4: {=_xlfn.SWITCH(ROUND(VLOOKUP(A4,Table1[#All],3),0),11,H4,12,I4,13,J4,14,K4,"N/A")} -> 13 | G4: {=_xlfn.SWITCH(ROUND(VLOOKUP(A4,Table1[#All],5),0),11,H4,12,I4,13,J4,14,K4,"N/A")} -> 14 | H4: =IF(OR('Raw Data'!H2=0,'Raw Data'!H2="Delete"),"",'Raw Data'!H2) -> 13 | I4: =IF(OR('Raw Data'!I2=0,'Raw Data'!I2="Delete"),"",'Raw Data'!I2) -> 14 | J4: =IF(OR('Raw Data'!J2=0,'Raw Data'!J2="Delete"),"",'Raw Data'!J2) | K4: =IF(OR('Raw Data'!K2=0,'Raw Data'!K2="Delete"),"",'Raw Data'!K2) | L4: =R4 -> Available | M4: =IF(A4="","",IF(OR(AWReleaseNum>=A4,AWReleaseNum=0),"Available","Not Supported")) -> Available | N4: =IF(A4="","",IF(TcRelease="Any","Available",IF(OR(AND(TcReleaseNum>=VLOOKUP(AWReleaseNum,MinVerInfo,3,FALSE),TcReleaseNum<=VLOOKUP(AWReleaseNum,MinVerInfo,4,FALSE)),AND(TcReleaseNum>=VLOOKUP(AWReleaseNum,MinVerInfo,5,FALSE),TcReleaseNum<=VLOOKUP(AWReleaseNum,MinVerInfo,6,FALSE))),"Available","Not Supported"))) -> Available | O4: =IF(TcReleaseNum<P4,"Not Supported","Available") -> Available | P4: {=_xlfn.SWITCH(TcBaseVer, 14, K4, 13, J4, 12, I4, 11, IFERROR(VLOOKUP(H4,Table2[#All],3,FALSE),"N/A"),0)} -> 0 | Q4: =IF(TcBaseVer=0,M4,IF(AND(N4="Available",M4="Available",O4="Available"),"Available",IF(M4="","","Not Supported"))) -> Available | R4: =IF(A4>=AWCurrentRel, "Future",Q4) -> Available | S4: =HYPERLINK(U4,T4) -> Not Available | T4: =IFERROR(VLOOKUP(CONCATENATE($B4,"_",$A4),Table4[#All],5,FALSE),"Not Available") -> Not Available | U4: =IFERROR(VLOOKUP(CONCATENATE(B4,"_",A4),Table4[#All],6,FALSE),"")
A5: =IF(OR('Raw Data'!A3=0,'Raw Data'!A3="Delete"),"",'Raw Data'!A3) -> 2 | B5: =IF(OR('Raw Data'!B3=0,'Raw Data'!B3="Delete"),"",'Raw Data'!B3) -> Foundation | C5: =IF(OR('Raw Data'!C3=0,'Raw Data'!C3="Delete"),"",'Raw Data'!C3) -> Connectivity | D5: =IF(OR('Raw Data'!D3=0,'Raw Data'!D3="Delete"),"",'Raw Data'!D3) -> Active Integration | E5: =IF(OR('Raw Data'!E3=0,'Raw Data'!E3="Delete"),"",'Raw Data'!E3) -> Open TcVis on simple configured structure | F5: {=_xlfn.SWITCH(ROUND(VLOOKUP(A5,Table1[#All],3),0),11,H5,12,I5,13,J5,14,K5,"N/A")} -> 13 | G5: {=_xlfn.SWITCH(ROUND(VLOOKUP(A5,Table1[#All],5),0),11,H5,12,I5,13,J5,14,K5,"N/A")} -> 14 | H5: =IF(OR('Raw Data'!H3=0,'Raw Data'!H3="Delete"),"",'Raw Data'!H3) -> 13 | I5: =IF(OR('Raw Data'!I3=0,'Raw Data'!I3="Delete"),"",'Raw Data'!I3) -> 14 | J5: =IF(OR('Raw Data'!J3=0,'Raw Data'!J3="Delete"),"",'Raw Data'!J3) | K5: =IF(OR('Raw Data'!K3=0,'Raw Data'!K3="Delete"),"",'Raw Data'!K3) | L5: =R5 -> Available | M5: =IF(A5="","",IF(OR(AWReleaseNum>=A5,AWReleaseNum=0),"Available","Not Supported")) -> Available | N5: =IF(A5="","",IF(TcRelease="Any","Available",IF(OR(AND(TcReleaseNum>=VLOOKUP(AWReleaseNum,MinVerInfo,3,FALSE),TcReleaseNum<=VLOOKUP(AWReleaseNum,MinVerInfo,4,FALSE)),AND(TcReleaseNum>=VLOOKUP(AWReleaseNum,MinVerInfo,5,FALSE),TcReleaseNum<=VLOOKUP(AWReleaseNum,MinVerInfo,6,FALSE))),"Available","Not Supported"))) -> Available | O5: =IF(TcReleaseNum<P5,"Not Supported","Available") -> Available | P5: {=_xlfn.SWITCH(TcBaseVer, 14, K5, 13, J5, 12, I5, 11, IFERROR(VLOOKUP(H5,Table2[#All],3,FALSE),"N/A"),0)} -> 0 | Q5: =IF(TcBaseVer=0,M5,IF(AND(N5="Available",M5="Available",O5="Available"),"Available",IF(M5="","","Not Supported"))) -> Available | R5: =IF(A5>=AWCurrentRel, "Future",Q5) -> Available | S5: =HYPERLINK(U5,T5) -> Not Available | T5: =IFERROR(VLOOKUP(CONCATENATE($B5,"_",$A5),Table4[#All],5,FALSE),"Not Available") -> Not Available | U5: =IFERROR(VLOOKUP(CONCATENATE(B5,"_",A5),Table4[#All],6,FALSE),"")
A6: =IF(OR('Raw Data'!A28=0,'Raw Data'!A28="Delete"),"",'Raw Data'!A28) -> 2 | B6: =IF(OR('Raw Data'!B28=0,'Raw Data'!B28="Delete"),"",'Raw Data'!B28) -> Foundation | C6: =IF(OR('Raw Data'!C28=0,'Raw Data'!C28="Delete"),"",'Raw Data'!C28) -> Usability | D6: =IF(OR('Raw Data'!D28=0,'Raw Data'!D28="Delete"),"",'Raw Data'!D28) -> Platform - Active Workspace Framework - Usability | E6: =IF(OR('Raw Data'!E28=0,'Raw Data'!E28="Delete"),"",'Raw Data'!E28) -> Configurable Home Page | F6: {=_xlfn.SWITCH(ROUND(VLOOKUP(A6,Table1[#All],3),0),11,H6,12,I6,13,J6,14,K6,"N/A")} -> 13 | G6: {=_xlfn.SWITCH(ROUND(VLOOKUP(A6,Table1[#All],5),0),11,H6,12,I6,13,J6,14,K6,"N/A")} -> 14 | H6: =IF(OR('Raw Data'!H28=0,'Raw Data'!H28="Delete"),"",'Raw Data'!H28) -> 13 | I6: =IF(OR('Raw Data'!I28=0,'Raw Data'!I28="Delete"),"",'Raw Data'!I28) -> 14 | J6: =IF(OR('Raw Data'!J28=0,'Raw Data'!J28="Delete"),"",'Raw Data'!J28) | K6: =IF(OR('Raw Data'!K28=0,'Raw Data'!K28="Delete"),"",'Raw Data'!K28) | L6: =R6 -> Available | M6: =IF(A6="","",IF(OR(AWReleaseNum>=A6,AWReleaseNum=0),"Available","Not Supported")) -> Available | N6: =IF(A6="","",IF(TcRelease="Any","Available",IF(OR(AND(TcReleaseNum>=VLOOKUP(AWReleaseNum,MinVerInfo,3,FALSE),TcReleaseNum<=VLOOKUP(AWReleaseNum,MinVerInfo,4,FALSE)),AND(TcReleaseNum>=VLOOKUP(AWReleaseNum,MinVerInfo,5,FALSE),TcReleaseNum<=VLOOKUP(AWReleaseNum,MinVerInfo,6,FALSE))),"Available","Not Supported"))) -> Available | O6: =IF(TcReleaseNum<P6,"Not Supported","Available") -> Available | P6: {=_xlfn.SWITCH(TcBaseVer, 14, K6, 13, J6, 12, I6, 11, IFERROR(VLOOKUP(H6,Table2[#All],3,FALSE),"N/A"),0)} -> 0 | Q6: =IF(TcBaseVer=0,M6,IF(AND(N6="Available",M6="Available",O6="Available"),"Available",IF(M6="","","Not Supported"))) -> Available | R6: =IF(A6>=AWCurrentRel, "Future",Q6) -> Available | S6: =HYPERLINK(U6,T6) -> Not Available | T6: =IFERROR(VLOOKUP(CONCATENATE($B6,"_",$A6),Table4[#All],5,FALSE),"Not Available") -> Not Available | U6: =IFERROR(VLOOKUP(CONCATENATE(B6,"_",A6),Table4[#All],6,FALSE),"")
A7: =IF(OR('Raw Data'!A29=0,'Raw Data'!A29="Delete"),"",'Raw Data'!A29) -> 2 | B7: =IF(OR('Raw Data'!B29=0,'Raw Data'!B29="Delete"),"",'Raw Data'!B29) -> Foundation | C7: =IF(OR('Raw Data'!C29=0,'Raw Data'!C29="Delete"),"",'Raw Data'!C29) -> Usability | D7: =IF(OR('Raw Data'!D29=0,'Raw Data'!D29="Delete"),"",'Raw Data'!D29) -> Platform - Active Workspace Framework - Usability | E7: =IF(OR('Raw Data'!E29=0,'Raw Data'!E29="Delete"),"",'Raw Data'!E29) -> Create Item | F7: {=_xlfn.SWITCH(ROUND(VLOOKUP(A7,Table1[#All],3),0),11,H7,12,I7,13,J7,14,K7,"N/A")} -> 13 | G7: {=_xlfn.SWITCH(ROUND(VLOOKUP(A7,Table1[#All],5),0),11,H7,12,I7,13,J7,14,K7,"N/A")} -> 14 | H7: =IF(OR('Raw Data'!H29=0,'Raw Data'!H29="Delete"),"",'Raw Data'!H29) -> 13 | I7: =IF(OR('Raw Data'!I29=0,'Raw Data'!I29="Delete"),"",'Raw Data'!I29) -> 14 | J7: =IF(OR('Raw Data'!J29=0,'Raw Data'!J29="Delete"),"",'Raw Data'!J29) | K7: =IF(OR('Raw Data'!K29=0,'Raw Data'!K29="Delete"),"",'Raw Data'!K29) | L7: =R7 -> Available | M7: =IF(A7="","",IF(OR(AWReleaseNum>=A7,AWReleaseNum=0),"Available","Not Supported")) -> Available | N7: =IF(A7="","",IF(TcRelease="Any","Available",IF(OR(AND(TcReleaseNum>=VLOOKUP(AWReleaseNum,MinVerInfo,3,FALSE),TcReleaseNum<=VLOOKUP(AWReleaseNum,MinVerInfo,4,FALSE)),AND(TcReleaseNum>=VLOOKUP(AWReleaseNum,MinVerInfo,5,FALSE),TcReleaseNum<=VLOOKUP(AWReleaseNum,MinVerInfo,6,FALSE))),"Available","Not Supported"))) -> Available | O7: =IF(TcReleaseNum<P7,"Not Supported","Available") -> Available | P7: {=_xlfn.SWITCH(TcBaseVer, 14, K7, 13, J7, 12, I7, 11, IFERROR(VLOOKUP(H7,Table2[#All],3,FALSE),"N/A"),0)} -> 0 | Q7: =IF(TcBaseVer=0,M7,IF(AND(N7="Available",M7="Available",O7="Available"),"Available",IF(M7="","","Not Supported"))) -> Available | R7: =IF(A7>=AWCurrentRel, "Future",Q7) -> Available | S7: =HYPERLINK(U7,T7) -> Not Available | T7: =IFERROR(VLOOKUP(CONCATENATE($B7,"_",$A7),Table4[#All],5,FALSE),"Not Available") -> Not Available | U7: =IFERROR(VLOOKUP(CONCATENATE(B7,"_",A7),Table4[#All],6,FALSE),"")
A8: =IF(OR('Raw Data'!A30=0,'Raw Data'!A30="Delete"),"",'Raw Data'!A30) -> 2 | B8: =IF(OR('Raw Data'!B30=0,'Raw Data'!B30="Delete"),"",'Raw Data'!B30) -> Foundation | C8: =IF(OR('Raw Data'!C30=0,'Raw Data'!C30="Delete"),"",'Raw Data'!C30) -> Usability | D8: =IF(OR('Raw Data'!D30=0,'Raw Data'!D30="Delete"),"",'Raw Data'!D30) -> Platform - Active Workspace Framework - Usability | E8: =IF(OR('Raw Data'!E30=0,'Raw Data'!E30="Delete"),"",'Raw Data'!E30) -> Create Folder | F8: {=_xlfn.SWITCH(ROUND(VLOOKUP(A8,Table1[#All],3),0),11,H8,12,I8,13,J8,14,K8,"N/A")} -> 13 | G8: {=_xlfn.SWITCH(ROUND(VLOOKUP(A8,Table1[#All],5),0),11,H8,12,I8,13,J8,14,K8,"N/A")} -> 14 | H8: =IF(OR('Raw Data'!H30=0,'Raw Data'!H30="Delete"),"",'Raw Data'!H30) -> 13 | I8: =IF(OR('Raw Data'!I30=0,'Raw Data'!I30="Delete"),"",'Raw Data'!I30) -> 14 | J8: =IF(OR('Raw Data'!J30=0,'Raw Data'!J30="Delete"),"",'Raw Data'!J30) | K8: =IF(OR('Raw Data'!K30=0,'Raw Data'!K30="Delete"),"",'Raw Data'!K30) | L8: =R8 -> Available | M8: =IF(A8="","",IF(OR(AWReleaseNum>=A8,AWReleaseNum=0),"Available","Not Supported")) -> Available | N8: =IF(A8="","",IF(TcRelease="Any","Available",IF(OR(AND(TcReleaseNum>=VLOOKUP(AWReleaseNum,MinVerInfo,3,FALSE),TcReleaseNum<=VLOOKUP(AWReleaseNum,MinVerInfo,4,FALSE)),AND(TcReleaseNum>=VLOOKUP(AWReleaseNum,MinVerInfo,5,FALSE),TcReleaseNum<=VLOOKUP(AWReleaseNum,MinVerInfo,6,FALSE))),"Available","Not Supported"))) -> Available | O8: =IF(TcReleaseNum<P8,"Not Supported","Available") -> Available | P8: {=_xlfn.SWITCH(TcBaseVer, 14, K8, 13, J8, 12, I8, 11, IFERROR(VLOOKUP(H8,Table2[#All],3,FALSE),"N/A"),0)} -> 0 | Q8: =IF(TcBaseVer=0,M8,IF(AND(N8="Available",M8="Available",O8="Available"),"Available",IF(M8="","","Not Supported"))) -> Available | R8: =IF(A8>=AWCurrentRel, "Future",Q8) -> Available | S8: =HYPERLINK(U8,T8) -> Not Available | T8: =IFERROR(VLOOKUP(CONCATENATE($B8,"_",$A8),Table4[#All],5,FALSE),"Not Available") -> Not Available | U8: =IFERROR(VLOOKUP(CONCATENATE(B8,"_",A8),Table4[#All],6,FALSE),"")
A9: =IF(OR('Raw Data'!A31=0,'Raw Data'!A31="Delete"),"",'Raw Data'!A31) -> 2 | B9: =IF(OR('Raw Data'!B31=0,'Raw Data'!B31="Delete"),"",'Raw Data'!B31) -> Foundation | C9: =IF(OR('Raw Data'!C31=0,'Raw Data'!C31="Delete"),"",'Raw Data'!C31) -> Usability | D9: =IF(OR('Raw Data'!D31=0,'Raw Data'!D31="Delete"),"",'Raw Data'!D31) -> Platform - Active Workspace Framework - Usability | E9: =IF(OR('Raw Data'!E31=0,'Raw Data'!E31="Delete"),"",'Raw Data'!E31) -> Create File (w/Upload) | F9: {=_xlfn.SWITCH(ROUND(VLOOKUP(A9,Table1[#All],3),0),11,H9,12,I9,13,J9,14,K9,"N/A")} -> 13 | G9: {=_xlfn.SWITCH(ROUND(VLOOKUP(A9,Table1[#All],5),0),11,H9,12,I9,13,J9,14,K9,"N/A")} -> 14 | H9: =IF(OR('Raw Data'!H31=0,'Raw Data'!H31="Delete"),"",'Raw Data'!H31) -> 13 | I9: =IF(OR('Raw Data'!I31=0,'Raw Data'!I31="Delete"),"",'Raw Data'!I31) -> 14 | J9: =IF(OR('Raw Data'!J31=0,'Raw Data'!J31="Delete"),"",'Raw Data'!J31) | K9: =IF(OR('Raw Data'!K31=0,'Raw Data'!K31="Delete"),"",'Raw Data'!K31) | L9: =R9 -> Available | M9: =IF(A9="","",IF(OR(AWReleaseNum>=A9,AWReleaseNum=0),"Available","Not Supported")) -> Available | N9: =IF(A9="","",IF(TcRelease="Any","Available",IF(OR(AND(TcReleaseNum>=VLOOKUP(AWReleaseNum,MinVerInfo,3,FALSE),TcReleaseNum<=VLOOKUP(AWReleaseNum,MinVerInfo,4,FALSE)),AND(TcReleaseNum>=VLOOKUP(AWReleaseNum,MinVerInfo,5,FALSE),TcReleaseNum<=VLOOKUP(AWReleaseNum,MinVerInfo,6,FALSE))),"Available","Not Supported"))) -> Available | O9: =IF(TcReleaseNum<P9,"Not Supported","Available") -> Available | P9: {=_xlfn.SWITCH(TcBaseVer, 14, K9, 13, J9, 12, I9, 11, IFERROR(VLOOKUP(H9,Table2[#All],3,FALSE),"N/A"),0)} -> 0 | Q9: =IF(TcBaseVer=0,M9,IF(AND(N9="Available",M9="Available",O9="Available"),"Available",IF(M9="","","Not Supported"))) -> Available | R9: =IF(A9>=AWCurrentRel, "Future",Q9) -> Available | S9: =HYPERLINK(U9,T9) -> Not Available | T9: =IFERROR(VLOOKUP(CONCATENATE($B9,"_",$A9),Table4[#All],5,FALSE),"Not Available") -> Not Available | U9: =IFERROR(VLOOKUP(CONCATENATE(B9,"_",A9),Table4[#All],6,FALSE),"")
A10: =IF(OR('Raw Data'!A32=0,'Raw Data'!A32="Delete"),"",'Raw Data'!A32) -> 2 | B10: =IF(OR('Raw Data'!B32=0,'Raw Data'!B32="Delete"),"",'Raw Data'!B32) -> Foundation | C10: =IF(OR('Raw Data'!C32=0,'Raw Data'!C32="Delete"),"",'Raw Data'!C32) -> Usability | D10: =IF(OR('Raw Data'!D32=0,'Raw Data'!D32="Delete"),"",'Raw Data'!D32) -> Platform - Active Workspace Framework - Usability | E10: =IF(OR('Raw Data'!E32=0,'Raw Data'!E32="Delete"),"",'Raw Data'!E32) -> Create change in context (or not) | F10: {=_xlfn.SWITCH(ROUND(VLOOKUP(A10,Table1[#All],3),0),11,H10,12,I10,13,J10,14,K10,"N/A")} -> 13 | G10: {=_xlfn.SWITCH(ROUND(VLOOKUP(A10,Table1[#All],5),0),11,H10,12,I10,13,J10,14,K10,"N/A")} -> 14 | H10: =IF(OR('Raw Data'!H32=0,'Raw Data'!H32="Delete"),"",'Raw Data'!H32) -> 13 | I10: =IF(OR('Raw Data'!I32=0,'Raw Data'!I32="Delete"),"",'Raw Data'!I32) -> 14 | J10: =IF(OR('Raw Data'!J32=0,'Raw Data'!J32="Delete"),"",'Raw Data'!J32) | K10: =IF(OR('Raw Data'!K32=0,'Raw Data'!K32="Delete"),"",'Raw Data'!K32) | L10: =R10 -> Available | M10: =IF(A10="","",IF(OR(AWReleaseNum>=A10,AWReleaseNum=0),"Available","Not Supported")) -> Available | N10: =IF(A10="","",IF(TcRelease="Any","Available",IF(OR(AND(TcReleaseNum>=VLOOKUP(AWReleaseNum,MinVerInfo,3,FALSE),TcReleaseNum<=VLOOKUP(AWReleaseNum,MinVerInfo,4,FALSE)),AND(TcReleaseNum>=VLOOKUP(AWReleaseNum,MinVerInfo,5,FALSE),TcReleaseNum<=VLOOKUP(AWReleaseNum,MinVerInfo,6,FALSE))),"Available","Not Supported"))) -> Available | O10: =IF(TcReleaseNum<P10,"Not Supported","Available") -> Available | P10: {=_xlfn.SWITCH(TcBaseVer, 14, K10, 13, J10, 12, I10, 11, IFERROR(VLOOKUP(H10,Table2[#All],3,FALSE),"N/A"),0)} -> 0 | Q10: =IF(TcBaseVer=0,M10,IF(AND(N10="Available",M10="Available",O10="Available"),"Available",IF(M10="","","Not Supported"))) -> Available | R10: =IF(A10>=AWCurrentRel, "Future",Q10) -> Available | S10: =HYPERLINK(U10,T10) -> Not Available | T10: =IFERROR(VLOOKUP(CONCATENATE($B10,"_",$A10),Table4[#All],5,FALSE),"Not Available") -> Not Available | U10: =IFERROR(VLOOKUP(CONCATENATE(B10,"_",A10),Table4[#All],6,FALSE),"")
A11: =IF(OR('Raw Data'!A33=0,'Raw Data'!A33="Delete"),"",'Raw Data'!A33) -> 2 | B11: =IF(OR('Raw Data'!B33=0,'Raw Data'!B33="Delete"),"",'Raw Data'!B33) -> Foundation | C11: =IF(OR('Raw Data'!C33=0,'Raw Data'!C33="Delete"),"",'Raw Data'!C33) -> Usability | D11: =IF(OR('Raw Data'!D33=0,'Raw Data'!D33="Delete"),"",'Raw Data'!D33) -> Platform - Active Workspace Framework - Usability | E11: =IF(OR('Raw Data'!E33=0,'Raw Data'!E33="Delete"),"",'Raw Data'!E33) -> Revise | F11: {=_xlfn.SWITCH(ROUND(VLOOKUP(A11,Table1[#All],3),0),11,H11,12,I11,13,J11,14,K11,"N/A")} -> 13 | G11: {=_xlfn.SWITCH(ROUND(VLOOKUP(A11,Table1[#All],5),0),11,H11,12,I11,13,J11,14,K11,"N/A")} -> 14 | H11: =IF(OR('Raw Data'!H33=0,'Raw Data'!H33="Delete"),"",'Raw Data'!H33) -> 13 | I11: =IF(OR('Raw Data'!I33=0,'Raw Data'!I33="Delete"),"",'Raw Data'!I33) -> 14 | J11: =IF(OR('Raw Data'!J33=0,'Raw Data'!J33="Delete"),"",'Raw Data'!J33) | K11: =IF(OR('Raw Data'!K33=0,'Raw Data'!K33="Delete"),"",'Raw Data'!K33) | L11: =R11 -> Available | M11: =IF(A11="","",IF(OR(AWReleaseNum>=A11,AWReleaseNum=0),"Available","Not Supported")) -> Available | N11: =IF(A11="","",IF(TcRelease="Any","Available",IF(OR(AND(TcReleaseNum>=VLOOKUP(AWReleaseNum,MinVerInfo,3,FALSE),TcReleaseNum<=VLOOKUP(AWReleaseNum,MinVerInfo,4,FALSE)),AND(TcReleaseNum>=VLOOKUP(AWReleaseNum,MinVerInfo,5,FALSE),TcReleaseNum<=VLOOKUP(AWReleaseNum,MinVerInfo,6,FALSE))),"Available","Not Supported"))) -> Available | O11: =IF(TcReleaseNum<P11,"Not Supported","Available") -> Available | P11: {=_xlfn.SWITCH(TcBaseVer, 14, K11, 13, J11, 12, I11, 11, IFERROR(VLOOKUP(H11,Table2[#All],3,FALSE),"N/A"),0)} -> 0 | Q11: =IF(TcBaseVer=0,M11,IF(AND(N11="Available",M11="Available",O11="Available"),"Available",IF(M11="","","Not Supported"))) -> Available | R11: =IF(A11>=AWCurrentRel, "Future",Q11) -> Available | S11: =HYPERLINK(U11,T11) -> Not Available | T11: =IFERROR(VLOOKUP(CONCATENATE($B11,"_",$A11),Table4[#All],5,FALSE),"Not Available") -> Not Available | U11: =IFERROR(VLOOKUP(CONCATENATE(B11,"_",A11),Table4[#All],6,FALSE),"")
A12: =IF(OR('Raw Data'!A34=0,'Raw Data'!A34="Delete"),"",'Raw Data'!A34) -> 2 | B12: =IF(OR('Raw Data'!B34=0,'Raw Data'!B34="Delete"),"",'Raw Data'!B34) -> Foundation | C12: =IF(OR('Raw Data'!C34=0,'Raw Data'!C34="Delete"),"",'Raw Data'!C34) -> Usability | D12: =IF(OR('Raw Data'!D34=0,'Raw Data'!D34="Delete"),"",'Raw Data'!D34) -> Platform - Active Workspace Framework - Usability | E12: =IF(OR('Raw Data'!E34=0,'Raw Data'!E34="Delete"),"",'Raw Data'!E34) -> Context Setting – Project, Group/Role, Revision Rule | F12: {=_xlfn.SWITCH(ROUND(VLOOKUP(A12,Table1[#All],3),0),11,H12,12,I12,13,J12,14,K12,"N/A")} -> 13 | G12: {=_xlfn.SWITCH(ROUND(VLOOKUP(A12,Table1[#All],5),0),11,H12,12,I12,13,J12,14,K12,"N/A")} -> 14 | H12: =IF(OR('Raw Data'!H34=0,'Raw Data'!H34="Delete"),"",'Raw Data'!H34) -> 13 | I12: =IF(OR('Raw Data'!I34=0,'Raw Data'!I34="Delete"),"",'Raw Data'!I34) -> 14 | J12: =IF(OR('Raw Data'!J34=0,'Raw Data'!J34="Delete"),"",'Raw Data'!J34) | K12: =IF(OR('Raw Data'!K34=0,'Raw Data'!K34="Delete"),"",'Raw Data'!K34) | L12: =R12 -> Available | M12: =IF(A12="","",IF(OR(AWReleaseNum>=A12,AWReleaseNum=0),"Available","Not Supported")) -> Available | N12: =IF(A12="","",IF(TcRelease="Any","Available",IF(OR(AND(TcReleaseNum>=VLOOKUP(AWReleaseNum,MinVerInfo,3,FALSE),TcReleaseNum<=VLOOKUP(AWReleaseNum,MinVerInfo,4,FALSE)),AND(TcReleaseNum>=VLOOKUP(AWReleaseNum,MinVerInfo,5,FALSE),TcReleaseNum<=VLOOKUP(AWReleaseNum,MinVerInfo,6,FALSE))),"Available","Not Supported"))) -> Available | O12: =IF(TcReleaseNum<P12,"Not Supported","Available") -> Available | P12: {=_xlfn.SWITCH(TcBaseVer, 14, K12, 13, J12, 12, I12, 11, IFERROR(VLOOKUP(H12,Table2[#All],3,FALSE),"N/A"),0)} -> 0 | Q12: =IF(TcBaseVer=0,M12,IF(AND(N12="Available",M12="Available",O12="Available"),"Available",IF(M12="","","Not Supported"))) -> Available | R12: =IF(A12>=AWCurrentRel, "Future",Q12) -> Available | S12: =HYPERLINK(U12,T12) -> Not Available | T12: =IFERROR(VLOOKUP(CONCATENATE($B12,"_",$A12),Table4[#All],5,FALSE),"Not Available") -> Not Available | U12: =IFERROR(VLOOKUP(CONCATENATE(B12,"_",A12),Table4[#All],6,FALSE),"")
A13: =IF(OR('Raw Data'!A35=0,'Raw Data'!A35="Delete"),"",'Raw Data'!A35) -> 2 | B13: =IF(OR('Raw Data'!B35=0,'Raw Data'!B35="Delete"),"",'Raw Data'!B35) -> Foundation | C13: =IF(OR('Raw Data'!C35=0,'Raw Data'!C35="Delete"),"",'Raw Data'!C35) -> Usability | D13: =IF(OR('Raw Data'!D35=0,'Raw Data'!D35="Delete"),"",'Raw Data'!D35) -> Platform - Active Workspace Framework - Usability | E13: =IF(OR('Raw Data'!E35=0,'Raw Data'!E35="Delete"),"",'Raw Data'!E35) -> Stacked Commands | F13: {=_xlfn.SWITCH(ROUND(VLOOKUP(A13,Table1[#All],3),0),11,H13,12,I13,13,J13,14,K13,"N/A")} -> 13 | G13: {=_xlfn.SWITCH(ROUND(VLOOKUP(A13,Table1[#All],5),0),11,H13,12,I13,13,J13,14,K13,"N/A")} -> 14 | H13: =IF(OR('Raw Data'!H35=0,'Raw Data'!H35="Delete"),"",'Raw Data'!H35) -> 13 | I13: =IF(OR('Raw Data'!I35=0,'Raw Data'!I35="Delete"),"",'Raw Data'!I35) -> 14 | J13: =IF(OR('Raw Data'!J35=0,'Raw Data'!J35="Delete"),"",'Raw Data'!J35) | K13: =IF(OR('Raw Data'!K35=0,'Raw Data'!K35="Delete"),"",'Raw Data'!K35) | L13: =R13 -> Available | M13: =IF(A13="","",IF(OR(AWReleaseNum>=A13,AWReleaseNum=0),"Available","Not Supported")) -> Available | N13: =IF(A13="","",IF(TcRelease="Any","Available",IF(OR(AND(TcReleaseNum>=VLOOKUP(AWReleaseNum,MinVerInfo,3,FALSE),TcReleaseNum<=VLOOKUP(AWReleaseNum,MinVerInfo,4,FALSE)),AND(TcReleaseNum>=VLOOKUP(AWReleaseNum,MinVerInfo,5,FALSE),TcReleaseNum<=VLOOKUP(AWReleaseNum,MinVerInfo,6,FALSE))),"Available","Not Supported"))) -> Available | O13: =IF(TcReleaseNum<P13,"Not Supported","Available") -> Available | P13: {=_xlfn.SWITCH(TcBaseVer, 14, K13, 13, J13, 12, I13, 11, IFERROR(VLOOKUP(H13,Table2[#All],3,FALSE),"N/A"),0)} -> 0 | Q13: =IF(TcBaseVer=0,M13,IF(AND(N13="Available",M13="Available",O13="Available"),"Available",IF(M13="","","Not Supported"))) -> Available | R13: =IF(A13>=AWCurrentRel, "Future",Q13) -> Available | S13: =HYPERLINK(U13,T13) -> Not Available | T13: =IFERROR(VLOOKUP(CONCATENATE($B13,"_",$A13),Table4[#All],5,FALSE),"Not Available") -> Not Available | U13: =IFERROR(VLOOKUP(CONCATENATE(B13,"_",A13),Table4[#All],6,FALSE),"")
A14: =IF(OR('Raw Data'!A36=0,'Raw Data'!A36="Delete"),"",'Raw Data'!A36) -> 2 | B14: =IF(OR('Raw Data'!B36=0,'Raw Data'!B36="Delete"),"",'Raw Data'!B36) -> Foundation | C14: =IF(OR('Raw Data'!C36=0,'Raw Data'!C36="Delete"),"",'Raw Data'!C36) -> Usability | D14: =IF(OR('Raw Data'!D36=0,'Raw Data'!D36="Delete"),"",'Raw Data'!D36) -> Platform - Active Workspace Framework - Usability | E14: =IF(OR('Raw Data'!E36=0,'Raw Data'!E36="Delete"),"",'Raw Data'!E36) -> Property Editing | F14: {=_xlfn.SWITCH(ROUND(VLOOKUP(A14,Table1[#All],3),0),11,H14,12,I14,13,J14,14,K14,"N/A")} -> 13 | G14: {=_xlfn.SWITCH(ROUND(VLOOKUP(A14,Table1[#All],5),0),11,H14,12,I14,13,J14,14,K14,"N/A")} -> 14 | H14: =IF(OR('Raw Data'!H36=0,'Raw Data'!H36="Delete"),"",'Raw Data'!H36) -> 13 | I14: =IF(OR('Raw Data'!I36=0,'Raw Data'!I36="Delete"),"",'Raw Data'!I36) -> 14 | J14: =IF(OR('Raw Data'!J36=0,'Raw Data'!J36="Delete"),"",'Raw Data'!J36) | K14: =IF(OR('Raw Data'!K36=0,'Raw Data'!K36="Delete"),"",'Raw Data'!K36) | L14: =R14 -> Available | M14: =IF(A14="","",IF(OR(AWReleaseNum>=A14,AWReleaseNum=0),"Available","Not Supported")) -> Available | N14: =IF(A14="","",IF(TcRelease="Any","Available",IF(OR(AND(TcReleaseNum>=VLOOKUP(AWReleaseNum,MinVerInfo,3,FALSE),TcReleaseNum<=VLOOKUP(AWReleaseNum,MinVerInfo,4,FALSE)),AND(TcReleaseNum>=VLOOKUP(AWReleaseNum,MinVerInfo,5,FALSE),TcReleaseNum<=VLOOKUP(AWReleaseNum,MinVerInfo,6,FALSE))),"Available","Not Supported"))) -> Available | O14: =IF(TcReleaseNum<P14,"Not Supported","Available") -> Available | P14: {=_xlfn.SWITCH(TcBaseVer, 14, K14, 13, J14, 12, I14, 11, IFERROR(VLOOKUP(H14,Table2[#All],3,FALSE),"N/A"),0)} -> 0 | Q14: =IF(TcBaseVer=0,M14,IF(AND(N14="Available",M14="Available",O14="Available"),"Available",IF(M14="","","Not Supported"))) -> Available | R14: =IF(A14>=AWCurrentRel, "Future",Q14) -> Available | S14: =HYPERLINK(U14,T14) -> Not Available | T14: =IFERROR(VLOOKUP(CONCATENATE($B14,"_",$A14),Table4[#All],5,FALSE),"Not Available") -> Not Available | U14: =IFERROR(VLOOKUP(CONCATENATE(B14,"_",A14),Table4[#All],6,FALSE),"")
A15: =IF(OR('Raw Data'!A37=0,'Raw Data'!A37="Delete"),"",'Raw Data'!A37) -> 2 | B15: =IF(OR('Raw Data'!B37=0,'Raw Data'!B37="Delete"),"",'Raw Data'!B37) -> Foundation | C15: =IF(OR('Raw Data'!C37=0,'Raw Data'!C37="Delete"),"",'Raw Data'!C37) -> Usability | D15: =IF(OR('Raw Data'!D37=0,'Raw Data'!D37="Delete"),"",'Raw Data'!D37) -> Platform - Active Workspace Framework - Usability | E15: =IF(OR('Raw Data'!E37=0,'Raw Data'!E37="Delete"),"",'Raw Data'!E37) -> Open Rich Client on selected Object | F15: {=_xlfn.SWITCH(ROUND(VLOOKUP(A15,Table1[#All],3),0),11,H15,12,I15,13,J15,14,K15,"N/A")} -> 13 | G15: {=_xlfn.SWITCH(ROUND(VLOOKUP(A15,Table1[#All],5),0),11,H15,12,I15,13,J15,14,K15,"N/A")} -> 14 | H15: =IF(OR('Raw Data'!H37=0,'Raw Data'!H37="Delete"),"",'Raw Data'!H37) -> 13 | I15: =IF(OR('Raw Data'!I37=0,'Raw Data'!I37="Delete"),"",'Raw Data'!I37) -> 14 | J15: =IF(OR('Raw Data'!J37=0,'Raw Data'!J37="Delete"),"",'Raw Data'!J37) | K15: =IF(OR('Raw Data'!K37=0,'Raw Data'!K37="Delete"),"",'Raw Data'!K37) | L15: =R15 -> Available | M15: =IF(A15="","",IF(OR(AWReleaseNum>=A15,AWReleaseNum=0),"Available","Not Supported")) -> Available | N15: =IF(A15="","",IF(TcRelease="Any","Available",IF(OR(AND(TcReleaseNum>=VLOOKUP(AWReleaseNum,MinVerInfo,3,FALSE),TcReleaseNum<=VLOOKUP(AWReleaseNum,MinVerInfo,4,FALSE)),AND(TcReleaseNum>=VLOOKUP(AWReleaseNum,MinVerInfo,5,FALSE),TcReleaseNum<=VLOOKUP(AWReleaseNum,MinVerInfo,6,FALSE))),"Available","Not Supported"))) -> Available | O15: =IF(TcReleaseNum<P15,"Not Supported","Available") -> Available | P15: {=_xlfn.SWITCH(TcBaseVer, 14, K15, 13, J15, 12, I15, 11, IFERROR(VLOOKUP(H15,Table2[#All],3,FALSE),"N/A"),0)} -> 0 | Q15: =IF(TcBaseVer=0,M15,IF(AND(N15="Available",M15="Available",O15="Available"),"Available",IF(M15="","","Not Supported"))) -> Available | R15: =IF(A15>=AWCurrentRel, "Future",Q15) -> Available | S15: =HYPERLINK(U15,T15) -> Not Available | T15: =IFERROR(VLOOKUP(CONCATENATE($B15,"_",$A15),Table4[#All],5,FALSE),"Not Available") -> Not Available | U15: =IFERROR(VLOOKUP(CONCATENATE(B15,"_",A15),Table4[#All],6,FALSE),"")
A16: =IF(OR('Raw Data'!A38=0,'Raw Data'!A38="Delete"),"",'Raw Data'!A38) -> 2 | B16: =IF(OR('Raw Data'!B38=0,'Raw Data'!B38="Delete"),"",'Raw Data'!B38) -> Foundation | C16: =IF(OR('Raw Data'!C38=0,'Raw Data'!C38="Delete"),"",'Raw Data'!C38) -> Usability | D16: =IF(OR('Raw Data'!D38=0,'Raw Data'!D38="Delete"),"",'Raw Data'!D38) -> Platform - Active Workspace Framework - Usability | E16: =IF(OR('Raw Data'!E38=0,'Raw Data'!E38="Delete"),"",'Raw Data'!E38) -> Object Summary View | F16: {=_xlfn.SWITCH(ROUND(VLOOKUP(A16,Table1[#All],3),0),11,H16,12,I16,13,J16,14,K16,"N/A")} -> 13 | G16: {=_xlfn.SWITCH(ROUND(VLOOKUP(A16,Table1[#All],5),0),11,H16,12,I16,13,J16,14,K16,"N/A")} -> 14 | H16: =IF(OR('Raw Data'!H38=0,'Raw Data'!H38="Delete"),"",'Raw Data'!H38) -> 13 | I16: =IF(OR('Raw Data'!I38=0,'Raw Data'!I38="Delete"),"",'Raw Data'!I38) -> 14 | J16: =IF(OR('Raw Data'!J38=0,'Raw Data'!J38="Delete"),"",'Raw Data'!J38) | K16: =IF(OR('Raw Data'!K38=0,'Raw Data'!K38="Delete"),"",'Raw Data'!K38) | L16: =R16 -> Available | M16: =IF(A16="","",IF(OR(AWReleaseNum>=A16,AWReleaseNum=0),"Available","Not Supported")) -> Available | N16: =IF(A16="","",IF(TcRelease="Any","Available",IF(OR(AND(TcReleaseNum>=VLOOKUP(AWReleaseNum,MinVerInfo,3,FALSE),TcReleaseNum<=VLOOKUP(AWReleaseNum,MinVerInfo,4,FALSE)),AND(TcReleaseNum>=VLOOKUP(AWReleaseNum,MinVerInfo,5,FALSE),TcReleaseNum<=VLOOKUP(AWReleaseNum,MinVerInfo,6,FALSE))),"Available","Not Supported"))) -> Available | O16: =IF(TcReleaseNum<P16,"Not Supported","Available") -> Available | P16: {=_xlfn.SWITCH(TcBaseVer, 14, K16, 13, J16, 12, I16, 11, IFERROR(VLOOKUP(H16,Table2[#All],3,FALSE),"N/A"),0)} -> 0 | Q16: =IF(TcBaseVer=0,M16,IF(AND(N16="Available",M16="Available",O16="Available"),"Available",IF(M16="","","Not Supported"))) -> Available | R16: =IF(A16>=AWCurrentRel, "Future",Q16) -> Available | S16: =HYPERLINK(U16,T16) -> Not Available | T16: =IFERROR(VLOOKUP(CONCATENATE($B16,"_",$A16),Table4[#All],5,FALSE),"Not Available") -> Not Available | U16: =IFERROR(VLOOKUP(CONCATENATE(B16,"_",A16),Table4[#All],6,FALSE),"")
A17: =IF(OR('Raw Data'!A39=0,'Raw Data'!A39="Delete"),"",'Raw Data'!A39) -> 2 | B17: =IF(OR('Raw Data'!B39=0,'Raw Data'!B39="Delete"),"",'Raw Data'!B39) -> Foundation | C17: =IF(OR('Raw Data'!C39=0,'Raw Data'!C39="Delete"),"",'Raw Data'!C39) -> Usability | D17: =IF(OR('Raw Data'!D39=0,'Raw Data'!D39="Delete"),"",'Raw Data'!D39) -> Platform - Active Workspace Framework - Usability | E17: =IF(OR('Raw Data'!E39=0,'Raw Data'!E39="Delete"),"",'Raw Data'!E39) -> Multiple smart tabs | F17: {=_xlfn.SWITCH(ROUND(VLOOKUP(A17,Table1[#All],3),0),11,H17,12,I17,13,J17,14,K17,"N/A")} -> 13 | G17: {=_xlfn.SWITCH(ROUND(VLOOKUP(A17,Table1[#All],5),0),11,H17,12,I17,13,J17,14,K17,"N/A")} -> 14 | H17: =IF(OR('Raw Data'!H39=0,'Raw Data'!H39="Delete"),"",'Raw Data'!H39) -> 13 | I17: =IF(OR('Raw Data'!I39=0,'Raw Data'!I39="Delete"),"",'Raw Data'!I39) -> 14 | J17: =IF(OR('Raw Data'!J39=0,'Raw Data'!J39="Delete"),"",'Raw Data'!J39) | K17: =IF(OR('Raw Data'!K39=0,'Raw Data'!K39="Delete"),"",'Raw Data'!K39) | L17: =R17 -> Available | M17: =IF(A17="","",IF(OR(AWReleaseNum>=A17,AWReleaseNum=0),"Available","Not Supported")) -> Available | N17: =IF(A17="","",IF(TcRelease="Any","Available",IF(OR(AND(TcReleaseNum>=VLOOKUP(AWReleaseNum,MinVerInfo,3,FALSE),TcReleaseNum<=VLOOKUP(AWReleaseNum,MinVerInfo,4,FALSE)),AND(TcReleaseNum>=VLOOKUP(AWReleaseNum,MinVerInfo,5,FALSE),TcReleaseNum<=VLOOKUP(AWReleaseNum,MinVerInfo,6,FALSE))),"Available","Not Supported"))) -> Available | O17: =IF(TcReleaseNum<P17,"Not Supported","Available") -> Available | P17: {=_xlfn.SWITCH(TcBaseVer, 14, K17, 13, J17, 12, I17, 11, IFERROR(VLOOKUP(H17,Table2[#All],3,FALSE),"N/A"),0)} -> 0 | Q17: =IF(TcBaseVer=0,M17,IF(AND(N17="Available",M17="Available",O17="Available"),"Available",IF(M17="","","Not Supported"))) -> Available | R17: =IF(A17>=AWCurrentRel, "Future",Q17) -> Available | S17: =HYPERLINK(U17,T17) -> Not Available | T17: =IFERROR(VLOOKUP(CONCATENATE($B17,"_",$A17),Table4[#All],5,FALSE),"Not Available") -> Not Available | U17: =IFERROR(VLOOKUP(CONCATENATE(B17,"_",A17),Table4[#All],6,FALSE),"")
... A28: =IF(OR('Raw Data'!A50=0,'Raw Data'!A50="Delete"),"",'Raw Data'!A50) -> 2 | B28: =IF(OR('Raw Data'!B50=0,'Raw Data'!B50="Delete"),"",'Raw Data'!B50) -> Plan | C28: =IF(OR('Raw Data'!C50=0,'Raw Data'!C50="Delete"),"",'Raw Data'!C50) -> Requirements | D28: =IF(OR('Raw Data'!D50=0,'Raw Data'!D50="Delete"),"",'Raw Data'!D50) -> Requirements Management | E28: =IF(OR('Raw Data'!E50=0,'Raw Data'!E50="Delete"),"",'Raw Data'!E50) -> Traceability tracking | F28: {=_xlfn.SWITCH(ROUND(VLOOKUP(A28,Table1[#All],3),0),11,H28,12,I28,13,J28,14,K28,"N/A")} -> 13 | G28: {=_xlfn.SWITCH(ROUND(VLOOKUP(A28,Table1[#All],5),0),11,H28,12,I28,13,J28,14,K28,"N/A")} -> 14 | H28: =IF(OR('Raw Data'!H50=0,'Raw Data'!H50="Delete"),"",'Raw Data'!H50) -> 13 | I28: =IF(OR('Raw Data'!I50=0,'Raw Data'!I50="Delete"),"",'Raw Data'!I50) -> 14 | J28: =IF(OR('Raw Data'!J50=0,'Raw Data'!J50="Delete"),"",'Raw Data'!J50) | K28: =IF(OR('Raw Data'!K50=0,'Raw Data'!K50="Delete"),"",'Raw Data'!K50) | L28: =R28 -> Available | M28: =IF(A28="","",IF(OR(AWReleaseNum>=A28,AWReleaseNum=0),"Available","Not Supported")) -> Available | N28: =IF(A28="","",IF(TcRelease="Any","Available",IF(OR(AND(TcReleaseNum>=VLOOKUP(AWReleaseNum,MinVerInfo,3,FALSE),TcReleaseNum<=VLOOKUP(AWReleaseNum,MinVerInfo,4,FALSE)),AND(TcReleaseNum>=VLOOKUP(AWReleaseNum,MinVerInfo,5,FALSE),TcReleaseNum<=VLOOKUP(AWReleaseNum,MinVerInfo,6,FALSE))),"Available","Not Supported"))) -> Available | O28: =IF(TcReleaseNum<P28,"Not Supported","Available") -> Available | P28: {=_xlfn.SWITCH(TcBaseVer, 14, K28, 13, J28, 12, I28, 11, IFERROR(VLOOKUP(H28,Table2[#All],3,FALSE),"N/A"),0)} -> 0 | Q28: =IF(TcBaseVer=0,M28,IF(AND(N28="Available",M28="Available",O28="Available"),"Available",IF(M28="","","Not Supported"))) -> Available | R28: =IF(A28>=AWCurrentRel, "Future",Q28) -> Available | S28: =HYPERLINK(U28,T28) -> Not Available | T28: =IFERROR(VLOOKUP(CONCATENATE($B28,"_",$A28),Table4[#All],5,FALSE),"Not Available") -> Not Available | U28: =IFERROR(VLOOKUP(CONCATENATE(B28,"_",A28),Table4[#All],6,FALSE),"")
A29: =IF(OR('Raw Data'!A4=0,'Raw Data'!A4="Delete"),"",'Raw Data'!A4) -> 2 | B29: =IF(OR('Raw Data'!B4=0,'Raw Data'!B4="Delete"),"",'Raw Data'!B4) -> Deliver | C29: =IF(OR('Raw Data'!C4=0,'Raw Data'!C4="Delete"),"",'Raw Data'!C4) -> Analytics | D29: =IF(OR('Raw Data'!D4=0,'Raw Data'!D4="Delete"),"",'Raw Data'!D4) -> Search and Analytics - Search | E29: =IF(OR('Raw Data'!E4=0,'Raw Data'!E4="Delete"),"",'Raw Data'!E4) -> Breadcrumb | F29: {=_xlfn.SWITCH(ROUND(VLOOKUP(A29,Table1[#All],3),0),11,H29,12,I29,13,J29,14,K29,"N/A")} -> 13 | G29: {=_xlfn.SWITCH(ROUND(VLOOKUP(A29,Table1[#All],5),0),11,H29,12,I29,13,J29,14,K29,"N/A")} -> 14 | H29: =IF(OR('Raw Data'!H4=0,'Raw Data'!H4="Delete"),"",'Raw Data'!H4) -> 13 | I29: =IF(OR('Raw Data'!I4=0,'Raw Data'!I4="Delete"),"",'Raw Data'!I4) -> 14 | J29: =IF(OR('Raw Data'!J4=0,'Raw Data'!J4="Delete"),"",'Raw Data'!J4) | K29: =IF(OR('Raw Data'!K4=0,'Raw Data'!K4="Delete"),"",'Raw Data'!K4) | L29: =R29 -> Available | M29: =IF(A29="","",IF(OR(AWReleaseNum>=A29,AWReleaseNum=0),"Available","Not Supported")) -> Available | N29: =IF(A29="","",IF(TcRelease="Any","Available",IF(OR(AND(TcReleaseNum>=VLOOKUP(AWReleaseNum,MinVerInfo,3,FALSE),TcReleaseNum<=VLOOKUP(AWReleaseNum,MinVerInfo,4,FALSE)),AND(TcReleaseNum>=VLOOKUP(AWReleaseNum,MinVerInfo,5,FALSE),TcReleaseNum<=VLOOKUP(AWReleaseNum,MinVerInfo,6,FALSE))),"Available","Not Supported"))) -> Available | O29: =IF(TcReleaseNum<P29,"Not Supported","Available") -> Available | P29: {=_xlfn.SWITCH(TcBaseVer, 14, K29, 13, J29, 12, I29, 11, IFERROR(VLOOKUP(H29,Table2[#All],3,FALSE),"N/A"),0)} -> 0 | Q29: =IF(TcBaseVer=0,M29,IF(AND(N29="Available",M29="Available",O29="Available"),"Available",IF(M29="","","Not Supported"))) -> Available | R29: =IF(A29>=AWCurrentRel, "Future",Q29) -> Available | S29: =HYPERLINK(U29,T29) -> Not Available | T29: =IFERROR(VLOOKUP(CONCATENATE($B29,"_",$A29),Table4[#All],5,FALSE),"Not Available") -> Not Available | U29: =IFERROR(VLOOKUP(CONCATENATE(B29,"_",A29),Table4[#All],6,FALSE),"")
A30: =IF(OR('Raw Data'!A5=0,'Raw Data'!A5="Delete"),"",'Raw Data'!A5) -> 2 | B30: =IF(OR('Raw Data'!B5=0,'Raw Data'!B5="Delete"),"",'Raw Data'!B5) -> Deliver | C30: =IF(OR('Raw Data'!C5=0,'Raw Data'!C5="Delete"),"",'Raw Data'!C5) -> Analytics | D30: =IF(OR('Raw Data'!D5=0,'Raw Data'!D5="Delete"),"",'Raw Data'!D5) -> Search and Analytics - Search | E30: =IF(OR('Raw Data'!E5=0,'Raw Data'!E5="Delete"),"",'Raw Data'!E5) -> Filter results | F30: {=_xlfn.SWITCH(ROUND(VLOOKUP(A30,Table1[#All],3),0),11,H30,12,I30,13,J30,14,K30,"N/A")} -> 13 | G30: {=_xlfn.SWITCH(ROUND(VLOOKUP(A30,Table1[#All],5),0),11,H30,12,I30,13,J30,14,K30,"N/A")} -> 14 | H30: =IF(OR('Raw Data'!H5=0,'Raw Data'!H5="Delete"),"",'Raw Data'!H5) -> 13 | I30: =IF(OR('Raw Data'!I5=0,'Raw Data'!I5="Delete"),"",'Raw Data'!I5) -> 14 | J30: =IF(OR('Raw Data'!J5=0,'Raw Data'!J5="Delete"),"",'Raw Data'!J5) | K30: =IF(OR('Raw Data'!K5=0,'Raw Data'!K5="Delete"),"",'Raw Data'!K5) | L30: =R30 -> Available | M30: =IF(A30="","",IF(OR(AWReleaseNum>=A30,AWReleaseNum=0),"Available","Not Supported")) -> Available | N30: =IF(A30="","",IF(TcRelease="Any","Available",IF(OR(AND(TcReleaseNum>=VLOOKUP(AWReleaseNum,MinVerInfo,3,FALSE),TcReleaseNum<=VLOOKUP(AWReleaseNum,MinVerInfo,4,FALSE)),AND(TcReleaseNum>=VLOOKUP(AWReleaseNum,MinVerInfo,5,FALSE),TcReleaseNum<=VLOOKUP(AWReleaseNum,MinVerInfo,6,FALSE))),"Available","Not Supported"))) -> Available | O30: =IF(TcReleaseNum<P30,"Not Supported","Available") -> Available | P30: {=_xlfn.SWITCH(TcBaseVer, 14, K30, 13, J30, 12, I30, 11, IFERROR(VLOOKUP(H30,Table2[#All],3,FALSE),"N/A"),0)} -> 0 | Q30: =IF(TcBaseVer=0,M30,IF(AND(N30="Available",M30="Available",O30="Available"),"Available",IF(M30="","","Not Supported"))) -> Available | R30: =IF(A30>=AWCurrentRel, "Future",Q30) -> Available | S30: =HYPERLINK(U30,T30) -> Not Available | T30: =IFERROR(VLOOKUP(CONCATENATE($B30,"_",$A30),Table4[#All],5,FALSE),"Not Available") -> Not Available | U30: =IFERROR(VLOOKUP(CONCATENATE(B30,"_",A30),Table4[#All],6,FALSE),"")
A31: =IF(OR('Raw Data'!A6=0,'Raw Data'!A6="Delete"),"",'Raw Data'!A6) -> 2 | B31: =IF(OR('Raw Data'!B6=0,'Raw Data'!B6="Delete"),"",'Raw Data'!B6) -> Deliver | C31: =IF(OR('Raw Data'!C6=0,'Raw Data'!C6="Delete"),"",'Raw Data'!C6) -> Analytics | D31: =IF(OR('Raw Data'!D6=0,'Raw Data'!D6="Delete"),"",'Raw Data'!D6) -> Search and Analytics - Search | E31: =IF(OR('Raw Data'!E6=0,'Raw Data'!E6="Delete"),"",'Raw Data'!E6) -> Relevance Ranking (AND, Modification date, attribute vs. FTS, specific attribute priority) | F31: {=_xlfn.SWITCH(ROUND(VLOOKUP(A31,Table1[#All],3),0),11,H31,12,I31,13,J31,14,K31,"N/A")} -> 13 | G31: {=_xlfn.SWITCH(ROUND(VLOOKUP(A31,Table1[#All],5),0),11,H31,12,I31,13,J31,14,K31,"N/A")} -> 14 | H31: =IF(OR('Raw Data'!H6=0,'Raw Data'!H6="Delete"),"",'Raw Data'!H6) -> 13 | I31: =IF(OR('Raw Data'!I6=0,'Raw Data'!I6="Delete"),"",'Raw Data'!I6) -> 14 | J31: =IF(OR('Raw Data'!J6=0,'Raw Data'!J6="Delete"),"",'Raw Data'!J6) | K31: =IF(OR('Raw Data'!K6=0,'Raw Data'!K6="Delete"),"",'Raw Data'!K6) | L31: =R31 -> Available | M31: =IF(A31="","",IF(OR(AWReleaseNum>=A31,AWReleaseNum=0),"Available","Not Supported")) -> Available | N31: =IF(A31="","",IF(TcRelease="Any","Available",IF(OR(AND(TcReleaseNum>=VLOOKUP(AWReleaseNum,MinVerInfo,3,FALSE),TcReleaseNum<=VLOOKUP(AWReleaseNum,MinVerInfo,4,FALSE)),AND(TcReleaseNum>=VLOOKUP(AWReleaseNum,MinVerInfo,5,FALSE),TcReleaseNum<=VLOOKUP(AWReleaseNum,MinVerInfo,6,FALSE))),"Available","Not Supported"))) -> Available | O31: =IF(TcReleaseNum<P31,"Not Supported","Available") -> Available | P31: {=_xlfn.SWITCH(TcBaseVer, 14, K31, 13, J31, 12, I31, 11, IFERROR(VLOOKUP(H31,Table2[#All],3,FALSE),"N/A"),0)} -> 0 | Q31: =IF(TcBaseVer=0,M31,IF(AND(N31="Available",M31="Available",O31="Available"),"Available",IF(M31="","","Not Supported"))) -> Available | R31: =IF(A31>=AWCurrentRel, "Future",Q31) -> Available | S31: =HYPERLINK(U31,T31) -> Not Available | T31: =IFERROR(VLOOKUP(CONCATENATE($B31,"_",$A31),Table4[#All],5,FALSE),"Not Available") -> Not Available | U31: =IFERROR(VLOOKUP(CONCATENATE(B31,"_",A31),Table4[#All],6,FALSE),"")
A32: =IF(OR('Raw Data'!A7=0,'Raw Data'!A7="Delete"),"",'Raw Data'!A7) -> 2 | B32: =IF(OR('Raw Data'!B7=0,'Raw Data'!B7="Delete"),"",'Raw Data'!B7) -> Deliver | C32: =IF(OR('Raw Data'!C7=0,'Raw Data'!C7="Delete"),"",'Raw Data'!C7) -> Analytics | D32: =IF(OR('Raw Data'!D7=0,'Raw Data'!D7="Delete"),"",'Raw Data'!D7) -> Search and Analytics - Search | E32: =IF(OR('Raw Data'!E7=0,'Raw Data'!E7="Delete"),"",'Raw Data'!E7) -> Accurate results based on access rules | F32: {=_xlfn.SWITCH(ROUND(VLOOKUP(A32,Table1[#All],3),0),11,H32,12,I32,13,J32,14,K32,"N/A")} -> 13 | G32: {=_xlfn.SWITCH(ROUND(VLOOKUP(A32,Table1[#All],5),0),11,H32,12,I32,13,J32,14,K32,"N/A")} -> 14 | H32: =IF(OR('Raw Data'!H7=0,'Raw Data'!H7="Delete"),"",'Raw Data'!H7) -> 13 | I32: =IF(OR('Raw Data'!I7=0,'Raw Data'!I7="Delete"),"",'Raw Data'!I7) -> 14 | J32: =IF(OR('Raw Data'!J7=0,'Raw Data'!J7="Delete"),"",'Raw Data'!J7) | K32: =IF(OR('Raw Data'!K7=0,'Raw Data'!K7="Delete"),"",'Raw Data'!K7) | L32: =R32 -> Available | M32: =IF(A32="","",IF(OR(AWReleaseNum>=A32,AWReleaseNum=0),"Available","Not Supported")) -> Available | N32: =IF(A32="","",IF(TcRelease="Any","Available",IF(OR(AND(TcReleaseNum>=VLOOKUP(AWReleaseNum,MinVerInfo,3,FALSE),TcReleaseNum<=VLOOKUP(AWReleaseNum,MinVerInfo,4,FALSE)),AND(TcReleaseNum>=VLOOKUP(AWReleaseNum,MinVerInfo,5,FALSE),TcReleaseNum<=VLOOKUP(AWReleaseNum,MinVerInfo,6,FALSE))),"Available","Not Supported"))) -> Available | O32: =IF(TcReleaseNum<P32,"Not Supported","Available") -> Available | P32: {=_xlfn.SWITCH(TcBaseVer, 14, K32, 13, J32, 12, I32, 11, IFERROR(VLOOKUP(H32,Table2[#All],3,FALSE),"N/A"),0)} -> 0 | Q32: =IF(TcBaseVer=0,M32,IF(AND(N32="Available",M32="Available",O32="Available"),"Available",IF(M32="","","Not Supported"))) -> Available | R32: =IF(A32>=AWCurrentRel, "Future",Q32) -> Available | S32: =HYPERLINK(U32,T32) -> Not Available | T32: =IFERROR(VLOOKUP(CONCATENATE($B32,"_",$A32),Table4[#All],5,FALSE),"Not Available") -> Not Available | U32: =IFERROR(VLOOKUP(CONCATENATE(B32,"_",A32),Table4[#All],6,FALSE),"")
A33: =IF(OR('Raw Data'!A8=0,'Raw Data'!A8="Delete"),"",'Raw Data'!A8) -> 2 | B33: =IF(OR('Raw Data'!B8=0,'Raw Data'!B8="Delete"),"",'Raw Data'!B8) -> Deliver | C33: =IF(OR('Raw Data'!C8=0,'Raw Data'!C8="Delete"),"",'Raw Data'!C8) -> Analytics | D33: =IF(OR('Raw Data'!D8=0,'Raw Data'!D8="Delete"),"",'Raw Data'!D8) -> Search and Analytics - Search | E33: =IF(OR('Raw Data'!E8=0,'Raw Data'!E8="Delete"),"",'Raw Data'!E8) -> Aggregate Search - Preproduction support for searching from additional repositories | F33: {=_xlfn.SWITCH(ROUND(VLOOKUP(A33,Table1[#All],3),0),11,H33,12,I33,13,J33,14,K33,"N/A")} -> 13 | G33: {=_xlfn.SWITCH(ROUND(VLOOKUP(A33,Table1[#All],5),0),11,H33,12,I33,13,J33,14,K33,"N/A")} -> 14 | H33: =IF(OR('Raw Data'!H8=0,'Raw Data'!H8="Delete"),"",'Raw Data'!H8) -> 13 | I33: =IF(OR('Raw Data'!I8=0,'Raw Data'!I8="Delete"),"",'Raw Data'!I8) -> 14 | J33: =IF(OR('Raw Data'!J8=0,'Raw Data'!J8="Delete"),"",'Raw Data'!J8) | K33: =IF(OR('Raw Data'!K8=0,'Raw Data'!K8="Delete"),"",'Raw Data'!K8) | L33: =R33 -> Available | M33: =IF(A33="","",IF(OR(AWReleaseNum>=A33,AWReleaseNum=0),"Available","Not Supported")) -> Available | N33: =IF(A33="","",IF(TcRelease="Any","Available",IF(OR(AND(TcReleaseNum>=VLOOKUP(AWReleaseNum,MinVerInfo,3,FALSE),TcReleaseNum<=VLOOKUP(AWReleaseNum,MinVerInfo,4,FALSE)),AND(TcReleaseNum>=VLOOKUP(AWReleaseNum,MinVerInfo,5,FALSE),TcReleaseNum<=VLOOKUP(AWReleaseNum,MinVerInfo,6,FALSE))),"Available","Not Supported"))) -> Available | O33: =IF(TcReleaseNum<P33,"Not Supported","Available") -> Available | P33: {=_xlfn.SWITCH(TcBaseVer, 14, K33, 13, J33, 12, I33, 11, IFERROR(VLOOKUP(H33,Table2[#All],3,FALSE),"N/A"),0)} -> 0 | Q33: =IF(TcBaseVer=0,M33,IF(AND(N33="Available",M33="Available",O33="Available"),"Available",IF(M33="","","Not Supported"))) -> Available | R33: =IF(A33>=AWCurrentRel, "Future",Q33) -> Available | S33: =HYPERLINK(U33,T33) -> Not Available | T33: =IFERROR(VLOOKUP(CONCATENATE($B33,"_",$A33),Table4[#All],5,FALSE),"Not Available") -> Not Available | U33: =IFERROR(VLOOKUP(CONCATENATE(B33,"_",A33),Table4[#All],6,FALSE),"")
A34: =IF(OR('Raw Data'!A9=0,'Raw Data'!A9="Delete"),"",'Raw Data'!A9) -> 2 | B34: =IF(OR('Raw Data'!B9=0,'Raw Data'!B9="Delete"),"",'Raw Data'!B9) -> Deliver | C34: =IF(OR('Raw Data'!C9=0,'Raw Data'!C9="Delete"),"",'Raw Data'!C9) -> Analytics | D34: =IF(OR('Raw Data'!D9=0,'Raw Data'!D9="Delete"),"",'Raw Data'!D9) -> Search and Analytics - Search | E34: =IF(OR('Raw Data'!E9=0,'Raw Data'!E9="Delete"),"",'Raw Data'!E9) -> Searching on file contents as well as Business Objects Metadata | F34: {=_xlfn.SWITCH(ROUND(VLOOKUP(A34,Table1[#All],3),0),11,H34,12,I34,13,J34,14,K34,"N/A")} -> 13 | G34: {=_xlfn.SWITCH(ROUND(VLOOKUP(A34,Table1[#All],5),0),11,H34,12,I34,13,J34,14,K34,"N/A")} -> 14 | H34: =IF(OR('Raw Data'!H9=0,'Raw Data'!H9="Delete"),"",'Raw Data'!H9) -> 13 | I34: =IF(OR('Raw Data'!I9=0,'Raw Data'!I9="Delete"),"",'Raw Data'!I9) -> 14 | J34: =IF(OR('Raw Data'!J9=0,'Raw Data'!J9="Delete"),"",'Raw Data'!J9) | K34: =IF(OR('Raw Data'!K9=0,'Raw Data'!K9="Delete"),"",'Raw Data'!K9) | L34: =R34 -> Available | M34: =IF(A34="","",IF(OR(AWReleaseNum>=A34,AWReleaseNum=0),"Available","Not Supported")) -> Available | N34: =IF(A34="","",IF(TcRelease="Any","Available",IF(OR(AND(TcReleaseNum>=VLOOKUP(AWReleaseNum,MinVerInfo,3,FALSE),TcReleaseNum<=VLOOKUP(AWReleaseNum,MinVerInfo,4,FALSE)),AND(TcReleaseNum>=VLOOKUP(AWReleaseNum,MinVerInfo,5,FALSE),TcReleaseNum<=VLOOKUP(AWReleaseNum,MinVerInfo,6,FALSE))),"Available","Not Supported"))) -> Available | O34: =IF(TcReleaseNum<P34,"Not Supported","Available") -> Available | P34: {=_xlfn.SWITCH(TcBaseVer, 14, K34, 13, J34, 12, I34, 11, IFERROR(VLOOKUP(H34,Table2[#All],3,FALSE),"N/A"),0)} -> 0 | Q34: =IF(TcBaseVer=0,M34,IF(AND(N34="Available",M34="Available",O34="Available"),"Available",IF(M34="","","Not Supported"))) -> Available | R34: =IF(A34>=AWCurrentRel, "Future",Q34) -> Available | S34: =HYPERLINK(U34,T34) -> Not Available | T34: =IFERROR(VLOOKUP(CONCATENATE($B34,"_",$A34),Table4[#All],5,FALSE),"Not Available") -> Not Available | U34: =IFERROR(VLOOKUP(CONCATENATE(B34,"_",A34),Table4[#All],6,FALSE),"")
A35: =IF(OR('Raw Data'!A18=0,'Raw Data'!A18="Delete"),"",'Raw Data'!A18) -> 2 | B35: =IF(OR('Raw Data'!B18=0,'Raw Data'!B18="Delete"),"",'Raw Data'!B18) -> Deliver | C35: =IF(OR('Raw Data'!C18=0,'Raw Data'!C18="Delete"),"",'Raw Data'!C18) -> Analytics | D35: =IF(OR('Raw Data'!D18=0,'Raw Data'!D18="Delete"),"",'Raw Data'!D18) -> Search and Analytics - Search | E35: =IF(OR('Raw Data'!E18=0,'Raw Data'!E18="Delete"),"",'Raw Data'!E18) -> Searching for files (not just Business Objects) | F35: {=_xlfn.SWITCH(ROUND(VLOOKUP(A35,Table1[#All],3),0),11,H35,12,I35,13,J35,14,K35,"N/A")} -> 13 | G35: {=_xlfn.SWITCH(ROUND(VLOOKUP(A35,Table1[#All],5),0),11,H35,12,I35,13,J35,14,K35,"N/A")} -> 14 | H35: =IF(OR('Raw Data'!H18=0,'Raw Data'!H18="Delete"),"",'Raw Data'!H18) -> 13 | I35: =IF(OR('Raw Data'!I18=0,'Raw Data'!I18="Delete"),"",'Raw Data'!I18) -> 14 | J35: =IF(OR('Raw Data'!J18=0,'Raw Data'!J18="Delete"),"",'Raw Data'!J18) | K35: =IF(OR('Raw Data'!K18=0,'Raw Data'!K18="Delete"),"",'Raw Data'!K18) | L35: =R35 -> Available | M35: =IF(A35="","",IF(OR(AWReleaseNum>=A35,AWReleaseNum=0),"Available","Not Supported")) -> Available | N35: =IF(A35="","",IF(TcRelease="Any","Available",IF(OR(AND(TcReleaseNum>=VLOOKUP(AWReleaseNum,MinVerInfo,3,FALSE),TcReleaseNum<=VLOOKUP(AWReleaseNum,MinVerInfo,4,FALSE)),AND(TcReleaseNum>=VLOOKUP(AWReleaseNum,MinVerInfo,5,FALSE),TcReleaseNum<=VLOOKUP(AWReleaseNum,MinVerInfo,6,FALSE))),"Available","Not Supported"))) -> Available | O35: =IF(TcReleaseNum<P35,"Not Supported","Available") -> Available | P35: {=_xlfn.SWITCH(TcBaseVer, 14, K35, 13, J35, 12, I35, 11, IFERROR(VLOOKUP(H35,Table2[#All],3,FALSE),"N/A"),0)} -> 0 | Q35: =IF(TcBaseVer=0,M35,IF(AND(N35="Available",M35="Available",O35="Available"),"Available",IF(M35="","","Not Supported"))) -> Available | R35: =IF(A35>=AWCurrentRel, "Future",Q35) -> Available | S35: =HYPERLINK(U35,T35) -> Not Available | T35: =IFERROR(VLOOKUP(CONCATENATE($B35,"_",$A35),Table4[#All],5,FALSE),"Not Available") -> Not Available | U35: =IFERROR(VLOOKUP(CONCATENATE(B35,"_",A35),Table4[#All],6,FALSE),"")
A36: =IF(OR('Raw Data'!A19=0,'Raw Data'!A19="Delete"),"",'Raw Data'!A19) -> 2 | B36: =IF(OR('Raw Data'!B19=0,'Raw Data'!B19="Delete"),"",'Raw Data'!B19) -> Deliver | C36: =IF(OR('Raw Data'!C19=0,'Raw Data'!C19="Delete"),"",'Raw Data'!C19) -> Analytics | D36: =IF(OR('Raw Data'!D19=0,'Raw Data'!D19="Delete"),"",'Raw Data'!D19) -> Search and Analytics - Search | E36: =IF(OR('Raw Data'!E19=0,'Raw Data'!E19="Delete"),"",'Raw Data'!E19) -> Shape Search | F36: {=_xlfn.SWITCH(ROUND(VLOOKUP(A36,Table1[#All],3),0),11,H36,12,I36,13,J36,14,K36,"N/A")} -> 13 | G36: {=_xlfn.SWITCH(ROUND(VLOOKUP(A36,Table1[#All],5),0),11,H36,12,I36,13,J36,14,K36,"N/A")} -> 14 | H36: =IF(OR('Raw Data'!H19=0,'Raw Data'!H19="Delete"),"",'Raw Data'!H19) -> 13 | I36: =IF(OR('Raw Data'!I19=0,'Raw Data'!I19="Delete"),"",'Raw Data'!I19) -> 14 | J36: =IF(OR('Raw Data'!J19=0,'Raw Data'!J19="Delete"),"",'Raw Data'!J19) | K36: =IF(OR('Raw Data'!K19=0,'Raw Data'!K19="Delete"),"",'Raw Data'!K19) | L36: =R36 -> Available | M36: =IF(A36="","",IF(OR(AWReleaseNum>=A36,AWReleaseNum=0),"Available","Not Supported")) -> Available | N36: =IF(A36="","",IF(TcRelease="Any","Available",IF(OR(AND(TcReleaseNum>=VLOOKUP(AWReleaseNum,MinVerInfo,3,FALSE),TcReleaseNum<=VLOOKUP(AWReleaseNum,MinVerInfo,4,FALSE)),AND(TcReleaseNum>=VLOOKUP(AWReleaseNum,MinVerInfo,5,FALSE),TcReleaseNum<=VLOOKUP(AWReleaseNum,MinVerInfo,6,FALSE))),"Available","Not Supported"))) -> Available | O36: =IF(TcReleaseNum<P36,"Not Supported","Available") -> Available | P36: {=_xlfn.SWITCH(TcBaseVer, 14, K36, 13, J36, 12, I36, 11, IFERROR(VLOOKUP(H36,Table2[#All],3,FALSE),"N/A"),0)} -> 0 | Q36: =IF(TcBaseVer=0,M36,IF(AND(N36="Available",M36="Available",O36="Available"),"Available",IF(M36="","","Not Supported"))) -> Available | R36: =IF(A36>=AWCurrentRel, "Future",Q36) -> Available | S36: =HYPERLINK(U36,T36) -> Not Available | T36: =IFERROR(VLOOKUP(CONCATENATE($B36,"_",$A36),Table4[#All],5,FALSE),"Not Available") -> Not Available | U36: =IFERROR(VLOOKUP(CONCATENATE(B36,"_",A36),Table4[#All],6,FALSE),"")
A37: =IF(OR('Raw Data'!A20=0,'Raw Data'!A20="Delete"),"",'Raw Data'!A20) -> 2 | B37: =IF(OR('Raw Data'!B20=0,'Raw Data'!B20="Delete"),"",'Raw Data'!B20) -> Deliver | C37: =IF(OR('Raw Data'!C20=0,'Raw Data'!C20="Delete"),"",'Raw Data'!C20) -> Analytics | D37: =IF(OR('Raw Data'!D20=0,'Raw Data'!D20="Delete"),"",'Raw Data'!D20) -> Search and Analytics - Search | E37: =IF(OR('Raw Data'!E20=0,'Raw Data'!E20="Delete"),"",'Raw Data'!E20) -> Classification Search | F37: {=_xlfn.SWITCH(ROUND(VLOOKUP(A37,Table1[#All],3),0),11,H37,12,I37,13,J37,14,K37,"N/A")} -> 13 | G37: {=_xlfn.SWITCH(ROUND(VLOOKUP(A37,Table1[#All],5),0),11,H37,12,I37,13,J37,14,K37,"N/A")} -> 14 | H37: =IF(OR('Raw Data'!H20=0,'Raw Data'!H20="Delete"),"",'Raw Data'!H20) -> 13 | I37: =IF(OR('Raw Data'!I20=0,'Raw Data'!I20="Delete"),"",'Raw Data'!I20) -> 14 | J37: =IF(OR('Raw Data'!J20=0,'Raw Data'!J20="Delete"),"",'Raw Data'!J20) | K37: =IF(OR('Raw Data'!K20=0,'Raw Data'!K20="Delete"),"",'Raw Data'!K20) | L37: =R37 -> Available | M37: =IF(A37="","",IF(OR(AWReleaseNum>=A37,AWReleaseNum=0),"Available","Not Supported")) -> Available | N37: =IF(A37="","",IF(TcRelease="Any","Available",IF(OR(AND(TcReleaseNum>=VLOOKUP(AWReleaseNum,MinVerInfo,3,FALSE),TcReleaseNum<=VLOOKUP(AWReleaseNum,MinVerInfo,4,FALSE)),AND(TcReleaseNum>=VLOOKUP(AWReleaseNum,MinVerInfo,5,FALSE),TcReleaseNum<=VLOOKUP(AWReleaseNum,MinVerInfo,6,FALSE))),"Available","Not Supported"))) -> Available | O37: =IF(TcReleaseNum<P37,"Not Supported","Available") -> Available | P37: {=_xlfn.SWITCH(TcBaseVer, 14, K37, 13, J37, 12, I37, 11, IFERROR(VLOOKUP(H37,Table2[#All],3,FALSE),"N/A"),0)} -> 0 | Q37: =IF(TcBaseVer=0,M37,IF(AND(N37="Available",M37="Available",O37="Available"),"Available",IF(M37="","","Not Supported"))) -> Available | R37: =IF(A37>=AWCurrentRel, "Future",Q37) -> Available | S37: =HYPERLINK(U37,T37) -> Not Available | T37: =IFERROR(VLOOKUP(CONCATENATE($B37,"_",$A37),Table4[#All],5,FALSE),"Not Available") -> Not Available | U37: =IFERROR(VLOOKUP(CONCATENATE(B37,"_",A37),Table4[#All],6,FALSE),"")
A38: =IF(OR('Raw Data'!A21=0,'Raw Data'!A21="Delete"),"",'Raw Data'!A21) -> 2 | B38: =IF(OR('Raw Data'!B21=0,'Raw Data'!B21="Delete"),"",'Raw Data'!B21) -> Deliver | C38: =IF(OR('Raw Data'!C21=0,'Raw Data'!C21="Delete"),"",'Raw Data'!C21) -> Analytics | D38: =IF(OR('Raw Data'!D21=0,'Raw Data'!D21="Delete"),"",'Raw Data'!D21) -> Search and Analytics - Search | E38: =IF(OR('Raw Data'!E21=0,'Raw Data'!E21="Delete"),"",'Raw Data'!E21) -> One text box search | F38: {=_xlfn.SWITCH(ROUND(VLOOKUP(A38,Table1[#All],3),0),11,H38,12,I38,13,J38,14,K38,"N/A")} -> 13 | G38: {=_xlfn.SWITCH(ROUND(VLOOKUP(A38,Table1[#All],5),0),11,H38,12,I38,13,J38,14,K38,"N/A")} -> 14 | H38: =IF(OR('Raw Data'!H21=0,'Raw Data'!H21="Delete"),"",'Raw Data'!H21) -> 13 | I38: =IF(OR('Raw Data'!I21=0,'Raw Data'!I21="Delete"),"",'Raw Data'!I21) -> 14 | J38: =IF(OR('Raw Data'!J21=0,'Raw Data'!J21="Delete"),"",'Raw Data'!J21) | K38: =IF(OR('Raw Data'!K21=0,'Raw Data'!K21="Delete"),"",'Raw Data'!K21) | L38: =R38 -> Available | M38: =IF(A38="","",IF(OR(AWReleaseNum>=A38,AWReleaseNum=0),"Available","Not Supported")) -> Available | N38: =IF(A38="","",IF(TcRelease="Any","Available",IF(OR(AND(TcReleaseNum>=VLOOKUP(AWReleaseNum,MinVerInfo,3,FALSE),TcReleaseNum<=VLOOKUP(AWReleaseNum,MinVerInfo,4,FALSE)),AND(TcReleaseNum>=VLOOKUP(AWReleaseNum,MinVerInfo,5,FALSE),TcReleaseNum<=VLOOKUP(AWReleaseNum,MinVerInfo,6,FALSE))),"Available","Not Supported"))) -> Available | O38: =IF(TcReleaseNum<P38,"Not Supported","Available") -> Available | P38: {=_xlfn.SWITCH(TcBaseVer, 14, K38, 13, J38, 12, I38, 11, IFERROR(VLOOKUP(H38,Table2[#All],3,FALSE),"N/A"),0)} -> 0 | Q38: =IF(TcBaseVer=0,M38,IF(AND(N38="Available",M38="Available",O38="Available"),"Available",IF(M38="","","Not Supported"))) -> Available | R38: =IF(A38>=AWCurrentRel, "Future",Q38) -> Available | S38: =HYPERLINK(U38,T38) -> Not Available | T38: =IFERROR(VLOOKUP(CONCATENATE($B38,"_",$A38),Table4[#All],5,FALSE),"Not Available") -> Not Available | U38: =IFERROR(VLOOKUP(CONCATENATE(B38,"_",A38),Table4[#All],6,FALSE),"")
A39: =IF(OR('Raw Data'!A22=0,'Raw Data'!A22="Delete"),"",'Raw Data'!A22) -> 2 | B39: =IF(OR('Raw Data'!B22=0,'Raw Data'!B22="Delete"),"",'Raw Data'!B22) -> Deliver | C39: =IF(OR('Raw Data'!C22=0,'Raw Data'!C22="Delete"),"",'Raw Data'!C22) -> Analytics | D39: =IF(OR('Raw Data'!D22=0,'Raw Data'!D22="Delete"),"",'Raw Data'!D22) -> Search and Analytics - Search | E39: =IF(OR('Raw Data'!E22=0,'Raw Data'!E22="Delete"),"",'Raw Data'!E22) -> Filter results via bar chart | F39: {=_xlfn.SWITCH(ROUND(VLOOKUP(A39,Table1[#All],3),0),11,H39,12,I39,13,J39,14,K39,"N/A")} -> 13 | G39: {=_xlfn.SWITCH(ROUND(VLOOKUP(A39,Table1[#All],5),0),11,H39,12,I39,13,J39,14,K39,"N/A")} -> 14 | H39: =IF(OR('Raw Data'!H22=0,'Raw Data'!H22="Delete"),"",'Raw Data'!H22) -> 13 | I39: =IF(OR('Raw Data'!I22=0,'Raw Data'!I22="Delete"),"",'Raw Data'!I22) -> 14 | J39: =IF(OR('Raw Data'!J22=0,'Raw Data'!J22="Delete"),"",'Raw Data'!J22) | K39: =IF(OR('Raw Data'!K22=0,'Raw Data'!K22="Delete"),"",'Raw Data'!K22) | L39: =R39 -> Available | M39: =IF(A39="","",IF(OR(AWReleaseNum>=A39,AWReleaseNum=0),"Available","Not Supported")) -> Available | N39: =IF(A39="","",IF(TcRelease="Any","Available",IF(OR(AND(TcReleaseNum>=VLOOKUP(AWReleaseNum,MinVerInfo,3,FALSE),TcReleaseNum<=VLOOKUP(AWReleaseNum,MinVerInfo,4,FALSE)),AND(TcReleaseNum>=VLOOKUP(AWReleaseNum,MinVerInfo,5,FALSE),TcReleaseNum<=VLOOKUP(AWReleaseNum,MinVerInfo,6,FALSE))),"Available","Not Supported"))) -> Available | O39: =IF(TcReleaseNum<P39,"Not Supported","Available") -> Available | P39: {=_xlfn.SWITCH(TcBaseVer, 14, K39, 13, J39, 12, I39, 11, IFERROR(VLOOKUP(H39,Table2[#All],3,FALSE),"N/A"),0)} -> 0 | Q39: =IF(TcBaseVer=0,M39,IF(AND(N39="Available",M39="Available",O39="Available"),"Available",IF(M39="","","Not Supported"))) -> Available | R39: =IF(A39>=AWCurrentRel, "Future",Q39) -> Available | S39: =HYPERLINK(U39,T39) -> Not Available | T39: =IFERROR(VLOOKUP(CONCATENATE($B39,"_",$A39),Table4[#All],5,FALSE),"Not Available") -> Not Available | U39: =IFERROR(VLOOKUP(CONCATENATE(B39,"_",A39),Table4[#All],6,FALSE),"")
A40: =IF(OR('Raw Data'!A23=0,'Raw Data'!A23="Delete"),"",'Raw Data'!A23) -> 2 | B40: =IF(OR('Raw Data'!B23=0,'Raw Data'!B23="Delete"),"",'Raw Data'!B23) -> Deliver | C40: =IF(OR('Raw Data'!C23=0,'Raw Data'!C23="Delete"),"",'Raw Data'!C23) -> Analytics | D40: =IF(OR('Raw Data'!D23=0,'Raw Data'!D23="Delete"),"",'Raw Data'!D23) -> Search and Analytics - Search | E40: =IF(OR('Raw Data'!E23=0,'Raw Data'!E23="Delete"),"",'Raw Data'!E23) -> Filter results via fly out filter panel | F40: {=_xlfn.SWITCH(ROUND(VLOOKUP(A40,Table1[#All],3),0),11,H40,12,I40,13,J40,14,K40,"N/A")} -> 13 | G40: {=_xlfn.SWITCH(ROUND(VLOOKUP(A40,Table1[#All],5),0),11,H40,12,I40,13,J40,14,K40,"N/A")} -> 14 | H40: =IF(OR('Raw Data'!H23=0,'Raw Data'!H23="Delete"),"",'Raw Data'!H23) -> 13 | I40: =IF(OR('Raw Data'!I23=0,'Raw Data'!I23="Delete"),"",'Raw Data'!I23) -> 14 | J40: =IF(OR('Raw Data'!J23=0,'Raw Data'!J23="Delete"),"",'Raw Data'!J23) | K40: =IF(OR('Raw Data'!K23=0,'Raw Data'!K23="Delete"),"",'Raw Data'!K23) | L40: =R40 -> Available | M40: =IF(A40="","",IF(OR(AWReleaseNum>=A40,AWReleaseNum=0),"Available","Not Supported")) -> Available | N40: =IF(A40="","",IF(TcRelease="Any","Available",IF(OR(AND(TcReleaseNum>=VLOOKUP(AWReleaseNum,MinVerInfo,3,FALSE),TcReleaseNum<=VLOOKUP(AWReleaseNum,MinVerInfo,4,FALSE)),AND(TcReleaseNum>=VLOOKUP(AWReleaseNum,MinVerInfo,5,FALSE),TcReleaseNum<=VLOOKUP(AWReleaseNum,MinVerInfo,6,FALSE))),"Available","Not Supported"))) -> Available | O40: =IF(TcReleaseNum<P40,"Not Supported","Available") -> Available | P40: {=_xlfn.SWITCH(TcBaseVer, 14, K40, 13, J40, 12, I40, 11, IFERROR(VLOOKUP(H40,Table2[#All],3,FALSE),"N/A"),0)} -> 0 | Q40: =IF(TcBaseVer=0,M40,IF(AND(N40="Available",M40="Available",O40="Available"),"Available",IF(M40="","","Not Supported"))) -> Available | R40: =IF(A40>=AWCurrentRel, "Future",Q40) -> Available | S40: =HYPERLINK(U40,T40) -> Not Available | T40: =IFERROR(VLOOKUP(CONCATENATE($B40,"_",$A40),Table4[#All],5,FALSE),"Not Available") -> Not Available | U40: =IFERROR(VLOOKUP(CONCATENATE(B40,"_",A40),Table4[#All],6,FALSE),"")
A41: =IF(OR('Raw Data'!A24=0,'Raw Data'!A24="Delete"),"",'Raw Data'!A24) -> 2 | B41: =IF(OR('Raw Data'!B24=0,'Raw Data'!B24="Delete"),"",'Raw Data'!B24) -> Deliver | C41: =IF(OR('Raw Data'!C24=0,'Raw Data'!C24="Delete"),"",'Raw Data'!C24) -> Analytics | D41: =IF(OR('Raw Data'!D24=0,'Raw Data'!D24="Delete"),"",'Raw Data'!D24) -> Search and Analytics - Search | E41: =IF(OR('Raw Data'!E24=0,'Raw Data'!E24="Delete"),"",'Raw Data'!E24) -> Open Results | F41: {=_xlfn.SWITCH(ROUND(VLOOKUP(A41,Table1[#All],3),0),11,H41,12,I41,13,J41,14,K41,"N/A")} -> 13 | G41: {=_xlfn.SWITCH(ROUND(VLOOKUP(A41,Table1[#All],5),0),11,H41,12,I41,13,J41,14,K41,"N/A")} -> 14 | H41: =IF(OR('Raw Data'!H24=0,'Raw Data'!H24="Delete"),"",'Raw Data'!H24) -> 13 | I41: =IF(OR('Raw Data'!I24=0,'Raw Data'!I24="Delete"),"",'Raw Data'!I24) -> 14 | J41: =IF(OR('Raw Data'!J24=0,'Raw Data'!J24="Delete"),"",'Raw Data'!J24) | K41: =IF(OR('Raw Data'!K24=0,'Raw Data'!K24="Delete"),"",'Raw Data'!K24) | L41: =R41 -> Available | M41: =IF(A41="","",IF(OR(AWReleaseNum>=A41,AWReleaseNum=0),"Available","Not Supported")) -> Available | N41: =IF(A41="","",IF(TcRelease="Any","Available",IF(OR(AND(TcReleaseNum>=VLOOKUP(AWReleaseNum,MinVerInfo,3,FALSE),TcReleaseNum<=VLOOKUP(AWReleaseNum,MinVerInfo,4,FALSE)),AND(TcReleaseNum>=VLOOKUP(AWReleaseNum,MinVerInfo,5,FALSE),TcReleaseNum<=VLOOKUP(AWReleaseNum,MinVerInfo,6,FALSE))),"Available","Not Supported"))) -> Available | O41: =IF(TcReleaseNum<P41,"Not Supported","Available") -> Available | P41: {=_xlfn.SWITCH(TcBaseVer, 14, K41, 13, J41, 12, I41, 11, IFERROR(VLOOKUP(H41,Table2[#All],3,FALSE),"N/A"),0)} -> 0 | Q41: =IF(TcBaseVer=0,M41,IF(AND(N41="Available",M41="Available",O41="Available"),"Available",IF(M41="","","Not Supported"))) -> Available | R41: =IF(A41>=AWCurrentRel, "Future",Q41) -> Available | S41: =HYPERLINK(U41,T41) -> Not Available | T41: =IFERROR(VLOOKUP(CONCATENATE($B41,"_",$A41),Table4[#All],5,FALSE),"Not Available") -> Not Available | U41: =IFERROR(VLOOKUP(CONCATENATE(B41,"_",A41),Table4[#All],6,FALSE),"")
A42: =IF(OR('Raw Data'!A25=0,'Raw Data'!A25="Delete"),"",'Raw Data'!A25) -> 2 | B42: =IF(OR('Raw Data'!B25=0,'Raw Data'!B25="Delete"),"",'Raw Data'!B25) -> Deliver | C42: =IF(OR('Raw Data'!C25=0,'Raw Data'!C25="Delete"),"",'Raw Data'!C25) -> Analytics | D42: =IF(OR('Raw Data'!D25=0,'Raw Data'!D25="Delete"),"",'Raw Data'!D25) -> Search and Analytics - Search | E42: =IF(OR('Raw Data'!E25=0,'Raw Data'!E25="Delete"),"",'Raw Data'!E25) -> Searches can be saved (open / add / remove) | F42: {=_xlfn.SWITCH(ROUND(VLOOKUP(A42,Table1[#All],3),0),11,H42,12,I42,13,J42,14,K42,"N/A")} -> 13 | G42: {=_xlfn.SWITCH(ROUND(VLOOKUP(A42,Table1[#All],5),0),11,H42,12,I42,13,J42,14,K42,"N/A")} -> 14 | H42: =IF(OR('Raw Data'!H25=0,'Raw Data'!H25="Delete"),"",'Raw Data'!H25) -> 13 | I42: =IF(OR('Raw Data'!I25=0,'Raw Data'!I25="Delete"),"",'Raw Data'!I25) -> 14 | J42: =IF(OR('Raw Data'!J25=0,'Raw Data'!J25="Delete"),"",'Raw Data'!J25) | K42: =IF(OR('Raw Data'!K25=0,'Raw Data'!K25="Delete"),"",'Raw Data'!K25) | L42: =R42 -> Available | M42: =IF(A42="","",IF(OR(AWReleaseNum>=A42,AWReleaseNum=0),"Available","Not Supported")) -> Available | N42: =IF(A42="","",IF(TcRelease="Any","Available",IF(OR(AND(TcReleaseNum>=VLOOKUP(AWReleaseNum,MinVerInfo,3,FALSE),TcReleaseNum<=VLOOKUP(AWReleaseNum,MinVerInfo,4,FALSE)),AND(TcReleaseNum>=VLOOKUP(AWReleaseNum,MinVerInfo,5,FALSE),TcReleaseNum<=VLOOKUP(AWReleaseNum,MinVerInfo,6,FALSE))),"Available","Not Supported"))) -> Available | O42: =IF(TcReleaseNum<P42,"Not Supported","Available") -> Available | P42: {=_xlfn.SWITCH(TcBaseVer, 14, K42, 13, J42, 12, I42, 11, IFERROR(VLOOKUP(H42,Table2[#All],3,FALSE),"N/A"),0)} -> 0 | Q42: =IF(TcBaseVer=0,M42,IF(AND(N42="Available",M42="Available",O42="Available"),"Available",IF(M42="","","Not Supported"))) -> Available | R42: =IF(A42>=AWCurrentRel, "Future",Q42) -> Available | S42: =HYPERLINK(U42,T42) -> Not Available | T42: =IFERROR(VLOOKUP(CONCATENATE($B42,"_",$A42),Table4[#All],5,FALSE),"Not Available") -> Not Available | U42: =IFERROR(VLOOKUP(CONCATENATE(B42,"_",A42),Table4[#All],6,FALSE),"")
A43: =IF(OR('Raw Data'!A26=0,'Raw Data'!A26="Delete"),"",'Raw Data'!A26) -> 2 | B43: =IF(OR('Raw Data'!B26=0,'Raw Data'!B26="Delete"),"",'Raw Data'!B26) -> Deliver | C43: =IF(OR('Raw Data'!C26=0,'Raw Data'!C26="Delete"),"",'Raw Data'!C26) -> Analytics | D43: =IF(OR('Raw Data'!D26=0,'Raw Data'!D26="Delete"),"",'Raw Data'!D26) -> Search and Analytics - Search | E43: =IF(OR('Raw Data'!E26=0,'Raw Data'!E26="Delete"),"",'Raw Data'!E26) -> Track recent searches | F43: {=_xlfn.SWITCH(ROUND(VLOOKUP(A43,Table1[#All],3),0),11,H43,12,I43,13,J43,14,K43,"N/A")} -> 13 | G43: {=_xlfn.SWITCH(ROUND(VLOOKUP(A43,Table1[#All],5),0),11,H43,12,I43,13,J43,14,K43,"N/A")} -> 14 | H43: =IF(OR('Raw Data'!H26=0,'Raw Data'!H26="Delete"),"",'Raw Data'!H26) -> 13 | I43: =IF(OR('Raw Data'!I26=0,'Raw Data'!I26="Delete"),"",'Raw Data'!I26) -> 14 | J43: =IF(OR('Raw Data'!J26=0,'Raw Data'!J26="Delete"),"",'Raw Data'!J26) | K43: =IF(OR('Raw Data'!K26=0,'Raw Data'!K26="Delete"),"",'Raw Data'!K26) | L43: =R43 -> Available | M43: =IF(A43="","",IF(OR(AWReleaseNum>=A43,AWReleaseNum=0),"Available","Not Supported")) -> Available | N43: =IF(A43="","",IF(TcRelease="Any","Available",IF(OR(AND(TcReleaseNum>=VLOOKUP(AWReleaseNum,MinVerInfo,3,FALSE),TcReleaseNum<=VLOOKUP(AWReleaseNum,MinVerInfo,4,FALSE)),AND(TcReleaseNum>=VLOOKUP(AWReleaseNum,MinVerInfo,5,FALSE),TcReleaseNum<=VLOOKUP(AWReleaseNum,MinVerInfo,6,FALSE))),"Available","Not Supported"))) -> Available | O43: =IF(TcReleaseNum<P43,"Not Supported","Available") -> Available | P43: {=_xlfn.SWITCH(TcBaseVer, 14, K43, 13, J43, 12, I43, 11, IFERROR(VLOOKUP(H43,Table2[#All],3,FALSE),"N/A"),0)} -> 0 | Q43: =IF(TcBaseVer=0,M43,IF(AND(N43="Available",M43="Available",O43="Available"),"Available",IF(M43="","","Not Supported"))) -> Available | R43: =IF(A43>=AWCurrentRel, "Future",Q43) -> Available | S43: =HYPERLINK(U43,T43) -> Not Available | T43: =IFERROR(VLOOKUP(CONCATENATE($B43,"_",$A43),Table4[#All],5,FALSE),"Not Available") -> Not Available | U43: =IFERROR(VLOOKUP(CONCATENATE(B43,"_",A43),Table4[#All],6,FALSE),"")
A44: =IF(OR('Raw Data'!A27=0,'Raw Data'!A27="Delete"),"",'Raw Data'!A27) -> 2 | B44: =IF(OR('Raw Data'!B27=0,'Raw Data'!B27="Delete"),"",'Raw Data'!B27) -> Deliver | C44: =IF(OR('Raw Data'!C27=0,'Raw Data'!C27="Delete"),"",'Raw Data'!C27) -> Analytics | D44: =IF(OR('Raw Data'!D27=0,'Raw Data'!D27="Delete"),"",'Raw Data'!D27) -> Search and Analytics - Search | E44: =IF(OR('Raw Data'!E27=0,'Raw Data'!E27="Delete"),"",'Raw Data'!E27) -> Pre-filter data to current user or specific business object type | F44: {=_xlfn.SWITCH(ROUND(VLOOKUP(A44,Table1[#All],3),0),11,H44,12,I44,13,J44,14,K44,"N/A")} -> 13 | G44: {=_xlfn.SWITCH(ROUND(VLOOKUP(A44,Table1[#All],5),0),11,H44,12,I44,13,J44,14,K44,"N/A")} -> 14 | H44: =IF(OR('Raw Data'!H27=0,'Raw Data'!H27="Delete"),"",'Raw Data'!H27) -> 13 | I44: =IF(OR('Raw Data'!I27=0,'Raw Data'!I27="Delete"),"",'Raw Data'!I27) -> 14 | J44: =IF(OR('Raw Data'!J27=0,'Raw Data'!J27="Delete"),"",'Raw Data'!J27) | K44: =IF(OR('Raw Data'!K27=0,'Raw Data'!K27="Delete"),"",'Raw Data'!K27) | L44: =R44 -> Available | M44: =IF(A44="","",IF(OR(AWReleaseNum>=A44,AWReleaseNum=0),"Available","Not Supported")) -> Available | N44: =IF(A44="","",IF(TcRelease="Any","Available",IF(OR(AND(TcReleaseNum>=VLOOKUP(AWReleaseNum,MinVerInfo,3,FALSE),TcReleaseNum<=VLOOKUP(AWReleaseNum,MinVerInfo,4,FALSE)),AND(TcReleaseNum>=VLOOKUP(AWReleaseNum,MinVerInfo,5,FALSE),TcReleaseNum<=VLOOKUP(AWReleaseNum,MinVerInfo,6,FALSE))),"Available","Not Supported"))) -> Available | O44: =IF(TcReleaseNum<P44,"Not Supported","Available") -> Available | P44: {=_xlfn.SWITCH(TcBaseVer, 14, K44, 13, J44, 12, I44, 11, IFERROR(VLOOKUP(H44,Table2[#All],3,FALSE),"N/A"),0)} -> 0 | Q44: =IF(TcBaseVer=0,M44,IF(AND(N44="Available",M44="Available",O44="Available"),"Available",IF(M44="","","Not Supported"))) -> Available | R44: =IF(A44>=AWCurrentRel, "Future",Q44) -> Available | S44: =HYPERLINK(U44,T44) -> Not Available | T44: =IFERROR(VLOOKUP(CONCATENATE($B44,"_",$A44),Table4[#All],5,FALSE),"Not Available") -> Not Available | U44: =IFERROR(VLOOKUP(CONCATENATE(B44,"_",A44),Table4[#All],6,FALSE),"")
A45: =IF(OR('Raw Data'!A51=0,'Raw Data'!A51="Delete"),"",'Raw Data'!A51) -> 2 | B45: =IF(OR('Raw Data'!B51=0,'Raw Data'!B51="Delete"),"",'Raw Data'!B51) -> Develop | C45: =IF(OR('Raw Data'!C51=0,'Raw Data'!C51="Delete"),"",'Raw Data'!C51) -> Visualization | D45: =IF(OR('Raw Data'!D51=0,'Raw Data'!D51="Delete"),"",'Raw Data'!D51) -> Visualization - Usability | E45: =IF(OR('Raw Data'!E51=0,'Raw Data'!E51="Delete"),"",'Raw Data'!E51) -> Preproduction viewing 3D of JT files | F45: {=_xlfn.SWITCH(ROUND(VLOOKUP(A45,Table1[#All],3),0),11,H45,12,I45,13,J45,14,K45,"N/A")} -> 13 | G45: {=_xlfn.SWITCH(ROUND(VLOOKUP(A45,Table1[#All],5),0),11,H45,12,I45,13,J45,14,K45,"N/A")} -> 14 | H45: =IF(OR('Raw Data'!H51=0,'Raw Data'!H51="Delete"),"",'Raw Data'!H51) -> 13 | I45: =IF(OR('Raw Data'!I51=0,'Raw Data'!I51="Delete"),"",'Raw Data'!I51) -> 14 | J45: =IF(OR('Raw Data'!J51=0,'Raw Data'!J51="Delete"),"",'Raw Data'!J51) | K45: =IF(OR('Raw Data'!K51=0,'Raw Data'!K51="Delete"),"",'Raw Data'!K51) | L45: =R45 -> Available | M45: =IF(A45="","",IF(OR(AWReleaseNum>=A45,AWReleaseNum=0),"Available","Not Supported")) -> Available | N45: =IF(A45="","",IF(TcRelease="Any","Available",IF(OR(AND(TcReleaseNum>=VLOOKUP(AWReleaseNum,MinVerInfo,3,FALSE),TcReleaseNum<=VLOOKUP(AWReleaseNum,MinVerInfo,4,FALSE)),AND(TcReleaseNum>=VLOOKUP(AWReleaseNum,MinVerInfo,5,FALSE),TcReleaseNum<=VLOOKUP(AWReleaseNum,MinVerInfo,6,FALSE))),"Available","Not Supported"))) -> Available | O45: =IF(TcReleaseNum<P45,"Not Supported","Available") -> Available | P45: {=_xlfn.SWITCH(TcBaseVer, 14, K45, 13, J45, 12, I45, 11, IFERROR(VLOOKUP(H45,Table2[#All],3,FALSE),"N/A"),0)} -> 0 | Q45: =IF(TcBaseVer=0,M45,IF(AND(N45="Available",M45="Available",O45="Available"),"Available",IF(M45="","","Not Supported"))) -> Available | R45: =IF(A45>=AWCurrentRel, "Future",Q45) -> Available | S45: =HYPERLINK(U45,T45) -> Not Available | T45: =IFERROR(VLOOKUP(CONCATENATE($B45,"_",$A45),Table4[#All],5,FALSE),"Not Available") -> Not Available | U45: =IFERROR(VLOOKUP(CONCATENATE(B45,"_",A45),Table4[#All],6,FALSE),"")
A46: =IF(OR('Raw Data'!A52=0,'Raw Data'!A52="Delete"),"",'Raw Data'!A52) -> 2 | B46: =IF(OR('Raw Data'!B52=0,'Raw Data'!B52="Delete"),"",'Raw Data'!B52) -> Develop | C46: =IF(OR('Raw Data'!C52=0,'Raw Data'!C52="Delete"),"",'Raw Data'!C52) -> Visualization | D46: =IF(OR('Raw Data'!D52=0,'Raw Data'!D52="Delete"),"",'Raw Data'!D52) -> Visualization - Usability | E46: =IF(OR('Raw Data'!E52=0,'Raw Data'!E52="Delete"),"",'Raw Data'!E52) -> PMI Viewing | F46: {=_xlfn.SWITCH(ROUND(VLOOKUP(A46,Table1[#All],3),0),11,H46,12,I46,13,J46,14,K46,"N/A")} -> 13 | G46: {=_xlfn.SWITCH(ROUND(VLOOKUP(A46,Table1[#All],5),0),11,H46,12,I46,13,J46,14,K46,"N/A")} -> 14 | H46: =IF(OR('Raw Data'!H52=0,'Raw Data'!H52="Delete"),"",'Raw Data'!H52) -> 13 | I46: =IF(OR('Raw Data'!I52=0,'Raw Data'!I52="Delete"),"",'Raw Data'!I52) -> 14 | J46: =IF(OR('Raw Data'!J52=0,'Raw Data'!J52="Delete"),"",'Raw Data'!J52) | K46: =IF(OR('Raw Data'!K52=0,'Raw Data'!K52="Delete"),"",'Raw Data'!K52) | L46: =R46 -> Available | M46: =IF(A46="","",IF(OR(AWReleaseNum>=A46,AWReleaseNum=0),"Available","Not Supported")) -> Available | N46: =IF(A46="","",IF(TcRelease="Any","Available",IF(OR(AND(TcReleaseNum>=VLOOKUP(AWReleaseNum,MinVerInfo,3,FALSE),TcReleaseNum<=VLOOKUP(AWReleaseNum,MinVerInfo,4,FALSE)),AND(TcReleaseNum>=VLOOKUP(AWReleaseNum,MinVerInfo,5,FALSE),TcReleaseNum<=VLOOKUP(AWReleaseNum,MinVerInfo,6,FALSE))),"Available","Not Supported"))) -> Available | O46: =IF(TcReleaseNum<P46,"Not Supported","Available") -> Available | P46: {=_xlfn.SWITCH(TcBaseVer, 14, K46, 13, J46, 12, I46, 11, IFERROR(VLOOKUP(H46,Table2[#All],3,FALSE),"N/A"),0)} -> 0 | Q46: =IF(TcBaseVer=0,M46,IF(AND(N46="Available",M46="Available",O46="Available"),"Available",IF(M46="","","Not Supported"))) -> Available | R46: =IF(A46>=AWCurrentRel, "Future",Q46) -> Available | S46: =HYPERLINK(U46,T46) -> Not Available | T46: =IFERROR(VLOOKUP(CONCATENATE($B46,"_",$A46),Table4[#All],5,FALSE),"Not Available") -> Not Available | U46: =IFERROR(VLOOKUP(CONCATENATE(B46,"_",A46),Table4[#All],6,FALSE),"")
A47: =IF(OR('Raw Data'!A53=0,'Raw Data'!A53="Delete"),"",'Raw Data'!A53) -> 2 | B47: =IF(OR('Raw Data'!B53=0,'Raw Data'!B53="Delete"),"",'Raw Data'!B53) -> Develop | C47: =IF(OR('Raw Data'!C53=0,'Raw Data'!C53="Delete"),"",'Raw Data'!C53) -> Visualization | D47: =IF(OR('Raw Data'!D53=0,'Raw Data'!D53="Delete"),"",'Raw Data'!D53) -> Visualization - Usability | E47: =IF(OR('Raw Data'!E53=0,'Raw Data'!E53="Delete"),"",'Raw Data'!E53) -> Display control including materials and floor options | F47: {=_xlfn.SWITCH(ROUND(VLOOKUP(A47,Table1[#All],3),0),11,H47,12,I47,13,J47,14,K47,"N/A")} -> 13 | G47: {=_xlfn.SWITCH(ROUND(VLOOKUP(A47,Table1[#All],5),0),11,H47,12,I47,13,J47,14,K47,"N/A")} -> 14 | H47: =IF(OR('Raw Data'!H53=0,'Raw Data'!H53="Delete"),"",'Raw Data'!H53) -> 13 | I47: =IF(OR('Raw Data'!I53=0,'Raw Data'!I53="Delete"),"",'Raw Data'!I53) -> 14 | J47: =IF(OR('Raw Data'!J53=0,'Raw Data'!J53="Delete"),"",'Raw Data'!J53) | K47: =IF(OR('Raw Data'!K53=0,'Raw Data'!K53="Delete"),"",'Raw Data'!K53) | L47: =R47 -> Available | M47: =IF(A47="","",IF(OR(AWReleaseNum>=A47,AWReleaseNum=0),"Available","Not Supported")) -> Available | N47: =IF(A47="","",IF(TcRelease="Any","Available",IF(OR(AND(TcReleaseNum>=VLOOKUP(AWReleaseNum,MinVerInfo,3,FALSE),TcReleaseNum<=VLOOKUP(AWReleaseNum,MinVerInfo,4,FALSE)),AND(TcReleaseNum>=VLOOKUP(AWReleaseNum,MinVerInfo,5,FALSE),TcReleaseNum<=VLOOKUP(AWReleaseNum,MinVerInfo,6,FALSE))),"Available","Not Supported"))) -> Available | O47: =IF(TcReleaseNum<P47,"Not Supported","Available") -> Available | P47: {=_xlfn.SWITCH(TcBaseVer, 14, K47, 13, J47, 12, I47, 11, IFERROR(VLOOKUP(H47,Table2[#All],3,FALSE),"N/A"),0)} -> 0 | Q47: =IF(TcBaseVer=0,M47,IF(AND(N47="Available",M47="Available",O47="Available"),"Available",IF(M47="","","Not Supported"))) -> Available | R47: =IF(A47>=AWCurrentRel, "Future",Q47) -> Available | S47: =HYPERLINK(U47,T47) -> Not Available | T47: =IFERROR(VLOOKUP(CONCATENATE($B47,"_",$A47),Table4[#All],5,FALSE),"Not Available") -> Not Available | U47: =IFERROR(VLOOKUP(CONCATENATE(B47,"_",A47),Table4[#All],6,FALSE),"")
A48: =IF(OR('Raw Data'!A54=0,'Raw Data'!A54="Delete"),"",'Raw Data'!A54) -> 2 | B48: =IF(OR('Raw Data'!B54=0,'Raw Data'!B54="Delete"),"",'Raw Data'!B54) -> Develop | C48: =IF(OR('Raw Data'!C54=0,'Raw Data'!C54="Delete"),"",'Raw Data'!C54) -> Visualization | D48: =IF(OR('Raw Data'!D54=0,'Raw Data'!D54="Delete"),"",'Raw Data'!D54) -> Visualization - Usability | E48: =IF(OR('Raw Data'!E54=0,'Raw Data'!E54="Delete"),"",'Raw Data'!E54) -> Preproduction 3D of JT files | F48: {=_xlfn.SWITCH(ROUND(VLOOKUP(A48,Table1[#All],3),0),11,H48,12,I48,13,J48,14,K48,"N/A")} -> 13 | G48: {=_xlfn.SWITCH(ROUND(VLOOKUP(A48,Table1[#All],5),0),11,H48,12,I48,13,J48,14,K48,"N/A")} -> 14 | H48: =IF(OR('Raw Data'!H54=0,'Raw Data'!H54="Delete"),"",'Raw Data'!H54) -> 13 | I48: =IF(OR('Raw Data'!I54=0,'Raw Data'!I54="Delete"),"",'Raw Data'!I54) -> 14 | J48: =IF(OR('Raw Data'!J54=0,'Raw Data'!J54="Delete"),"",'Raw Data'!J54) | K48: =IF(OR('Raw Data'!K54=0,'Raw Data'!K54="Delete"),"",'Raw Data'!K54) | L48: =R48 -> Available | M48: =IF(A48="","",IF(OR(AWReleaseNum>=A48,AWReleaseNum=0),"Available","Not Supported")) -> Available | N48: =IF(A48="","",IF(TcRelease="Any","Available",IF(OR(AND(TcReleaseNum>=VLOOKUP(AWReleaseNum,MinVerInfo,3,FALSE),TcReleaseNum<=VLOOKUP(AWReleaseNum,MinVerInfo,4,FALSE)),AND(TcReleaseNum>=VLOOKUP(AWReleaseNum,MinVerInfo,5,FALSE),TcReleaseNum<=VLOOKUP(AWReleaseNum,MinVerInfo,6,FALSE))),"Available","Not Supported"))) -> Available | O48: =IF(TcReleaseNum<P48,"Not Supported","Available") -> Available | P48: {=_xlfn.SWITCH(TcBaseVer, 14, K48, 13, J48, 12, I48, 11, IFERROR(VLOOKUP(H48,Table2[#All],3,FALSE),"N/A"),0)} -> 0 | Q48: =IF(TcBaseVer=0,M48,IF(AND(N48="Available",M48="Available",O48="Available"),"Available",IF(M48="","","Not Supported"))) -> Available | R48: =IF(A48>=AWCurrentRel, "Future",Q48) -> Available | S48: =HYPERLINK(U48,T48) -> Not Available | T48: =IFERROR(VLOOKUP(CONCATENATE($B48,"_",$A48),Table4[#All],5,FALSE),"Not Available") -> Not Available | U48: =IFERROR(VLOOKUP(CONCATENATE(B48,"_",A48),Table4[#All],6,FALSE),"")
A49: =IF(OR('Raw Data'!A1128=0,'Raw Data'!A1128="Delete"),"",'Raw Data'!A1128) -> 2 | B49: =IF(OR('Raw Data'!B1128=0,'Raw Data'!B1128="Delete"),"",'Raw Data'!B1128) -> Plan | C49: =IF(OR('Raw Data'!C1128=0,'Raw Data'!C1128="Delete"),"",'Raw Data'!C1128) -> Process | D49: =IF(OR('Raw Data'!D1128=0,'Raw Data'!D1128="Delete"),"",'Raw Data'!D1128) -> Workflow | E49: =IF(OR('Raw Data'!E1128=0,'Raw Data'!E1128="Delete"),"",'Raw Data'!E1128) -> Any opened object can be submitted into a workflow process | F49: {=_xlfn.SWITCH(ROUND(VLOOKUP(A49,Table1[#All],3),0),11,H49,12,I49,13,J49,14,K49,"N/A")} -> 13 | G49: {=_xlfn.SWITCH(ROUND(VLOOKUP(A49,Table1[#All],5),0),11,H49,12,I49,13,J49,14,K49,"N/A")} -> 14 | H49: =IF(OR('Raw Data'!H1128=0,'Raw Data'!H1128="Delete"),"",'Raw Data'!H1128) -> 13 | I49: =IF(OR('Raw Data'!I1128=0,'Raw Data'!I1128="Delete"),"",'Raw Data'!I1128) -> 14 | J49: =IF(OR('Raw Data'!J1128=0,'Raw Data'!J1128="Delete"),"",'Raw Data'!J1128) | K49: =IF(OR('Raw Data'!K1128=0,'Raw Data'!K1128="Delete"),"",'Raw Data'!K1128) | L49: =R49 -> Available | M49: =IF(A49="","",IF(OR(AWReleaseNum>=A49,AWReleaseNum=0),"Available","Not Supported")) -> Available | N49: =IF(A49="","",IF(TcRelease="Any","Available",IF(OR(AND(TcReleaseNum>=VLOOKUP(AWReleaseNum,MinVerInfo,3,FALSE),TcReleaseNum<=VLOOKUP(AWReleaseNum,MinVerInfo,4,FALSE)),AND(TcReleaseNum>=VLOOKUP(AWReleaseNum,MinVerInfo,5,FALSE),TcReleaseNum<=VLOOKUP(AWReleaseNum,MinVerInfo,6,FALSE))),"Available","Not Supported"))) -> Available | O49: =IF(TcReleaseNum<P49,"Not Supported","Available") -> Available | P49: {=_xlfn.SWITCH(TcBaseVer, 14, K49, 13, J49, 12, I49, 11, IFERROR(VLOOKUP(H49,Table2[#All],3,FALSE),"N/A"),0)} -> 0 | Q49: =IF(TcBaseVer=0,M49,IF(AND(N49="Available",M49="Available",O49="Available"),"Available",IF(M49="","","Not Supported"))) -> Available | R49: =IF(A49>=AWCurrentRel, "Future",Q49) -> Available | S49: =HYPERLINK(U49,T49) -> Not Available | T49: =IFERROR(VLOOKUP(CONCATENATE($B49,"_",$A49),Table4[#All],5,FALSE),"Not Available") -> Not Available | U49: =IFERROR(VLOOKUP(CONCATENATE(B49,"_",A49),Table4[#All],6,FALSE),"")
A50: =IF(OR('Raw Data'!A1129=0,'Raw Data'!A1129="Delete"),"",'Raw Data'!A1129) -> 2 | B50: =IF(OR('Raw Data'!B1129=0,'Raw Data'!B1129="Delete"),"",'Raw Data'!B1129) -> Plan | C50: =IF(OR('Raw Data'!C1129=0,'Raw Data'!C1129="Delete"),"",'Raw Data'!C1129) -> Process | D50: =IF(OR('Raw Data'!D1129=0,'Raw Data'!D1129="Delete"),"",'Raw Data'!D1129) -> Workflow | E50: =IF(OR('Raw Data'!E1129=0,'Raw Data'!E1129="Delete"),"",'Raw Data'!E1129) -> Filter inbox via pie chart | F50: {=_xlfn.SWITCH(ROUND(VLOOKUP(A50,Table1[#All],3),0),11,H50,12,I50,13,J50,14,K50,"N/A")} -> 13 | G50: {=_xlfn.SWITCH(ROUND(VLOOKUP(A50,Table1[#All],5),0),11,H50,12,I50,13,J50,14,K50,"N/A")} -> 14 | H50: =IF(OR('Raw Data'!H1129=0,'Raw Data'!H1129="Delete"),"",'Raw Data'!H1129) -> 13 | I50: =IF(OR('Raw Data'!I1129=0,'Raw Data'!I1129="Delete"),"",'Raw Data'!I1129) -> 14 | J50: =IF(OR('Raw Data'!J1129=0,'Raw Data'!J1129="Delete"),"",'Raw Data'!J1129) | K50: =IF(OR('Raw Data'!K1129=0,'Raw Data'!K1129="Delete"),"",'Raw Data'!K1129) | L50: =R50 -> Available | M50: =IF(A50="","",IF(OR(AWReleaseNum>=A50,AWReleaseNum=0),"Available","Not Supported")) -> Available | N50: =IF(A50="","",IF(TcRelease="Any","Available",IF(OR(AND(TcReleaseNum>=VLOOKUP(AWReleaseNum,MinVerInfo,3,FALSE),TcReleaseNum<=VLOOKUP(AWReleaseNum,MinVerInfo,4,FALSE)),AND(TcReleaseNum>=VLOOKUP(AWReleaseNum,MinVerInfo,5,FALSE),TcReleaseNum<=VLOOKUP(AWReleaseNum,MinVerInfo,6,FALSE))),"Available","Not Supported"))) -> Available | O50: =IF(TcReleaseNum<P50,"Not Supported","Available") -> Available | P50: {=_xlfn.SWITCH(TcBaseVer, 14, K50, 13, J50, 12, I50, 11, IFERROR(VLOOKUP(H50,Table2[#All],3,FALSE),"N/A"),0)} -> 0 | Q50: =IF(TcBaseVer=0,M50,IF(AND(N50="Available",M50="Available",O50="Available"),"Available",IF(M50="","","Not Supported"))) -> Available | R50: =IF(A50>=AWCurrentRel, "Future",Q50) -> Available | S50: =HYPERLINK(U50,T50) -> Not Available | T50: =IFERROR(VLOOKUP(CONCATENATE($B50,"_",$A50),Table4[#All],5,FALSE),"Not Available") -> Not Available | U50: =IFERROR(VLOOKUP(CONCATENATE(B50,"_",A50),Table4[#All],6,FALSE),"")
A51: =IF(OR('Raw Data'!A1130=0,'Raw Data'!A1130="Delete"),"",'Raw Data'!A1130) -> 2 | B51: =IF(OR('Raw Data'!B1130=0,'Raw Data'!B1130="Delete"),"",'Raw Data'!B1130) -> Plan | C51: =IF(OR('Raw Data'!C1130=0,'Raw Data'!C1130="Delete"),"",'Raw Data'!C1130) -> Process | D51: =IF(OR('Raw Data'!D1130=0,'Raw Data'!D1130="Delete"),"",'Raw Data'!D1130) -> Workflow | E51: =IF(OR('Raw Data'!E1130=0,'Raw Data'!E1130="Delete"),"",'Raw Data'!E1130) -> View and manage tasks | F51: {=_xlfn.SWITCH(ROUND(VLOOKUP(A51,Table1[#All],3),0),11,H51,12,I51,13,J51,14,K51,"N/A")} -> 13 | G51: {=_xlfn.SWITCH(ROUND(VLOOKUP(A51,Table1[#All],5),0),11,H51,12,I51,13,J51,14,K51,"N/A")} -> 14 | H51: =IF(OR('Raw Data'!H1130=0,'Raw Data'!H1130="Delete"),"",'Raw Data'!H1130) -> 13 | I51: =IF(OR('Raw Data'!I1130=0,'Raw Data'!I1130="Delete"),"",'Raw Data'!I1130) -> 14 | J51: =IF(OR('Raw Data'!J1130=0,'Raw Data'!J1130="Delete"),"",'Raw Data'!J1130) | K51: =IF(OR('Raw Data'!K1130=0,'Raw Data'!K1130="Delete"),"",'Raw Data'!K1130) | L51: =R51 -> Available | M51: =IF(A51="","",IF(OR(AWReleaseNum>=A51,AWReleaseNum=0),"Available","Not Supported")) -> Available | N51: =IF(A51="","",IF(TcRelease="Any","Available",IF(OR(AND(TcReleaseNum>=VLOOKUP(AWReleaseNum,MinVerInfo,3,FALSE),TcReleaseNum<=VLOOKUP(AWReleaseNum,MinVerInfo,4,FALSE)),AND(TcReleaseNum>=VLOOKUP(AWReleaseNum,MinVerInfo,5,FALSE),TcReleaseNum<=VLOOKUP(AWReleaseNum,MinVerInfo,6,FALSE))),"Available","Not Supported"))) -> Available | O51: =IF(TcReleaseNum<P51,"Not Supported","Available") -> Available | P51: {=_xlfn.SWITCH(TcBaseVer, 14, K51, 13, J51, 12, I51, 11, IFERROR(VLOOKUP(H51,Table2[#All],3,FALSE),"N/A"),0)} -> 0 | Q51: =IF(TcBaseVer=0,M51,IF(AND(N51="Available",M51="Available",O51="Available"),"Available",IF(M51="","","Not Supported"))) -> Available | R51: =IF(A51>=AWCurrentRel, "Future",Q51) -> Available | S51: =HYPERLINK(U51,T51) -> Not Available | T51: =IFERROR(VLOOKUP(CONCATENATE($B51,"_",$A51),Table4[#All],5,FALSE),"Not Available") -> Not Available | U51: =IFERROR(VLOOKUP(CONCATENATE(B51,"_",A51),Table4[#All],6,FALSE),"")
A52: =IF(OR('Raw Data'!A1131=0,'Raw Data'!A1131="Delete"),"",'Raw Data'!A1131) -> 2 | B52: =IF(OR('Raw Data'!B1131=0,'Raw Data'!B1131="Delete"),"",'Raw Data'!B1131) -> Plan | C52: =IF(OR('Raw Data'!C1131=0,'Raw Data'!C1131="Delete"),"",'Raw Data'!C1131) -> Process | D52: =IF(OR('Raw Data'!D1131=0,'Raw Data'!D1131="Delete"),"",'Raw Data'!D1131) -> Workflow | E52: =IF(OR('Raw Data'!E1131=0,'Raw Data'!E1131="Delete"),"",'Raw Data'!E1131) -> Perform Signoff | F52: {=_xlfn.SWITCH(ROUND(VLOOKUP(A52,Table1[#All],3),0),11,H52,12,I52,13,J52,14,K52,"N/A")} -> 13 | G52: {=_xlfn.SWITCH(ROUND(VLOOKUP(A52,Table1[#All],5),0),11,H52,12,I52,13,J52,14,K52,"N/A")} -> 14 | H52: =IF(OR('Raw Data'!H1131=0,'Raw Data'!H1131="Delete"),"",'Raw Data'!H1131) -> 13 | I52: =IF(OR('Raw Data'!I1131=0,'Raw Data'!I1131="Delete"),"",'Raw Data'!I1131) -> 14 | J52: =IF(OR('Raw Data'!J1131=0,'Raw Data'!J1131="Delete"),"",'Raw Data'!J1131) | K52: =IF(OR('Raw Data'!K1131=0,'Raw Data'!K1131="Delete"),"",'Raw Data'!K1131) | L52: =R52 -> Available | M52: =IF(A52="","",IF(OR(AWReleaseNum>=A52,AWReleaseNum=0),"Available","Not Supported")) -> Available | N52: =IF(A52="","",IF(TcRelease="Any","Available",IF(OR(AND(TcReleaseNum>=VLOOKUP(AWReleaseNum,MinVerInfo,3,FALSE),TcReleaseNum<=VLOOKUP(AWReleaseNum,MinVerInfo,4,FALSE)),AND(TcReleaseNum>=VLOOKUP(AWReleaseNum,MinVerInfo,5,FALSE),TcReleaseNum<=VLOOKUP(AWReleaseNum,MinVerInfo,6,FALSE))),"Available","Not Supported"))) -> Available | O52: =IF(TcReleaseNum<P52,"Not Supported","Available") -> Available | P52: {=_xlfn.SWITCH(TcBaseVer, 14, K52, 13, J52, 12, I52, 11, IFERROR(VLOOKUP(H52,Table2[#All],3,FALSE),"N/A"),0)} -> 0 | Q52: =IF(TcBaseVer=0,M52,IF(AND(N52="Available",M52="Available",O52="Available"),"Available",IF(M52="","","Not Supported"))) -> Available | R52: =IF(A52>=AWCurrentRel, "Future",Q52) -> Available | S52: =HYPERLINK(U52,T52) -> Not Available | T52: =IFERROR(VLOOKUP(CONCATENATE($B52,"_",$A52),Table4[#All],5,FALSE),"Not Available") -> Not Available | U52: =IFERROR(VLOOKUP(CONCATENATE(B52,"_",A52),Table4[#All],6,FALSE),"")
A53: =IF(OR('Raw Data'!A1132=0,'Raw Data'!A1132="Delete"),"",'Raw Data'!A1132) -> 2 | B53: =IF(OR('Raw Data'!B1132=0,'Raw Data'!B1132="Delete"),"",'Raw Data'!B1132) -> Plan | C53: =IF(OR('Raw Data'!C1132=0,'Raw Data'!C1132="Delete"),"",'Raw Data'!C1132) -> Process | D53: =IF(OR('Raw Data'!D1132=0,'Raw Data'!D1132="Delete"),"",'Raw Data'!D1132) -> Workflow | E53: =IF(OR('Raw Data'!E1132=0,'Raw Data'!E1132="Delete"),"",'Raw Data'!E1132) -> Select Signoff team | F53: {=_xlfn.SWITCH(ROUND(VLOOKUP(A53,Table1[#All],3),0),11,H53,12,I53,13,J53,14,K53,"N/A")} -> 13 | G53: {=_xlfn.SWITCH(ROUND(VLOOKUP(A53,Table1[#All],5),0),11,H53,12,I53,13,J53,14,K53,"N/A")} -> 14 | H53: =IF(OR('Raw Data'!H1132=0,'Raw Data'!H1132="Delete"),"",'Raw Data'!H1132) -> 13 | I53: =IF(OR('Raw Data'!I1132=0,'Raw Data'!I1132="Delete"),"",'Raw Data'!I1132) -> 14 | J53: =IF(OR('Raw Data'!J1132=0,'Raw Data'!J1132="Delete"),"",'Raw Data'!J1132) | K53: =IF(OR('Raw Data'!K1132=0,'Raw Data'!K1132="Delete"),"",'Raw Data'!K1132) | L53: =R53 -> Available | M53: =IF(A53="","",IF(OR(AWReleaseNum>=A53,AWReleaseNum=0),"Available","Not Supported")) -> Available | N53: =IF(A53="","",IF(TcRelease="Any","Available",IF(OR(AND(TcReleaseNum>=VLOOKUP(AWReleaseNum,MinVerInfo,3,FALSE),TcReleaseNum<=VLOOKUP(AWReleaseNum,MinVerInfo,4,FALSE)),AND(TcReleaseNum>=VLOOKUP(AWReleaseNum,MinVerInfo,5,FALSE),TcReleaseNum<=VLOOKUP(AWReleaseNum,MinVerInfo,6,FALSE))),"Available","Not Supported"))) -> Available | O53: =IF(TcReleaseNum<P53,"Not Supported","Available") -> Available | P53: {=_xlfn.SWITCH(TcBaseVer, 14, K53, 13, J53, 12, I53, 11, IFERROR(VLOOKUP(H53,Table2[#All],3,FALSE),"N/A"),0)} -> 0 | Q53: =IF(TcBaseVer=0,M53,IF(AND(N53="Available",M53="Available",O53="Available"),"Available",IF(M53="","","Not Supported"))) -> Available | R53: =IF(A53>=AWCurrentRel, "Future",Q53) -> Available | S53: =HYPERLINK(U53,T53) -> Not Available | T53: =IFERROR(VLOOKUP(CONCATENATE($B53,"_",$A53),Table4[#All],5,FALSE),"Not Available") -> Not Available | U53: =IFERROR(VLOOKUP(CONCATENATE(B53,"_",A53),Table4[#All],6,FALSE),"")
A54: =IF(OR('Raw Data'!A1197=0,'Raw Data'!A1197="Delete"),"",'Raw Data'!A1197) -> 2 | B54: =IF(OR('Raw Data'!B1197=0,'Raw Data'!B1197="Delete"),"",'Raw Data'!B1197) -> Plan | C54: =IF(OR('Raw Data'!C1197=0,'Raw Data'!C1197="Delete"),"",'Raw Data'!C1197) -> Process | D54: =IF(OR('Raw Data'!D1197=0,'Raw Data'!D1197="Delete"),"",'Raw Data'!D1197) -> Workflow | E54: =IF(OR('Raw Data'!E1197=0,'Raw Data'!E1197="Delete"),"",'Raw Data'!E1197) -> Do Tasks | F54: {=_xlfn.SWITCH(ROUND(VLOOKUP(A54,Table1[#All],3),0),11,H54,12,I54,13,J54,14,K54,"N/A")} -> 13 | G54: {=_xlfn.SWITCH(ROUND(VLOOKUP(A54,Table1[#All],5),0),11,H54,12,I54,13,J54,14,K54,"N/A")} -> 14 | H54: =IF(OR('Raw Data'!H1197=0,'Raw Data'!H1197="Delete"),"",'Raw Data'!H1197) -> 13 | I54: =IF(OR('Raw Data'!I1197=0,'Raw Data'!I1197="Delete"),"",'Raw Data'!I1197) -> 14 | J54: =IF(OR('Raw Data'!J1197=0,'Raw Data'!J1197="Delete"),"",'Raw Data'!J1197) | K54: =IF(OR('Raw Data'!K1197=0,'Raw Data'!K1197="Delete"),"",'Raw Data'!K1197) | L54: =R54 -> Available | M54: =IF(A54="","",IF(OR(AWReleaseNum>=A54,AWReleaseNum=0),"Available","Not Supported")) -> Available | N54: =IF(A54="","",IF(TcRelease="Any","Available",IF(OR(AND(TcReleaseNum>=VLOOKUP(AWReleaseNum,MinVerInfo,3,FALSE),TcReleaseNum<=VLOOKUP(AWReleaseNum,MinVerInfo,4,FALSE)),AND(TcReleaseNum>=VLOOKUP(AWReleaseNum,MinVerInfo,5,FALSE),TcReleaseNum<=VLOOKUP(AWReleaseNum,MinVerInfo,6,FALSE))),"Available","Not Supported"))) -> Available | O54: =IF(TcReleaseNum<P54,"Not Supported","Available") -> Available | P54: {=_xlfn.SWITCH(TcBaseVer, 14, K54, 13, J54, 12, I54, 11, IFERROR(VLOOKUP(H54,Table2[#All],3,FALSE),"N/A"),0)} -> 0 | Q54: =IF(TcBaseVer=0,M54,IF(AND(N54="Available",M54="Available",O54="Available"),"Available",IF(M54="","","Not Supported"))) -> Available | R54: =IF(A54>=AWCurrentRel, "Future",Q54) -> Available | S54: =HYPERLINK(U54,T54) -> Not Available | T54: =IFERROR(VLOOKUP(CONCATENATE($B54,"_",$A54),Table4[#All],5,FALSE),"Not Available") -> Not Available | U54: =IFERROR(VLOOKUP(CONCATENATE(B54,"_",A54),Table4[#All],6,FALSE),"")
A55: =IF(OR('Raw Data'!A1198=0,'Raw Data'!A1198="Delete"),"",'Raw Data'!A1198) -> 2 | B55: =IF(OR('Raw Data'!B1198=0,'Raw Data'!B1198="Delete"),"",'Raw Data'!B1198) -> Plan | C55: =IF(OR('Raw Data'!C1198=0,'Raw Data'!C1198="Delete"),"",'Raw Data'!C1198) -> Process | D55: =IF(OR('Raw Data'!D1198=0,'Raw Data'!D1198="Delete"),"",'Raw Data'!D1198) -> Workflow | E55: =IF(OR('Raw Data'!E1198=0,'Raw Data'!E1198="Delete"),"",'Raw Data'!E1198) -> Workflow viewer | F55: {=_xlfn.SWITCH(ROUND(VLOOKUP(A55,Table1[#All],3),0),11,H55,12,I55,13,J55,14,K55,"N/A")} -> 13 | G55: {=_xlfn.SWITCH(ROUND(VLOOKUP(A55,Table1[#All],5),0),11,H55,12,I55,13,J55,14,K55,"N/A")} -> 14 | H55: =IF(OR('Raw Data'!H1198=0,'Raw Data'!H1198="Delete"),"",'Raw Data'!H1198) -> 13 | I55: =IF(OR('Raw Data'!I1198=0,'Raw Data'!I1198="Delete"),"",'Raw Data'!I1198) -> 14 | J55: =IF(OR('Raw Data'!J1198=0,'Raw Data'!J1198="Delete"),"",'Raw Data'!J1198) | K55: =IF(OR('Raw Data'!K1198=0,'Raw Data'!K1198="Delete"),"",'Raw Data'!K1198) | L55: =R55 -> Available | M55: =IF(A55="","",IF(OR(AWReleaseNum>=A55,AWReleaseNum=0),"Available","Not Supported")) -> Available | N55: =IF(A55="","",IF(TcRelease="Any","Available",IF(OR(AND(TcReleaseNum>=VLOOKUP(AWReleaseNum,MinVerInfo,3,FALSE),TcReleaseNum<=VLOOKUP(AWReleaseNum,MinVerInfo,4,FALSE)),AND(TcReleaseNum>=VLOOKUP(AWReleaseNum,MinVerInfo,5,FALSE),TcReleaseNum<=VLOOKUP(AWReleaseNum,MinVerInfo,6,FALSE))),"Available","Not Supported"))) -> Available | O55: =IF(TcReleaseNum<P55,"Not Supported","Available") -> Available | P55: {=_xlfn.SWITCH(TcBaseVer, 14, K55, 13, J55, 12, I55, 11, IFERROR(VLOOKUP(H55,Table2[#All],3,FALSE),"N/A"),0)} -> 0 | Q55: =IF(TcBaseVer=0,M55,IF(AND(N55="Available",M55="Available",O55="Available"),"Available",IF(M55="","","Not Supported"))) -> Available | R55: =IF(A55>=AWCurrentRel, "Future",Q55) -> Available | S55: =HYPERLINK(U55,T55) -> Not Available | T55: =IFERROR(VLOOKUP(CONCATENATE($B55,"_",$A55),Table4[#All],5,FALSE),"Not Available") -> Not Available | U55: =IFERROR(VLOOKUP(CONCATENATE(B55,"_",A55),Table4[#All],6,FALSE),"")
A56: =IF(OR('Raw Data'!A1199=0,'Raw Data'!A1199="Delete"),"",'Raw Data'!A1199) -> 2 | B56: =IF(OR('Raw Data'!B1199=0,'Raw Data'!B1199="Delete"),"",'Raw Data'!B1199) -> Plan | C56: =IF(OR('Raw Data'!C1199=0,'Raw Data'!C1199="Delete"),"",'Raw Data'!C1199) -> Process | D56: =IF(OR('Raw Data'!D1199=0,'Raw Data'!D1199="Delete"),"",'Raw Data'!D1199) -> Workflow | E56: =IF(OR('Raw Data'!E1199=0,'Raw Data'!E1199="Delete"),"",'Raw Data'!E1199) -> Open and view related objects | F56: {=_xlfn.SWITCH(ROUND(VLOOKUP(A56,Table1[#All],3),0),11,H56,12,I56,13,J56,14,K56,"N/A")} -> 13 | G56: {=_xlfn.SWITCH(ROUND(VLOOKUP(A56,Table1[#All],5),0),11,H56,12,I56,13,J56,14,K56,"N/A")} -> 14 | H56: =IF(OR('Raw Data'!H1199=0,'Raw Data'!H1199="Delete"),"",'Raw Data'!H1199) -> 13 | I56: =IF(OR('Raw Data'!I1199=0,'Raw Data'!I1199="Delete"),"",'Raw Data'!I1199) -> 14 | J56: =IF(OR('Raw Data'!J1199=0,'Raw Data'!J1199="Delete"),"",'Raw Data'!J1199) | K56: =IF(OR('Raw Data'!K1199=0,'Raw Data'!K1199="Delete"),"",'Raw Data'!K1199) | L56: =R56 -> Available | M56: =IF(A56="","",IF(OR(AWReleaseNum>=A56,AWReleaseNum=0),"Available","Not Supported")) -> Available | N56: =IF(A56="","",IF(TcRelease="Any","Available",IF(OR(AND(TcReleaseNum>=VLOOKUP(AWReleaseNum,MinVerInfo,3,FALSE),TcReleaseNum<=VLOOKUP(AWReleaseNum,MinVerInfo,4,FALSE)),AND(TcReleaseNum>=VLOOKUP(AWReleaseNum,MinVerInfo,5,FALSE),TcReleaseNum<=VLOOKUP(AWReleaseNum,MinVerInfo,6,FALSE))),"Available","Not Supported"))) -> Available | O56: =IF(TcReleaseNum<P56,"Not Supported","Available") -> Available | P56: {=_xlfn.SWITCH(TcBaseVer, 14, K56, 13, J56, 12, I56, 11, IFERROR(VLOOKUP(H56,Table2[#All],3,FALSE),"N/A"),0)} -> 0 | Q56: =IF(TcBaseVer=0,M56,IF(AND(N56="Available",M56="Available",O56="Available"),"Available",IF(M56="","","Not Supported"))) -> Available | R56: =IF(A56>=AWCurrentRel, "Future",Q56) -> Available | S56: =HYPERLINK(U56,T56) -> Not Available | T56: =IFERROR(VLOOKUP(CONCATENATE($B56,"_",$A56),Table4[#All],5,FALSE),"Not Available") -> Not Available | U56: =IFERROR(VLOOKUP(CONCATENATE(B56,"_",A56),Table4[#All],6,FALSE),"")
A57: =IF(OR('Raw Data'!A55=0,'Raw Data'!A55="Delete"),"",'Raw Data'!A55) -> 2.1 | B57: =IF(OR('Raw Data'!B55=0,'Raw Data'!B55="Delete"),"",'Raw Data'!B55) -> Foundation | C57: =IF(OR('Raw Data'!C55=0,'Raw Data'!C55="Delete"),"",'Raw Data'!C55) -> Connectivity | D57: =IF(OR('Raw Data'!D55=0,'Raw Data'!D55="Delete"),"",'Raw Data'!D55) -> Active Integration | E57: =IF(OR('Raw Data'!E55=0,'Raw Data'!E55="Delete"),"",'Raw Data'!E55) -> Hosting Active Workspace in Teamcenter Rich client, Office, and Visualization | F57: {=_xlfn.SWITCH(ROUND(VLOOKUP(A57,Table1[#All],3),0),11,H57,12,I57,13,J57,14,K57,"N/A")} -> 13 | G57: {=_xlfn.SWITCH(ROUND(VLOOKUP(A57,Table1[#All],5),0),11,H57,12,I57,13,J57,14,K57,"N/A")} -> 14 | H57: =IF(OR('Raw Data'!H55=0,'Raw Data'!H55="Delete"),"",'Raw Data'!H55) -> 13 | I57: =IF(OR('Raw Data'!I55=0,'Raw Data'!I55="Delete"),"",'Raw Data'!I55) -> 14 | J57: =IF(OR('Raw Data'!J55=0,'Raw Data'!J55="Delete"),"",'Raw Data'!J55) | K57: =IF(OR('Raw Data'!K55=0,'Raw Data'!K55="Delete"),"",'Raw Data'!K55) | L57: =R57 -> Available | M57: =IF(A57="","",IF(OR(AWReleaseNum>=A57,AWReleaseNum=0),"Available","Not Supported")) -> Available | N57: =IF(A57="","",IF(TcRelease="Any","Available",IF(OR(AND(TcReleaseNum>=VLOOKUP(AWReleaseNum,MinVerInfo,3,FALSE),TcReleaseNum<=VLOOKUP(AWReleaseNum,MinVerInfo,4,FALSE)),AND(TcReleaseNum>=VLOOKUP(AWReleaseNum,MinVerInfo,5,FALSE),TcReleaseNum<=VLOOKUP(AWReleaseNum,MinVerInfo,6,FALSE))),"Available","Not Supported"))) -> Available | O57: =IF(TcReleaseNum<P57,"Not Supported","Available") -> Available | P57: {=_xlfn.SWITCH(TcBaseVer, 14, K57, 13, J57, 12, I57, 11, IFERROR(VLOOKUP(H57,Table2[#All],3,FALSE),"N/A"),0)} -> 0 | Q57: =IF(TcBaseVer=0,M57,IF(AND(N57="Available",M57="Available",O57="Available"),"Available",IF(M57="","","Not Supported"))) -> Available | R57: =IF(A57>=AWCurrentRel, "Future",Q57) -> Available | S57: =HYPERLINK(U57,T57) -> Not Available | T57: =IFERROR(VLOOKUP(CONCATENATE($B57,"_",$A57),Table4[#All],5,FALSE),"Not Available") -> Not Available | U57: =IFERROR(VLOOKUP(CONCATENATE(B57,"_",A57),Table4[#All],6,FALSE),"")
A58: =IF(OR('Raw Data'!A56=0,'Raw Data'!A56="Delete"),"",'Raw Data'!A56) -> 2.1 | B58: =IF(OR('Raw Data'!B56=0,'Raw Data'!B56="Delete"),"",'Raw Data'!B56) -> Foundation | C58: =IF(OR('Raw Data'!C56=0,'Raw Data'!C56="Delete"),"",'Raw Data'!C56) -> Connectivity | D58: =IF(OR('Raw Data'!D56=0,'Raw Data'!D56="Delete"),"",'Raw Data'!D56) -> Active Integration | E58: =IF(OR('Raw Data'!E56=0,'Raw Data'!E56="Delete"),"",'Raw Data'!E56) -> Shared session/login | F58: {=_xlfn.SWITCH(ROUND(VLOOKUP(A58,Table1[#All],3),0),11,H58,12,I58,13,J58,14,K58,"N/A")} -> 13 | G58: {=_xlfn.SWITCH(ROUND(VLOOKUP(A58,Table1[#All],5),0),11,H58,12,I58,13,J58,14,K58,"N/A")} -> 14 | H58: =IF(OR('Raw Data'!H56=0,'Raw Data'!H56="Delete"),"",'Raw Data'!H56) -> 13 | I58: =IF(OR('Raw Data'!I56=0,'Raw Data'!I56="Delete"),"",'Raw Data'!I56) -> 14 | J58: =IF(OR('Raw Data'!J56=0,'Raw Data'!J56="Delete"),"",'Raw Data'!J56) | K58: =IF(OR('Raw Data'!K56=0,'Raw Data'!K56="Delete"),"",'Raw Data'!K56) | L58: =R58 -> Available | M58: =IF(A58="","",IF(OR(AWReleaseNum>=A58,AWReleaseNum=0),"Available","Not Supported")) -> Available | N58: =IF(A58="","",IF(TcRelease="Any","Available",IF(OR(AND(TcReleaseNum>=VLOOKUP(AWReleaseNum,MinVerInfo,3,FALSE),TcReleaseNum<=VLOOKUP(AWReleaseNum,MinVerInfo,4,FALSE)),AND(TcReleaseNum>=VLOOKUP(AWReleaseNum,MinVerInfo,5,FALSE),TcReleaseNum<=VLOOKUP(AWReleaseNum,MinVerInfo,6,FALSE))),"Available","Not Supported"))) -> Available | O58: =IF(TcReleaseNum<P58,"Not Supported","Available") -> Available | P58: {=_xlfn.SWITCH(TcBaseVer, 14, K58, 13, J58, 12, I58, 11, IFERROR(VLOOKUP(H58,Table2[#All],3,FALSE),"N/A"),0)} -> 0 | Q58: =IF(TcBaseVer=0,M58,IF(AND(N58="Available",M58="Available",O58="Available"),"Available",IF(M58="","","Not Supported"))) -> Available | R58: =IF(A58>=AWCurrentRel, "Future",Q58) -> Available | S58: =HYPERLINK(U58,T58) -> Not Available | T58: =IFERROR(VLOOKUP(CONCATENATE($B58,"_",$A58),Table4[#All],5,FALSE),"Not Available") -> Not Available | U58: =IFERROR(VLOOKUP(CONCATENATE(B58,"_",A58),Table4[#All],6,FALSE),"")
A59: =IF(OR('Raw Data'!A57=0,'Raw Data'!A57="Delete"),"",'Raw Data'!A57) -> 2.1 | B59: =IF(OR('Raw Data'!B57=0,'Raw Data'!B57="Delete"),"",'Raw Data'!B57) -> Foundation | C59: =IF(OR('Raw Data'!C57=0,'Raw Data'!C57="Delete"),"",'Raw Data'!C57) -> Connectivity | D59: =IF(OR('Raw Data'!D57=0,'Raw Data'!D57="Delete"),"",'Raw Data'!D57) -> Active Integration | E59: =IF(OR('Raw Data'!E57=0,'Raw Data'!E57="Delete"),"",'Raw Data'!E57) -> Open in host | F59: {=_xlfn.SWITCH(ROUND(VLOOKUP(A59,Table1[#All],3),0),11,H59,12,I59,13,J59,14,K59,"N/A")} -> 13 | G59: {=_xlfn.SWITCH(ROUND(VLOOKUP(A59,Table1[#All],5),0),11,H59,12,I59,13,J59,14,K59,"N/A")} -> 14 | H59: =IF(OR('Raw Data'!H57=0,'Raw Data'!H57="Delete"),"",'Raw Data'!H57) -> 13 | I59: =IF(OR('Raw Data'!I57=0,'Raw Data'!I57="Delete"),"",'Raw Data'!I57) -> 14 | J59: =IF(OR('Raw Data'!J57=0,'Raw Data'!J57="Delete"),"",'Raw Data'!J57) | K59: =IF(OR('Raw Data'!K57=0,'Raw Data'!K57="Delete"),"",'Raw Data'!K57) | L59: =R59 -> Available | M59: =IF(A59="","",IF(OR(AWReleaseNum>=A59,AWReleaseNum=0),"Available","Not Supported")) -> Available | N59: =IF(A59="","",IF(TcRelease="Any","Available",IF(OR(AND(TcReleaseNum>=VLOOKUP(AWReleaseNum,MinVerInfo,3,FALSE),TcReleaseNum<=VLOOKUP(AWReleaseNum,MinVerInfo,4,FALSE)),AND(TcReleaseNum>=VLOOKUP(AWReleaseNum,MinVerInfo,5,FALSE),TcReleaseNum<=VLOOKUP(AWReleaseNum,MinVerInfo,6,FALSE))),"Available","Not Supported"))) -> Available | O59: =IF(TcReleaseNum<P59,"Not Supported","Available") -> Available | P59: {=_xlfn.SWITCH(TcBaseVer, 14, K59, 13, J59, 12, I59, 11, IFERROR(VLOOKUP(H59,Table2[#All],3,FALSE),"N/A"),0)} -> 0 | Q59: =IF(TcBaseVer=0,M59,IF(AND(N59="Available",M59="Available",O59="Available"),"Available",IF(M59="","","Not Supported"))) -> Available | R59: =IF(A59>=AWCurrentRel, "Future",Q59) -> Available | S59: =HYPERLINK(U59,T59) -> Not Available | T59: =IFERROR(VLOOKUP(CONCATENATE($B59,"_",$A59),Table4[#All],5,FALSE),"Not Available") -> Not Available | U59: =IFERROR(VLOOKUP(CONCATENATE(B59,"_",A59),Table4[#All],6,FALSE),"")
A60: =IF(OR('Raw Data'!A58=0,'Raw Data'!A58="Delete"),"",'Raw Data'!A58) -> 2.1 | B60: =IF(OR('Raw Data'!B58=0,'Raw Data'!B58="Delete"),"",'Raw Data'!B58) -> Foundation | C60: =IF(OR('Raw Data'!C58=0,'Raw Data'!C58="Delete"),"",'Raw Data'!C58) -> Connectivity | D60: =IF(OR('Raw Data'!D58=0,'Raw Data'!D58="Delete"),"",'Raw Data'!D58) -> Active Integration | E60: =IF(OR('Raw Data'!E58=0,'Raw Data'!E58="Delete"),"",'Raw Data'!E58) -> Show in Active Workspace | F60: {=_xlfn.SWITCH(ROUND(VLOOKUP(A60,Table1[#All],3),0),11,H60,12,I60,13,J60,14,K60,"N/A")} -> 13 | G60: {=_xlfn.SWITCH(ROUND(VLOOKUP(A60,Table1[#All],5),0),11,H60,12,I60,13,J60,14,K60,"N/A")} -> 14 | H60: =IF(OR('Raw Data'!H58=0,'Raw Data'!H58="Delete"),"",'Raw Data'!H58) -> 13 | I60: =IF(OR('Raw Data'!I58=0,'Raw Data'!I58="Delete"),"",'Raw Data'!I58) -> 14 | J60: =IF(OR('Raw Data'!J58=0,'Raw Data'!J58="Delete"),"",'Raw Data'!J58) | K60: =IF(OR('Raw Data'!K58=0,'Raw Data'!K58="Delete"),"",'Raw Data'!K58) | L60: =R60 -> Available | M60: =IF(A60="","",IF(OR(AWReleaseNum>=A60,AWReleaseNum=0),"Available","Not Supported")) -> Available | N60: =IF(A60="","",IF(TcRelease="Any","Available",IF(OR(AND(TcReleaseNum>=VLOOKUP(AWReleaseNum,MinVerInfo,3,FALSE),TcReleaseNum<=VLOOKUP(AWReleaseNum,MinVerInfo,4,FALSE)),AND(TcReleaseNum>=VLOOKUP(AWReleaseNum,MinVerInfo,5,FALSE),TcReleaseNum<=VLOOKUP(AWReleaseNum,MinVerInfo,6,FALSE))),"Available","Not Supported"))) -> Available | O60: =IF(TcReleaseNum<P60,"Not Supported","Available") -> Available | P60: {=_xlfn.SWITCH(TcBaseVer, 14, K60, 13, J60, 12, I60, 11, IFERROR(VLOOKUP(H60,Table2[#All],3,FALSE),"N/A"),0)} -> 0 | Q60: =IF(TcBaseVer=0,M60,IF(AND(N60="Available",M60="Available",O60="Available"),"Available",IF(M60="","","Not Supported"))) -> Available | R60: =IF(A60>=AWCurrentRel, "Future",Q60) -> Available | S60: =HYPERLINK(U60,T60) -> Not Available | T60: =IFERROR(VLOOKUP(CONCATENATE($B60,"_",$A60),Table4[#All],5,FALSE),"Not Available") -> Not Available | U60: =IFERROR(VLOOKUP(CONCATENATE(B60,"_",A60),Table4[#All],6,FALSE),"")
A61: =IF(OR('Raw Data'!A59=0,'Raw Data'!A59="Delete"),"",'Raw Data'!A59) -> 2.1 | B61: =IF(OR('Raw Data'!B59=0,'Raw Data'!B59="Delete"),"",'Raw Data'!B59) -> Foundation | C61: =IF(OR('Raw Data'!C59=0,'Raw Data'!C59="Delete"),"",'Raw Data'!C59) -> Connectivity | D61: =IF(OR('Raw Data'!D59=0,'Raw Data'!D59="Delete"),"",'Raw Data'!D59) -> Active Integration | E61: =IF(OR('Raw Data'!E59=0,'Raw Data'!E59="Delete"),"",'Raw Data'!E59) -> Common selection bus and command interoperability | F61: {=_xlfn.SWITCH(ROUND(VLOOKUP(A61,Table1[#All],3),0),11,H61,12,I61,13,J61,14,K61,"N/A")} -> 13 | G61: {=_xlfn.SWITCH(ROUND(VLOOKUP(A61,Table1[#All],5),0),11,H61,12,I61,13,J61,14,K61,"N/A")} -> 14 | H61: =IF(OR('Raw Data'!H59=0,'Raw Data'!H59="Delete"),"",'Raw Data'!H59) -> 13 | I61: =IF(OR('Raw Data'!I59=0,'Raw Data'!I59="Delete"),"",'Raw Data'!I59) -> 14 | J61: =IF(OR('Raw Data'!J59=0,'Raw Data'!J59="Delete"),"",'Raw Data'!J59) | K61: =IF(OR('Raw Data'!K59=0,'Raw Data'!K59="Delete"),"",'Raw Data'!K59) | L61: =R61 -> Available | M61: =IF(A61="","",IF(OR(AWReleaseNum>=A61,AWReleaseNum=0),"Available","Not Supported")) -> Available | N61: =IF(A61="","",IF(TcRelease="Any","Available",IF(OR(AND(TcReleaseNum>=VLOOKUP(AWReleaseNum,MinVerInfo,3,FALSE),TcReleaseNum<=VLOOKUP(AWReleaseNum,MinVerInfo,4,FALSE)),AND(TcReleaseNum>=VLOOKUP(AWReleaseNum,MinVerInfo,5,FALSE),TcReleaseNum<=VLOOKUP(AWReleaseNum,MinVerInfo,6,FALSE))),"Available","Not Supported"))) -> Available | O61: =IF(TcReleaseNum<P61,"Not Supported","Available") -> Available | P61: {=_xlfn.SWITCH(TcBaseVer, 14, K61, 13, J61, 12, I61, 11, IFERROR(VLOOKUP(H61,Table2[#All],3,FALSE),"N/A"),0)} -> 0 | Q61: =IF(TcBaseVer=0,M61,IF(AND(N61="Available",M61="Available",O61="Available"),"Available",IF(M61="","","Not Supported"))) -> Available | R61: =IF(A61>=AWCurrentRel, "Future",Q61) -> Available | S61: =HYPERLINK(U61,T61) -> Not Available | T61: =IFERROR(VLOOKUP(CONCATENATE($B61,"_",$A61),Table4[#All],5,FALSE),"Not Available") -> Not Available | U61: =IFERROR(VLOOKUP(CONCATENATE(B61,"_",A61),Table4[#All],6,FALSE),"")
A62: =IF(OR('Raw Data'!A10=0,'Raw Data'!A10="Delete"),"",'Raw Data'!A10) -> 2.1 | B62: =IF(OR('Raw Data'!B10=0,'Raw Data'!B10="Delete"),"",'Raw Data'!B10) -> Plan | C62: =IF(OR('Raw Data'!C10=0,'Raw Data'!C10="Delete"),"",'Raw Data'!C10) -> Process | D62: =IF(OR('Raw Data'!D10=0,'Raw Data'!D10="Delete"),"",'Raw Data'!D10) -> Change Management | E62: =IF(OR('Raw Data'!E10=0,'Raw Data'!E10="Delete"),"",'Raw Data'!E10) -> Report problem directly from Home Page | F62: {=_xlfn.SWITCH(ROUND(VLOOKUP(A62,Table1[#All],3),0),11,H62,12,I62,13,J62,14,K62,"N/A")} -> 13 | G62: {=_xlfn.SWITCH(ROUND(VLOOKUP(A62,Table1[#All],5),0),11,H62,12,I62,13,J62,14,K62,"N/A")} -> 14 | H62: =IF(OR('Raw Data'!H10=0,'Raw Data'!H10="Delete"),"",'Raw Data'!H10) -> 13 | I62: =IF(OR('Raw Data'!I10=0,'Raw Data'!I10="Delete"),"",'Raw Data'!I10) -> 14 | J62: =IF(OR('Raw Data'!J10=0,'Raw Data'!J10="Delete"),"",'Raw Data'!J10) | K62: =IF(OR('Raw Data'!K10=0,'Raw Data'!K10="Delete"),"",'Raw Data'!K10) | L62: =R62 -> Available | M62: =IF(A62="","",IF(OR(AWReleaseNum>=A62,AWReleaseNum=0),"Available","Not Supported")) -> Available | N62: =IF(A62="","",IF(TcRelease="Any","Available",IF(OR(AND(TcReleaseNum>=VLOOKUP(AWReleaseNum,MinVerInfo,3,FALSE),TcReleaseNum<=VLOOKUP(AWReleaseNum,MinVerInfo,4,FALSE)),AND(TcReleaseNum>=VLOOKUP(AWReleaseNum,MinVerInfo,5,FALSE),TcReleaseNum<=VLOOKUP(AWReleaseNum,MinVerInfo,6,FALSE))),"Available","Not Supported"))) -> Available | O62: =IF(TcReleaseNum<P62,"Not Supported","Available") -> Available | P62: {=_xlfn.SWITCH(TcBaseVer, 14, K62, 13, J62, 12, I62, 11, IFERROR(VLOOKUP(H62,Table2[#All],3,FALSE),"N/A"),0)} -> 0 | Q62: =IF(TcBaseVer=0,M62,IF(AND(N62="Available",M62="Available",O62="Available"),"Available",IF(M62="","","Not Supported"))) -> Available | R62: =IF(A62>=AWCurrentRel, "Future",Q62) -> Available | S62: =HYPERLINK(U62,T62) -> Not Available | T62: =IFERROR(VLOOKUP(CONCATENATE($B62,"_",$A62),Table4[#All],5,FALSE),"Not Available") -> Not Available | U62: =IFERROR(VLOOKUP(CONCATENATE(B62,"_",A62),Table4[#All],6,FALSE),"")
A63: =IF(OR('Raw Data'!A71=0,'Raw Data'!A71="Delete"),"",'Raw Data'!A71) -> 2.1 | B63: =IF(OR('Raw Data'!B71=0,'Raw Data'!B71="Delete"),"",'Raw Data'!B71) -> Foundation | C63: =IF(OR('Raw Data'!C71=0,'Raw Data'!C71="Delete"),"",'Raw Data'!C71) -> Deployability | D63: =IF(OR('Raw Data'!D71=0,'Raw Data'!D71="Delete"),"",'Raw Data'!D71) -> Deployability | E63: =IF(OR('Raw Data'!E71=0,'Raw Data'!E71="Delete"),"",'Raw Data'!E71) -> Improved search performance and robustness | F63: {=_xlfn.SWITCH(ROUND(VLOOKUP(A63,Table1[#All],3),0),11,H63,12,I63,13,J63,14,K63,"N/A")} -> 13 | G63: {=_xlfn.SWITCH(ROUND(VLOOKUP(A63,Table1[#All],5),0),11,H63,12,I63,13,J63,14,K63,"N/A")} -> 14 | H63: =IF(OR('Raw Data'!H71=0,'Raw Data'!H71="Delete"),"",'Raw Data'!H71) -> 13 | I63: =IF(OR('Raw Data'!I71=0,'Raw Data'!I71="Delete"),"",'Raw Data'!I71) -> 14 | J63: =IF(OR('Raw Data'!J71=0,'Raw Data'!J71="Delete"),"",'Raw Data'!J71) | K63: =IF(OR('Raw Data'!K71=0,'Raw Data'!K71="Delete"),"",'Raw Data'!K71) | L63: =R63 -> Available | M63: =IF(A63="","",IF(OR(AWReleaseNum>=A63,AWReleaseNum=0),"Available","Not Supported")) -> Available | N63: =IF(A63="","",IF(TcRelease="Any","Available",IF(OR(AND(TcReleaseNum>=VLOOKUP(AWReleaseNum,MinVerInfo,3,FALSE),TcReleaseNum<=VLOOKUP(AWReleaseNum,MinVerInfo,4,FALSE)),AND(TcReleaseNum>=VLOOKUP(AWReleaseNum,MinVerInfo,5,FALSE),TcReleaseNum<=VLOOKUP(AWReleaseNum,MinVerInfo,6,FALSE))),"Available","Not Supported"))) -> Available | O63: =IF(TcReleaseNum<P63,"Not Supported","Available") -> Available | P63: {=_xlfn.SWITCH(TcBaseVer, 14, K63, 13, J63, 12, I63, 11, IFERROR(VLOOKUP(H63,Table2[#All],3,FALSE),"N/A"),0)} -> 0 | Q63: =IF(TcBaseVer=0,M63,IF(AND(N63="Available",M63="Available",O63="Available"),"Available",IF(M63="","","Not Supported"))) -> Available | R63: =IF(A63>=AWCurrentRel, "Future",Q63) -> Available | S63: =HYPERLINK(U63,T63) -> Not Available | T63: =IFERROR(VLOOKUP(CONCATENATE($B63,"_",$A63),Table4[#All],5,FALSE),"Not Available") -> Not Available | U63: =IFERROR(VLOOKUP(CONCATENATE(B63,"_",A63),Table4[#All],6,FALSE),"")
A64: =IF(OR('Raw Data'!A72=0,'Raw Data'!A72="Delete"),"",'Raw Data'!A72) -> 2.1 | B64: =IF(OR('Raw Data'!B72=0,'Raw Data'!B72="Delete"),"",'Raw Data'!B72) -> Foundation | C64: =IF(OR('Raw Data'!C72=0,'Raw Data'!C72="Delete"),"",'Raw Data'!C72) -> Deployability | D64: =IF(OR('Raw Data'!D72=0,'Raw Data'!D72="Delete"),"",'Raw Data'!D72) -> Deployability | E64: =IF(OR('Raw Data'!E72=0,'Raw Data'!E72="Delete"),"",'Raw Data'!E72) -> Improved and automated server-side install | F64: {=_xlfn.SWITCH(ROUND(VLOOKUP(A64,Table1[#All],3),0),11,H64,12,I64,13,J64,14,K64,"N/A")} -> 13 | G64: {=_xlfn.SWITCH(ROUND(VLOOKUP(A64,Table1[#All],5),0),11,H64,12,I64,13,J64,14,K64,"N/A")} -> 14 | H64: =IF(OR('Raw Data'!H72=0,'Raw Data'!H72="Delete"),"",'Raw Data'!H72) -> 13 | I64: =IF(OR('Raw Data'!I72=0,'Raw Data'!I72="Delete"),"",'Raw Data'!I72) -> 14 | J64: =IF(OR('Raw Data'!J72=0,'Raw Data'!J72="Delete"),"",'Raw Data'!J72) | K64: =IF(OR('Raw Data'!K72=0,'Raw Data'!K72="Delete"),"",'Raw Data'!K72) | L64: =R64 -> Available | M64: =IF(A64="","",IF(OR(AWReleaseNum>=A64,AWReleaseNum=0),"Available","Not Supported")) -> Available | N64: =IF(A64="","",IF(TcRelease="Any","Available",IF(OR(AND(TcReleaseNum>=VLOOKUP(AWReleaseNum,MinVerInfo,3,FALSE),TcReleaseNum<=VLOOKUP(AWReleaseNum,MinVerInfo,4,FALSE)),AND(TcReleaseNum>=VLOOKUP(AWReleaseNum,MinVerInfo,5,FALSE),TcReleaseNum<=VLOOKUP(AWReleaseNum,MinVerInfo,6,FALSE))),"Available","Not Supported"))) -> Available | O64: =IF(TcReleaseNum<P64,"Not Supported","Available") -> Available | P64: {=_xlfn.SWITCH(TcBaseVer, 14, K64, 13, J64, 12, I64, 11, IFERROR(VLOOKUP(H64,Table2[#All],3,FALSE),"N/A"),0)} -> 0 | Q64: =IF(TcBaseVer=0,M64,IF(AND(N64="Available",M64="Available",O64="Available"),"Available",IF(M64="","","Not Supported"))) -> Available | R64: =IF(A64>=AWCurrentRel, "Future",Q64) -> Available | S64: =HYPERLINK(U64,T64) -> Not Available | T64: =IFERROR(VLOOKUP(CONCATENATE($B64,"_",$A64),Table4[#All],5,FALSE),"Not Available") -> Not Available | U64: =IFERROR(VLOOKUP(CONCATENATE(B64,"_",A64),Table4[#All],6,FALSE),"")
A65: =IF(OR('Raw Data'!A73=0,'Raw Data'!A73="Delete"),"",'Raw Data'!A73) -> 2.1 | B65: =IF(OR('Raw Data'!B73=0,'Raw Data'!B73="Delete"),"",'Raw Data'!B73) -> Foundation | C65: =IF(OR('Raw Data'!C73=0,'Raw Data'!C73="Delete"),"",'Raw Data'!C73) -> Deployability | D65: =IF(OR('Raw Data'!D73=0,'Raw Data'!D73="Delete"),"",'Raw Data'!D73) -> Deployability | E65: =IF(OR('Raw Data'!E73=0,'Raw Data'!E73="Delete"),"",'Raw Data'!E73) -> Improved deployability | F65: {=_xlfn.SWITCH(ROUND(VLOOKUP(A65,Table1[#All],3),0),11,H65,12,I65,13,J65,14,K65,"N/A")} -> 13 | G65: {=_xlfn.SWITCH(ROUND(VLOOKUP(A65,Table1[#All],5),0),11,H65,12,I65,13,J65,14,K65,"N/A")} -> 14 | H65: =IF(OR('Raw Data'!H73=0,'Raw Data'!H73="Delete"),"",'Raw Data'!H73) -> 13 | I65: =IF(OR('Raw Data'!I73=0,'Raw Data'!I73="Delete"),"",'Raw Data'!I73) -> 14 | J65: =IF(OR('Raw Data'!J73=0,'Raw Data'!J73="Delete"),"",'Raw Data'!J73) | K65: =IF(OR('Raw Data'!K73=0,'Raw Data'!K73="Delete"),"",'Raw Data'!K73) | L65: =R65 -> Available | M65: =IF(A65="","",IF(OR(AWReleaseNum>=A65,AWReleaseNum=0),"Available","Not Supported")) -> Available | N65: =IF(A65="","",IF(TcRelease="Any","Available",IF(OR(AND(TcReleaseNum>=VLOOKUP(AWReleaseNum,MinVerInfo,3,FALSE),TcReleaseNum<=VLOOKUP(AWReleaseNum,MinVerInfo,4,FALSE)),AND(TcReleaseNum>=VLOOKUP(AWReleaseNum,MinVerInfo,5,FALSE),TcReleaseNum<=VLOOKUP(AWReleaseNum,MinVerInfo,6,FALSE))),"Available","Not Supported"))) -> Available | O65: =IF(TcReleaseNum<P65,"Not Supported","Available") -> Available | P65: {=_xlfn.SWITCH(TcBaseVer, 14, K65, 13, J65, 12, I65, 11, IFERROR(VLOOKUP(H65,Table2[#All],3,FALSE),"N/A"),0)} -> 0 | Q65: =IF(TcBaseVer=0,M65,IF(AND(N65="Available",M65="Available",O65="Available"),"Available",IF(M65="","","Not Supported"))) -> Available | R65: =IF(A65>=AWCurrentRel, "Future",Q65) -> Available | S65: =HYPERLINK(U65,T65) -> Not Available | T65: =IFERROR(VLOOKUP(CONCATENATE($B65,"_",$A65),Table4[#All],5,FALSE),"Not Available") -> Not Available | U65: =IFERROR(VLOOKUP(CONCATENATE(B65,"_",A65),Table4[#All],6,FALSE),"")
A66: =IF(OR('Raw Data'!A74=0,'Raw Data'!A74="Delete"),"",'Raw Data'!A74) -> 2.1 | B66: =IF(OR('Raw Data'!B74=0,'Raw Data'!B74="Delete"),"",'Raw Data'!B74) -> Foundation | C66: =IF(OR('Raw Data'!C74=0,'Raw Data'!C74="Delete"),"",'Raw Data'!C74) -> Deployability | D66: =IF(OR('Raw Data'!D74=0,'Raw Data'!D74="Delete"),"",'Raw Data'!D74) -> Deployability | E66: =IF(OR('Raw Data'!E74=0,'Raw Data'!E74="Delete"),"",'Raw Data'!E74) -> Windows, Linux, Solaris, and AIX Server Support | F66: {=_xlfn.SWITCH(ROUND(VLOOKUP(A66,Table1[#All],3),0),11,H66,12,I66,13,J66,14,K66,"N/A")} -> 13 | G66: {=_xlfn.SWITCH(ROUND(VLOOKUP(A66,Table1[#All],5),0),11,H66,12,I66,13,J66,14,K66,"N/A")} -> 14 | H66: =IF(OR('Raw Data'!H74=0,'Raw Data'!H74="Delete"),"",'Raw Data'!H74) -> 13 | I66: =IF(OR('Raw Data'!I74=0,'Raw Data'!I74="Delete"),"",'Raw Data'!I74) -> 14 | J66: =IF(OR('Raw Data'!J74=0,'Raw Data'!J74="Delete"),"",'Raw Data'!J74) | K66: =IF(OR('Raw Data'!K74=0,'Raw Data'!K74="Delete"),"",'Raw Data'!K74) | L66: =R66 -> Available | M66: =IF(A66="","",IF(OR(AWReleaseNum>=A66,AWReleaseNum=0),"Available","Not Supported")) -> Available | N66: =IF(A66="","",IF(TcRelease="Any","Available",IF(OR(AND(TcReleaseNum>=VLOOKUP(AWReleaseNum,MinVerInfo,3,FALSE),TcReleaseNum<=VLOOKUP(AWReleaseNum,MinVerInfo,4,FALSE)),AND(TcReleaseNum>=VLOOKUP(AWReleaseNum,MinVerInfo,5,FALSE),TcReleaseNum<=VLOOKUP(AWReleaseNum,MinVerInfo,6,FALSE))),"Available","Not Supported"))) -> Available | O66: =IF(TcReleaseNum<P66,"Not Supported","Available") -> Available | P66: {=_xlfn.SWITCH(TcBaseVer, 14, K66, 13, J66, 12, I66, 11, IFERROR(VLOOKUP(H66,Table2[#All],3,FALSE),"N/A"),0)} -> 0 | Q66: =IF(TcBaseVer=0,M66,IF(AND(N66="Available",M66="Available",O66="Available"),"Available",IF(M66="","","Not Supported"))) -> Available | R66: =IF(A66>=AWCurrentRel, "Future",Q66) -> Available | S66: =HYPERLINK(U66,T66) -> Not Available | T66: =IFERROR(VLOOKUP(CONCATENATE($B66,"_",$A66),Table4[#All],5,FALSE),"Not Available") -> Not Available | U66: =IFERROR(VLOOKUP(CONCATENATE(B66,"_",A66),Table4[#All],6,FALSE),"")
A67: =IF(OR('Raw Data'!A75=0,'Raw Data'!A75="Delete"),"",'Raw Data'!A75) -> 2.1 | B67: =IF(OR('Raw Data'!B75=0,'Raw Data'!B75="Delete"),"",'Raw Data'!B75) -> Develop | C67: =IF(OR('Raw Data'!C75=0,'Raw Data'!C75="Delete"),"",'Raw Data'!C75) -> Mechanical | D67: =IF(OR('Raw Data'!D75=0,'Raw Data'!D75="Delete"),"",'Raw Data'!D75) -> Design Management | E67: =IF(OR('Raw Data'!E75=0,'Raw Data'!E75="Delete"),"",'Raw Data'!E75) -> Open parts in NX to edit the models | F67: {=_xlfn.SWITCH(ROUND(VLOOKUP(A67,Table1[#All],3),0),11,H67,12,I67,13,J67,14,K67,"N/A")} -> 13 | G67: {=_xlfn.SWITCH(ROUND(VLOOKUP(A67,Table1[#All],5),0),11,H67,12,I67,13,J67,14,K67,"N/A")} -> 14 | H67: =IF(OR('Raw Data'!H75=0,'Raw Data'!H75="Delete"),"",'Raw Data'!H75) -> 13 | I67: =IF(OR('Raw Data'!I75=0,'Raw Data'!I75="Delete"),"",'Raw Data'!I75) -> 14 | J67: =IF(OR('Raw Data'!J75=0,'Raw Data'!J75="Delete"),"",'Raw Data'!J75) | K67: =IF(OR('Raw Data'!K75=0,'Raw Data'!K75="Delete"),"",'Raw Data'!K75) | L67: =R67 -> Available | M67: =IF(A67="","",IF(OR(AWReleaseNum>=A67,AWReleaseNum=0),"Available","Not Supported")) -> Available | N67: =IF(A67="","",IF(TcRelease="Any","Available",IF(OR(AND(TcReleaseNum>=VLOOKUP(AWReleaseNum,MinVerInfo,3,FALSE),TcReleaseNum<=VLOOKUP(AWReleaseNum,MinVerInfo,4,FALSE)),AND(TcReleaseNum>=VLOOKUP(AWReleaseNum,MinVerInfo,5,FALSE),TcReleaseNum<=VLOOKUP(AWReleaseNum,MinVerInfo,6,FALSE))),"Available","Not Supported"))) -> Available | O67: =IF(TcReleaseNum<P67,"Not Supported","Available") -> Available | P67: {=_xlfn.SWITCH(TcBaseVer, 14, K67, 13, J67, 12, I67, 11, IFERROR(VLOOKUP(H67,Table2[#All],3,FALSE),"N/A"),0)} -> 0 | Q67: =IF(TcBaseVer=0,M67,IF(AND(N67="Available",M67="Available",O67="Available"),"Available",IF(M67="","","Not Supported"))) -> Available | R67: =IF(A67>=AWCurrentRel, "Future",Q67) -> Available | S67: =HYPERLINK(U67,T67) -> Not Available | T67: =IFERROR(VLOOKUP(CONCATENATE($B67,"_",$A67),Table4[#All],5,FALSE),"Not Available") -> Not Available | U67: =IFERROR(VLOOKUP(CONCATENATE(B67,"_",A67),Table4[#All],6,FALSE),"")
A68: =IF(OR('Raw Data'!A76=0,'Raw Data'!A76="Delete"),"",'Raw Data'!A76) -> 2.1 | B68: =IF(OR('Raw Data'!B76=0,'Raw Data'!B76="Delete"),"",'Raw Data'!B76) -> Develop | C68: =IF(OR('Raw Data'!C76=0,'Raw Data'!C76="Delete"),"",'Raw Data'!C76) -> Documents | D68: =IF(OR('Raw Data'!D76=0,'Raw Data'!D76="Delete"),"",'Raw Data'!D76) -> Document Management | E68: =IF(OR('Raw Data'!E76=0,'Raw Data'!E76="Delete"),"",'Raw Data'!E76) -> Edit and Save Office documents using Office Integration | F68: {=_xlfn.SWITCH(ROUND(VLOOKUP(A68,Table1[#All],3),0),11,H68,12,I68,13,J68,14,K68,"N/A")} -> 13 | G68: {=_xlfn.SWITCH(ROUND(VLOOKUP(A68,Table1[#All],5),0),11,H68,12,I68,13,J68,14,K68,"N/A")} -> 14 | H68: =IF(OR('Raw Data'!H76=0,'Raw Data'!H76="Delete"),"",'Raw Data'!H76) -> 13 | I68: =IF(OR('Raw Data'!I76=0,'Raw Data'!I76="Delete"),"",'Raw Data'!I76) -> 14 | J68: =IF(OR('Raw Data'!J76=0,'Raw Data'!J76="Delete"),"",'Raw Data'!J76) | K68: =IF(OR('Raw Data'!K76=0,'Raw Data'!K76="Delete"),"",'Raw Data'!K76) | L68: =R68 -> Available | M68: =IF(A68="","",IF(OR(AWReleaseNum>=A68,AWReleaseNum=0),"Available","Not Supported")) -> Available | N68: =IF(A68="","",IF(TcRelease="Any","Available",IF(OR(AND(TcReleaseNum>=VLOOKUP(AWReleaseNum,MinVerInfo,3,FALSE),TcReleaseNum<=VLOOKUP(AWReleaseNum,MinVerInfo,4,FALSE)),AND(TcReleaseNum>=VLOOKUP(AWReleaseNum,MinVerInfo,5,FALSE),TcReleaseNum<=VLOOKUP(AWReleaseNum,MinVerInfo,6,FALSE))),"Available","Not Supported"))) -> Available | O68: =IF(TcReleaseNum<P68,"Not Supported","Available") -> Available | P68: {=_xlfn.SWITCH(TcBaseVer, 14, K68, 13, J68, 12, I68, 11, IFERROR(VLOOKUP(H68,Table2[#All],3,FALSE),"N/A"),0)} -> 0 | Q68: =IF(TcBaseVer=0,M68,IF(AND(N68="Available",M68="Available",O68="Available"),"Available",IF(M68="","","Not Supported"))) -> Available | R68: =IF(A68>=AWCurrentRel, "Future",Q68) -> Available | S68: =HYPERLINK(U68,T68) -> Not Available | T68: =IFERROR(VLOOKUP(CONCATENATE($B68,"_",$A68),Table4[#All],5,FALSE),"Not Available") -> Not Available | U68: =IFERROR(VLOOKUP(CONCATENATE(B68,"_",A68),Table4[#All],6,FALSE),"")
A69: =IF(OR('Raw Data'!A77=0,'Raw Data'!A77="Delete"),"",'Raw Data'!A77) -> 2.1 | B69: =IF(OR('Raw Data'!B77=0,'Raw Data'!B77="Delete"),"",'Raw Data'!B77) -> Develop | C69: =IF(OR('Raw Data'!C77=0,'Raw Data'!C77="Delete"),"",'Raw Data'!C77) -> Documents | D69: =IF(OR('Raw Data'!D77=0,'Raw Data'!D77="Delete"),"",'Raw Data'!D77) -> Document Management | E69: =IF(OR('Raw Data'!E77=0,'Raw Data'!E77="Delete"),"",'Raw Data'!E77) -> Markup in neutral format | F69: {=_xlfn.SWITCH(ROUND(VLOOKUP(A69,Table1[#All],3),0),11,H69,12,I69,13,J69,14,K69,"N/A")} -> 13 | G69: {=_xlfn.SWITCH(ROUND(VLOOKUP(A69,Table1[#All],5),0),11,H69,12,I69,13,J69,14,K69,"N/A")} -> 14 | H69: =IF(OR('Raw Data'!H77=0,'Raw Data'!H77="Delete"),"",'Raw Data'!H77) -> 13 | I69: =IF(OR('Raw Data'!I77=0,'Raw Data'!I77="Delete"),"",'Raw Data'!I77) -> 14 | J69: =IF(OR('Raw Data'!J77=0,'Raw Data'!J77="Delete"),"",'Raw Data'!J77) | K69: =IF(OR('Raw Data'!K77=0,'Raw Data'!K77="Delete"),"",'Raw Data'!K77) | L69: =R69 -> Available | M69: =IF(A69="","",IF(OR(AWReleaseNum>=A69,AWReleaseNum=0),"Available","Not Supported")) -> Available | N69: =IF(A69="","",IF(TcRelease="Any","Available",IF(OR(AND(TcReleaseNum>=VLOOKUP(AWReleaseNum,MinVerInfo,3,FALSE),TcReleaseNum<=VLOOKUP(AWReleaseNum,MinVerInfo,4,FALSE)),AND(TcReleaseNum>=VLOOKUP(AWReleaseNum,MinVerInfo,5,FALSE),TcReleaseNum<=VLOOKUP(AWReleaseNum,MinVerInfo,6,FALSE))),"Available","Not Supported"))) -> Available | O69: =IF(TcReleaseNum<P69,"Not Supported","Available") -> Available | P69: {=_xlfn.SWITCH(TcBaseVer, 14, K69, 13, J69, 12, I69, 11, IFERROR(VLOOKUP(H69,Table2[#All],3,FALSE),"N/A"),0)} -> 0 | Q69: =IF(TcBaseVer=0,M69,IF(AND(N69="Available",M69="Available",O69="Available"),"Available",IF(M69="","","Not Supported"))) -> Available | R69: =IF(A69>=AWCurrentRel, "Future",Q69) -> Available | S69: =HYPERLINK(U69,T69) -> Not Available | T69: =IFERROR(VLOOKUP(CONCATENATE($B69,"_",$A69),Table4[#All],5,FALSE),"Not Available") -> Not Available | U69: =IFERROR(VLOOKUP(CONCATENATE(B69,"_",A69),Table4[#All],6,FALSE),"")
A70: =IF(OR('Raw Data'!A78=0,'Raw Data'!A78="Delete"),"",'Raw Data'!A78) -> 2.1 | B70: =IF(OR('Raw Data'!B78=0,'Raw Data'!B78="Delete"),"",'Raw Data'!B78) -> Develop | C70: =IF(OR('Raw Data'!C78=0,'Raw Data'!C78="Delete"),"",'Raw Data'!C78) -> Documents | D70: =IF(OR('Raw Data'!D78=0,'Raw Data'!D78="Delete"),"",'Raw Data'!D78) -> Document Management | E70: =IF(OR('Raw Data'!E78=0,'Raw Data'!E78="Delete"),"",'Raw Data'!E78) -> Organize markups | F70: {=_xlfn.SWITCH(ROUND(VLOOKUP(A70,Table1[#All],3),0),11,H70,12,I70,13,J70,14,K70,"N/A")} -> 13 | G70: {=_xlfn.SWITCH(ROUND(VLOOKUP(A70,Table1[#All],5),0),11,H70,12,I70,13,J70,14,K70,"N/A")} -> 14 | H70: =IF(OR('Raw Data'!H78=0,'Raw Data'!H78="Delete"),"",'Raw Data'!H78) -> 13 | I70: =IF(OR('Raw Data'!I78=0,'Raw Data'!I78="Delete"),"",'Raw Data'!I78) -> 14 | J70: =IF(OR('Raw Data'!J78=0,'Raw Data'!J78="Delete"),"",'Raw Data'!J78) | K70: =IF(OR('Raw Data'!K78=0,'Raw Data'!K78="Delete"),"",'Raw Data'!K78) | L70: =R70 -> Available | M70: =IF(A70="","",IF(OR(AWReleaseNum>=A70,AWReleaseNum=0),"Available","Not Supported")) -> Available | N70: =IF(A70="","",IF(TcRelease="Any","Available",IF(OR(AND(TcReleaseNum>=VLOOKUP(AWReleaseNum,MinVerInfo,3,FALSE),TcReleaseNum<=VLOOKUP(AWReleaseNum,MinVerInfo,4,FALSE)),AND(TcReleaseNum>=VLOOKUP(AWReleaseNum,MinVerInfo,5,FALSE),TcReleaseNum<=VLOOKUP(AWReleaseNum,MinVerInfo,6,FALSE))),"Available","Not Supported"))) -> Available | O70: =IF(TcReleaseNum<P70,"Not Supported","Available") -> Available | P70: {=_xlfn.SWITCH(TcBaseVer, 14, K70, 13, J70, 12, I70, 11, IFERROR(VLOOKUP(H70,Table2[#All],3,FALSE),"N/A"),0)} -> 0 | Q70: =IF(TcBaseVer=0,M70,IF(AND(N70="Available",M70="Available",O70="Available"),"Available",IF(M70="","","Not Supported"))) -> Available | R70: =IF(A70>=AWCurrentRel, "Future",Q70) -> Available | S70: =HYPERLINK(U70,T70) -> Not Available | T70: =IFERROR(VLOOKUP(CONCATENATE($B70,"_",$A70),Table4[#All],5,FALSE),"Not Available") -> Not Available | U70: =IFERROR(VLOOKUP(CONCATENATE(B70,"_",A70),Table4[#All],6,FALSE),"")
A71: =IF(OR('Raw Data'!A79=0,'Raw Data'!A79="Delete"),"",'Raw Data'!A79) -> 2.1 | B71: =IF(OR('Raw Data'!B79=0,'Raw Data'!B79="Delete"),"",'Raw Data'!B79) -> Develop | C71: =IF(OR('Raw Data'!C79=0,'Raw Data'!C79="Delete"),"",'Raw Data'!C79) -> Documents | D71: =IF(OR('Raw Data'!D79=0,'Raw Data'!D79="Delete"),"",'Raw Data'!D79) -> Document Management | E71: =IF(OR('Raw Data'!E79=0,'Raw Data'!E79="Delete"),"",'Raw Data'!E79) -> Manage markup access | F71: {=_xlfn.SWITCH(ROUND(VLOOKUP(A71,Table1[#All],3),0),11,H71,12,I71,13,J71,14,K71,"N/A")} -> 13 | G71: {=_xlfn.SWITCH(ROUND(VLOOKUP(A71,Table1[#All],5),0),11,H71,12,I71,13,J71,14,K71,"N/A")} -> 14 | H71: =IF(OR('Raw Data'!H79=0,'Raw Data'!H79="Delete"),"",'Raw Data'!H79) -> 13 | I71: =IF(OR('Raw Data'!I79=0,'Raw Data'!I79="Delete"),"",'Raw Data'!I79) -> 14 | J71: =IF(OR('Raw Data'!J79=0,'Raw Data'!J79="Delete"),"",'Raw Data'!J79) | K71: =IF(OR('Raw Data'!K79=0,'Raw Data'!K79="Delete"),"",'Raw Data'!K79) | L71: =R71 -> Available | M71: =IF(A71="","",IF(OR(AWReleaseNum>=A71,AWReleaseNum=0),"Available","Not Supported")) -> Available | N71: =IF(A71="","",IF(TcRelease="Any","Available",IF(OR(AND(TcReleaseNum>=VLOOKUP(AWReleaseNum,MinVerInfo,3,FALSE),TcReleaseNum<=VLOOKUP(AWReleaseNum,MinVerInfo,4,FALSE)),AND(TcReleaseNum>=VLOOKUP(AWReleaseNum,MinVerInfo,5,FALSE),TcReleaseNum<=VLOOKUP(AWReleaseNum,MinVerInfo,6,FALSE))),"Available","Not Supported"))) -> Available | O71: =IF(TcReleaseNum<P71,"Not Supported","Available") -> Available | P71: {=_xlfn.SWITCH(TcBaseVer, 14, K71, 13, J71, 12, I71, 11, IFERROR(VLOOKUP(H71,Table2[#All],3,FALSE),"N/A"),0)} -> 0 | Q71: =IF(TcBaseVer=0,M71,IF(AND(N71="Available",M71="Available",O71="Available"),"Available",IF(M71="","","Not Supported"))) -> Available | R71: =IF(A71>=AWCurrentRel, "Future",Q71) -> Available | S71: =HYPERLINK(U71,T71) -> Not Available | T71: =IFERROR(VLOOKUP(CONCATENATE($B71,"_",$A71),Table4[#All],5,FALSE),"Not Available") -> Not Available | U71: =IFERROR(VLOOKUP(CONCATENATE(B71,"_",A71),Table4[#All],6,FALSE),"")
A72: =IF(OR('Raw Data'!A80=0,'Raw Data'!A80="Delete"),"",'Raw Data'!A80) -> 2.1 | B72: =IF(OR('Raw Data'!B80=0,'Raw Data'!B80="Delete"),"",'Raw Data'!B80) -> Develop | C72: =IF(OR('Raw Data'!C80=0,'Raw Data'!C80="Delete"),"",'Raw Data'!C80) -> Documents | D72: =IF(OR('Raw Data'!D80=0,'Raw Data'!D80="Delete"),"",'Raw Data'!D80) -> Document Management | E72: =IF(OR('Raw Data'!E80=0,'Raw Data'!E80="Delete"),"",'Raw Data'!E80) -> Markup discussion threads | F72: {=_xlfn.SWITCH(ROUND(VLOOKUP(A72,Table1[#All],3),0),11,H72,12,I72,13,J72,14,K72,"N/A")} -> 13 | G72: {=_xlfn.SWITCH(ROUND(VLOOKUP(A72,Table1[#All],5),0),11,H72,12,I72,13,J72,14,K72,"N/A")} -> 14 | H72: =IF(OR('Raw Data'!H80=0,'Raw Data'!H80="Delete"),"",'Raw Data'!H80) -> 13 | I72: =IF(OR('Raw Data'!I80=0,'Raw Data'!I80="Delete"),"",'Raw Data'!I80) -> 14 | J72: =IF(OR('Raw Data'!J80=0,'Raw Data'!J80="Delete"),"",'Raw Data'!J80) | K72: =IF(OR('Raw Data'!K80=0,'Raw Data'!K80="Delete"),"",'Raw Data'!K80) | L72: =R72 -> Available | M72: =IF(A72="","",IF(OR(AWReleaseNum>=A72,AWReleaseNum=0),"Available","Not Supported")) -> Available | N72: =IF(A72="","",IF(TcRelease="Any","Available",IF(OR(AND(TcReleaseNum>=VLOOKUP(AWReleaseNum,MinVerInfo,3,FALSE),TcReleaseNum<=VLOOKUP(AWReleaseNum,MinVerInfo,4,FALSE)),AND(TcReleaseNum>=VLOOKUP(AWReleaseNum,MinVerInfo,5,FALSE),TcReleaseNum<=VLOOKUP(AWReleaseNum,MinVerInfo,6,FALSE))),"Available","Not Supported"))) -> Available | O72: =IF(TcReleaseNum<P72,"Not Supported","Available") -> Available | P72: {=_xlfn.SWITCH(TcBaseVer, 14, K72, 13, J72, 12, I72, 11, IFERROR(VLOOKUP(H72,Table2[#All],3,FALSE),"N/A"),0)} -> 0 | Q72: =IF(TcBaseVer=0,M72,IF(AND(N72="Available",M72="Available",O72="Available"),"Available",IF(M72="","","Not Supported"))) -> Available | R72: =IF(A72>=AWCurrentRel, "Future",Q72) -> Available | S72: =HYPERLINK(U72,T72) -> Not Available | T72: =IFERROR(VLOOKUP(CONCATENATE($B72,"_",$A72),Table4[#All],5,FALSE),"Not Available") -> Not Available | U72: =IFERROR(VLOOKUP(CONCATENATE(B72,"_",A72),Table4[#All],6,FALSE),"")
A73: =IF(OR('Raw Data'!A81=0,'Raw Data'!A81="Delete"),"",'Raw Data'!A81) -> 2.1 | B73: =IF(OR('Raw Data'!B81=0,'Raw Data'!B81="Delete"),"",'Raw Data'!B81) -> Develop | C73: =IF(OR('Raw Data'!C81=0,'Raw Data'!C81="Delete"),"",'Raw Data'!C81) -> Documents | D73: =IF(OR('Raw Data'!D81=0,'Raw Data'!D81="Delete"),"",'Raw Data'!D81) -> Document Management | E73: =IF(OR('Raw Data'!E81=0,'Raw Data'!E81="Delete"),"",'Raw Data'!E81) -> Disposition and resolution tracking by comment | F73: {=_xlfn.SWITCH(ROUND(VLOOKUP(A73,Table1[#All],3),0),11,H73,12,I73,13,J73,14,K73,"N/A")} -> 13 | G73: {=_xlfn.SWITCH(ROUND(VLOOKUP(A73,Table1[#All],5),0),11,H73,12,I73,13,J73,14,K73,"N/A")} -> 14 | H73: =IF(OR('Raw Data'!H81=0,'Raw Data'!H81="Delete"),"",'Raw Data'!H81) -> 13 | I73: =IF(OR('Raw Data'!I81=0,'Raw Data'!I81="Delete"),"",'Raw Data'!I81) -> 14 | J73: =IF(OR('Raw Data'!J81=0,'Raw Data'!J81="Delete"),"",'Raw Data'!J81) | K73: =IF(OR('Raw Data'!K81=0,'Raw Data'!K81="Delete"),"",'Raw Data'!K81) | L73: =R73 -> Available | M73: =IF(A73="","",IF(OR(AWReleaseNum>=A73,AWReleaseNum=0),"Available","Not Supported")) -> Available | N73: =IF(A73="","",IF(TcRelease="Any","Available",IF(OR(AND(TcReleaseNum>=VLOOKUP(AWReleaseNum,MinVerInfo,3,FALSE),TcReleaseNum<=VLOOKUP(AWReleaseNum,MinVerInfo,4,FALSE)),AND(TcReleaseNum>=VLOOKUP(AWReleaseNum,MinVerInfo,5,FALSE),TcReleaseNum<=VLOOKUP(AWReleaseNum,MinVerInfo,6,FALSE))),"Available","Not Supported"))) -> Available | O73: =IF(TcReleaseNum<P73,"Not Supported","Available") -> Available | P73: {=_xlfn.SWITCH(TcBaseVer, 14, K73, 13, J73, 12, I73, 11, IFERROR(VLOOKUP(H73,Table2[#All],3,FALSE),"N/A"),0)} -> 0 | Q73: =IF(TcBaseVer=0,M73,IF(AND(N73="Available",M73="Available",O73="Available"),"Available",IF(M73="","","Not Supported"))) -> Available | R73: =IF(A73>=AWCurrentRel, "Future",Q73) -> Available | S73: =HYPERLINK(U73,T73) -> Not Available | T73: =IFERROR(VLOOKUP(CONCATENATE($B73,"_",$A73),Table4[#All],5,FALSE),"Not Available") -> Not Available | U73: =IFERROR(VLOOKUP(CONCATENATE(B73,"_",A73),Table4[#All],6,FALSE),"")
A74: =IF(OR('Raw Data'!A82=0,'Raw Data'!A82="Delete"),"",'Raw Data'!A82) -> 2.1 | B74: =IF(OR('Raw Data'!B82=0,'Raw Data'!B82="Delete"),"",'Raw Data'!B82) -> Foundation | C74: =IF(OR('Raw Data'!C82=0,'Raw Data'!C82="Delete"),"",'Raw Data'!C82) -> Usability | D74: =IF(OR('Raw Data'!D82=0,'Raw Data'!D82="Delete"),"",'Raw Data'!D82) -> Platform - Active Workspace Framework - Usability | E74: =IF(OR('Raw Data'!E82=0,'Raw Data'!E82="Delete"),"",'Raw Data'!E82) -> Report Problem tile | F74: {=_xlfn.SWITCH(ROUND(VLOOKUP(A74,Table1[#All],3),0),11,H74,12,I74,13,J74,14,K74,"N/A")} -> 13 | G74: {=_xlfn.SWITCH(ROUND(VLOOKUP(A74,Table1[#All],5),0),11,H74,12,I74,13,J74,14,K74,"N/A")} -> 14 | H74: =IF(OR('Raw Data'!H82=0,'Raw Data'!H82="Delete"),"",'Raw Data'!H82) -> 13 | I74: =IF(OR('Raw Data'!I82=0,'Raw Data'!I82="Delete"),"",'Raw Data'!I82) -> 14 | J74: =IF(OR('Raw Data'!J82=0,'Raw Data'!J82="Delete"),"",'Raw Data'!J82) | K74: =IF(OR('Raw Data'!K82=0,'Raw Data'!K82="Delete"),"",'Raw Data'!K82) | L74: =R74 -> Available | M74: =IF(A74="","",IF(OR(AWReleaseNum>=A74,AWReleaseNum=0),"Available","Not Supported")) -> Available | N74: =IF(A74="","",IF(TcRelease="Any","Available",IF(OR(AND(TcReleaseNum>=VLOOKUP(AWReleaseNum,MinVerInfo,3,FALSE),TcReleaseNum<=VLOOKUP(AWReleaseNum,MinVerInfo,4,FALSE)),AND(TcReleaseNum>=VLOOKUP(AWReleaseNum,MinVerInfo,5,FALSE),TcReleaseNum<=VLOOKUP(AWReleaseNum,MinVerInfo,6,FALSE))),"Available","Not Supported"))) -> Available | O74: =IF(TcReleaseNum<P74,"Not Supported","Available") -> Available | P74: {=_xlfn.SWITCH(TcBaseVer, 14, K74, 13, J74, 12, I74, 11, IFERROR(VLOOKUP(H74,Table2[#All],3,FALSE),"N/A"),0)} -> 0 | Q74: =IF(TcBaseVer=0,M74,IF(AND(N74="Available",M74="Available",O74="Available"),"Available",IF(M74="","","Not Supported"))) -> Available | R74: =IF(A74>=AWCurrentRel, "Future",Q74) -> Available | S74: =HYPERLINK(U74,T74) -> Not Available | T74: =IFERROR(VLOOKUP(CONCATENATE($B74,"_",$A74),Table4[#All],5,FALSE),"Not Available") -> Not Available | U74: =IFERROR(VLOOKUP(CONCATENATE(B74,"_",A74),Table4[#All],6,FALSE),"")
... A82: =IF(OR('Raw Data'!A90=0,'Raw Data'!A90="Delete"),"",'Raw Data'!A90) -> 2.1 | B82: =IF(OR('Raw Data'!B90=0,'Raw Data'!B90="Delete"),"",'Raw Data'!B90) -> Plan | C82: =IF(OR('Raw Data'!C90=0,'Raw Data'!C90="Delete"),"",'Raw Data'!C90) -> Requirements | D82: =IF(OR('Raw Data'!D90=0,'Raw Data'!D90="Delete"),"",'Raw Data'!D90) -> Requirements Management | E82: =IF(OR('Raw Data'!E90=0,'Raw Data'!E90="Delete"),"",'Raw Data'!E90) -> Create tracelinks | F82: {=_xlfn.SWITCH(ROUND(VLOOKUP(A82,Table1[#All],3),0),11,H82,12,I82,13,J82,14,K82,"N/A")} -> 13 | G82: {=_xlfn.SWITCH(ROUND(VLOOKUP(A82,Table1[#All],5),0),11,H82,12,I82,13,J82,14,K82,"N/A")} -> 14 | H82: =IF(OR('Raw Data'!H90=0,'Raw Data'!H90="Delete"),"",'Raw Data'!H90) -> 13 | I82: =IF(OR('Raw Data'!I90=0,'Raw Data'!I90="Delete"),"",'Raw Data'!I90) -> 14 | J82: =IF(OR('Raw Data'!J90=0,'Raw Data'!J90="Delete"),"",'Raw Data'!J90) | K82: =IF(OR('Raw Data'!K90=0,'Raw Data'!K90="Delete"),"",'Raw Data'!K90) | L82: =R82 -> Available | M82: =IF(A82="","",IF(OR(AWReleaseNum>=A82,AWReleaseNum=0),"Available","Not Supported")) -> Available | N82: =IF(A82="","",IF(TcRelease="Any","Available",IF(OR(AND(TcReleaseNum>=VLOOKUP(AWReleaseNum,MinVerInfo,3,FALSE),TcReleaseNum<=VLOOKUP(AWReleaseNum,MinVerInfo,4,FALSE)),AND(TcReleaseNum>=VLOOKUP(AWReleaseNum,MinVerInfo,5,FALSE),TcReleaseNum<=VLOOKUP(AWReleaseNum,MinVerInfo,6,FALSE))),"Available","Not Supported"))) -> Available | O82: =IF(TcReleaseNum<P82,"Not Supported","Available") -> Available | P82: {=_xlfn.SWITCH(TcBaseVer, 14, K82, 13, J82, 12, I82, 11, IFERROR(VLOOKUP(H82,Table2[#All],3,FALSE),"N/A"),0)} -> 0 | Q82: =IF(TcBaseVer=0,M82,IF(AND(N82="Available",M82="Available",O82="Available"),"Available",IF(M82="","","Not Supported"))) -> Available | R82: =IF(A82>=AWCurrentRel, "Future",Q82) -> Available | S82: =HYPERLINK(U82,T82) -> Not Available | T82: =IFERROR(VLOOKUP(CONCATENATE($B82,"_",$A82),Table4[#All],5,FALSE),"Not Available") -> Not Available | U82: =IFERROR(VLOOKUP(CONCATENATE(B82,"_",A82),Table4[#All],6,FALSE),"")
A83: =IF(OR('Raw Data'!A68=0,'Raw Data'!A68="Delete"),"",'Raw Data'!A68) -> 2.1 | B83: =IF(OR('Raw Data'!B68=0,'Raw Data'!B68="Delete"),"",'Raw Data'!B68) -> Deliver | C83: =IF(OR('Raw Data'!C68=0,'Raw Data'!C68="Delete"),"",'Raw Data'!C68) -> Analytics | D83: =IF(OR('Raw Data'!D68=0,'Raw Data'!D68="Delete"),"",'Raw Data'!D68) -> Search and Analytics - Search | E83: =IF(OR('Raw Data'!E68=0,'Raw Data'!E68="Delete"),"",'Raw Data'!E68) -> Performance and syntax improvements | F83: {=_xlfn.SWITCH(ROUND(VLOOKUP(A83,Table1[#All],3),0),11,H83,12,I83,13,J83,14,K83,"N/A")} -> 13 | G83: {=_xlfn.SWITCH(ROUND(VLOOKUP(A83,Table1[#All],5),0),11,H83,12,I83,13,J83,14,K83,"N/A")} -> 14 | H83: =IF(OR('Raw Data'!H68=0,'Raw Data'!H68="Delete"),"",'Raw Data'!H68) -> 13 | I83: =IF(OR('Raw Data'!I68=0,'Raw Data'!I68="Delete"),"",'Raw Data'!I68) -> 14 | J83: =IF(OR('Raw Data'!J68=0,'Raw Data'!J68="Delete"),"",'Raw Data'!J68) | K83: =IF(OR('Raw Data'!K68=0,'Raw Data'!K68="Delete"),"",'Raw Data'!K68) | L83: =R83 -> Available | M83: =IF(A83="","",IF(OR(AWReleaseNum>=A83,AWReleaseNum=0),"Available","Not Supported")) -> Available | N83: =IF(A83="","",IF(TcRelease="Any","Available",IF(OR(AND(TcReleaseNum>=VLOOKUP(AWReleaseNum,MinVerInfo,3,FALSE),TcReleaseNum<=VLOOKUP(AWReleaseNum,MinVerInfo,4,FALSE)),AND(TcReleaseNum>=VLOOKUP(AWReleaseNum,MinVerInfo,5,FALSE),TcReleaseNum<=VLOOKUP(AWReleaseNum,MinVerInfo,6,FALSE))),"Available","Not Supported"))) -> Available | O83: =IF(TcReleaseNum<P83,"Not Supported","Available") -> Available | P83: {=_xlfn.SWITCH(TcBaseVer, 14, K83, 13, J83, 12, I83, 11, IFERROR(VLOOKUP(H83,Table2[#All],3,FALSE),"N/A"),0)} -> 0 | Q83: =IF(TcBaseVer=0,M83,IF(AND(N83="Available",M83="Available",O83="Available"),"Available",IF(M83="","","Not Supported"))) -> Available | R83: =IF(A83>=AWCurrentRel, "Future",Q83) -> Available | S83: =HYPERLINK(U83,T83) -> Not Available | T83: =IFERROR(VLOOKUP(CONCATENATE($B83,"_",$A83),Table4[#All],5,FALSE),"Not Available") -> Not Available | U83: =IFERROR(VLOOKUP(CONCATENATE(B83,"_",A83),Table4[#All],6,FALSE),"")
A84: =IF(OR('Raw Data'!A69=0,'Raw Data'!A69="Delete"),"",'Raw Data'!A69) -> 2.1 | B84: =IF(OR('Raw Data'!B69=0,'Raw Data'!B69="Delete"),"",'Raw Data'!B69) -> Deliver | C84: =IF(OR('Raw Data'!C69=0,'Raw Data'!C69="Delete"),"",'Raw Data'!C69) -> Analytics | D84: =IF(OR('Raw Data'!D69=0,'Raw Data'!D69="Delete"),"",'Raw Data'!D69) -> Search and Analytics - Search | E84: =IF(OR('Raw Data'!E69=0,'Raw Data'!E69="Delete"),"",'Raw Data'!E69) -> Indexing and searching localized data | F84: {=_xlfn.SWITCH(ROUND(VLOOKUP(A84,Table1[#All],3),0),11,H84,12,I84,13,J84,14,K84,"N/A")} -> 13 | G84: {=_xlfn.SWITCH(ROUND(VLOOKUP(A84,Table1[#All],5),0),11,H84,12,I84,13,J84,14,K84,"N/A")} -> 14 | H84: =IF(OR('Raw Data'!H69=0,'Raw Data'!H69="Delete"),"",'Raw Data'!H69) -> 13 | I84: =IF(OR('Raw Data'!I69=0,'Raw Data'!I69="Delete"),"",'Raw Data'!I69) -> 14 | J84: =IF(OR('Raw Data'!J69=0,'Raw Data'!J69="Delete"),"",'Raw Data'!J69) | K84: =IF(OR('Raw Data'!K69=0,'Raw Data'!K69="Delete"),"",'Raw Data'!K69) | L84: =R84 -> Available | M84: =IF(A84="","",IF(OR(AWReleaseNum>=A84,AWReleaseNum=0),"Available","Not Supported")) -> Available | N84: =IF(A84="","",IF(TcRelease="Any","Available",IF(OR(AND(TcReleaseNum>=VLOOKUP(AWReleaseNum,MinVerInfo,3,FALSE),TcReleaseNum<=VLOOKUP(AWReleaseNum,MinVerInfo,4,FALSE)),AND(TcReleaseNum>=VLOOKUP(AWReleaseNum,MinVerInfo,5,FALSE),TcReleaseNum<=VLOOKUP(AWReleaseNum,MinVerInfo,6,FALSE))),"Available","Not Supported"))) -> Available | O84: =IF(TcReleaseNum<P84,"Not Supported","Available") -> Available | P84: {=_xlfn.SWITCH(TcBaseVer, 14, K84, 13, J84, 12, I84, 11, IFERROR(VLOOKUP(H84,Table2[#All],3,FALSE),"N/A"),0)} -> 0 | Q84: =IF(TcBaseVer=0,M84,IF(AND(N84="Available",M84="Available",O84="Available"),"Available",IF(M84="","","Not Supported"))) -> Available | R84: =IF(A84>=AWCurrentRel, "Future",Q84) -> Available | S84: =HYPERLINK(U84,T84) -> Not Available | T84: =IFERROR(VLOOKUP(CONCATENATE($B84,"_",$A84),Table4[#All],5,FALSE),"Not Available") -> Not Available | U84: =IFERROR(VLOOKUP(CONCATENATE(B84,"_",A84),Table4[#All],6,FALSE),"")
A85: =IF(OR('Raw Data'!A70=0,'Raw Data'!A70="Delete"),"",'Raw Data'!A70) -> 2.1 | B85: =IF(OR('Raw Data'!B70=0,'Raw Data'!B70="Delete"),"",'Raw Data'!B70) -> Deliver | C85: =IF(OR('Raw Data'!C70=0,'Raw Data'!C70="Delete"),"",'Raw Data'!C70) -> Analytics | D85: =IF(OR('Raw Data'!D70=0,'Raw Data'!D70="Delete"),"",'Raw Data'!D70) -> Search and Analytics - Search | E85: =IF(OR('Raw Data'!E70=0,'Raw Data'!E70="Delete"),"",'Raw Data'!E70) -> Embed Active Workspace search in rich client | F85: {=_xlfn.SWITCH(ROUND(VLOOKUP(A85,Table1[#All],3),0),11,H85,12,I85,13,J85,14,K85,"N/A")} -> 13 | G85: {=_xlfn.SWITCH(ROUND(VLOOKUP(A85,Table1[#All],5),0),11,H85,12,I85,13,J85,14,K85,"N/A")} -> 14 | H85: =IF(OR('Raw Data'!H70=0,'Raw Data'!H70="Delete"),"",'Raw Data'!H70) -> 13 | I85: =IF(OR('Raw Data'!I70=0,'Raw Data'!I70="Delete"),"",'Raw Data'!I70) -> 14 | J85: =IF(OR('Raw Data'!J70=0,'Raw Data'!J70="Delete"),"",'Raw Data'!J70) | K85: =IF(OR('Raw Data'!K70=0,'Raw Data'!K70="Delete"),"",'Raw Data'!K70) | L85: =R85 -> Available | M85: =IF(A85="","",IF(OR(AWReleaseNum>=A85,AWReleaseNum=0),"Available","Not Supported")) -> Available | N85: =IF(A85="","",IF(TcRelease="Any","Available",IF(OR(AND(TcReleaseNum>=VLOOKUP(AWReleaseNum,MinVerInfo,3,FALSE),TcReleaseNum<=VLOOKUP(AWReleaseNum,MinVerInfo,4,FALSE)),AND(TcReleaseNum>=VLOOKUP(AWReleaseNum,MinVerInfo,5,FALSE),TcReleaseNum<=VLOOKUP(AWReleaseNum,MinVerInfo,6,FALSE))),"Available","Not Supported"))) -> Available | O85: =IF(TcReleaseNum<P85,"Not Supported","Available") -> Available | P85: {=_xlfn.SWITCH(TcBaseVer, 14, K85, 13, J85, 12, I85, 11, IFERROR(VLOOKUP(H85,Table2[#All],3,FALSE),"N/A"),0)} -> 0 | Q85: =IF(TcBaseVer=0,M85,IF(AND(N85="Available",M85="Available",O85="Available"),"Available",IF(M85="","","Not Supported"))) -> Available | R85: =IF(A85>=AWCurrentRel, "Future",Q85) -> Available | S85: =HYPERLINK(U85,T85) -> Not Available | T85: =IFERROR(VLOOKUP(CONCATENATE($B85,"_",$A85),Table4[#All],5,FALSE),"Not Available") -> Not Available | U85: =IFERROR(VLOOKUP(CONCATENATE(B85,"_",A85),Table4[#All],6,FALSE),"")
A86: =IF(OR('Raw Data'!A91=0,'Raw Data'!A91="Delete"),"",'Raw Data'!A91) -> 2.1 | B86: =IF(OR('Raw Data'!B91=0,'Raw Data'!B91="Delete"),"",'Raw Data'!B91) -> Develop | C86: =IF(OR('Raw Data'!C91=0,'Raw Data'!C91="Delete"),"",'Raw Data'!C91) -> Visualization | D86: =IF(OR('Raw Data'!D91=0,'Raw Data'!D91="Delete"),"",'Raw Data'!D91) -> Visualization - Deployability & Infrastructure | E86: =IF(OR('Raw Data'!E91=0,'Raw Data'!E91="Delete"),"",'Raw Data'!E91) -> Health monitoring of visualization rendering and indexing | F86: {=_xlfn.SWITCH(ROUND(VLOOKUP(A86,Table1[#All],3),0),11,H86,12,I86,13,J86,14,K86,"N/A")} -> 13 | G86: {=_xlfn.SWITCH(ROUND(VLOOKUP(A86,Table1[#All],5),0),11,H86,12,I86,13,J86,14,K86,"N/A")} -> 14 | H86: =IF(OR('Raw Data'!H91=0,'Raw Data'!H91="Delete"),"",'Raw Data'!H91) -> 13 | I86: =IF(OR('Raw Data'!I91=0,'Raw Data'!I91="Delete"),"",'Raw Data'!I91) -> 14 | J86: =IF(OR('Raw Data'!J91=0,'Raw Data'!J91="Delete"),"",'Raw Data'!J91) | K86: =IF(OR('Raw Data'!K91=0,'Raw Data'!K91="Delete"),"",'Raw Data'!K91) | L86: =R86 -> Available | M86: =IF(A86="","",IF(OR(AWReleaseNum>=A86,AWReleaseNum=0),"Available","Not Supported")) -> Available | N86: =IF(A86="","",IF(TcRelease="Any","Available",IF(OR(AND(TcReleaseNum>=VLOOKUP(AWReleaseNum,MinVerInfo,3,FALSE),TcReleaseNum<=VLOOKUP(AWReleaseNum,MinVerInfo,4,FALSE)),AND(TcReleaseNum>=VLOOKUP(AWReleaseNum,MinVerInfo,5,FALSE),TcReleaseNum<=VLOOKUP(AWReleaseNum,MinVerInfo,6,FALSE))),"Available","Not Supported"))) -> Available | O86: =IF(TcReleaseNum<P86,"Not Supported","Available") -> Available | P86: {=_xlfn.SWITCH(TcBaseVer, 14, K86, 13, J86, 12, I86, 11, IFERROR(VLOOKUP(H86,Table2[#All],3,FALSE),"N/A"),0)} -> 0 | Q86: =IF(TcBaseVer=0,M86,IF(AND(N86="Available",M86="Available",O86="Available"),"Available",IF(M86="","","Not Supported"))) -> Available | R86: =IF(A86>=AWCurrentRel, "Future",Q86) -> Available | S86: =HYPERLINK(U86,T86) -> Not Available | T86: =IFERROR(VLOOKUP(CONCATENATE($B86,"_",$A86),Table4[#All],5,FALSE),"Not Available") -> Not Available | U86: =IFERROR(VLOOKUP(CONCATENATE(B86,"_",A86),Table4[#All],6,FALSE),"")
A87: =IF(OR('Raw Data'!A92=0,'Raw Data'!A92="Delete"),"",'Raw Data'!A92) -> 2.1 | B87: =IF(OR('Raw Data'!B92=0,'Raw Data'!B92="Delete"),"",'Raw Data'!B92) -> Develop | C87: =IF(OR('Raw Data'!C92=0,'Raw Data'!C92="Delete"),"",'Raw Data'!C92) -> Visualization | D87: =IF(OR('Raw Data'!D92=0,'Raw Data'!D92="Delete"),"",'Raw Data'!D92) -> Visualization - Deployability & Infrastructure | E87: =IF(OR('Raw Data'!E92=0,'Raw Data'!E92="Delete"),"",'Raw Data'!E92) -> Viewer administration for components and processes | F87: {=_xlfn.SWITCH(ROUND(VLOOKUP(A87,Table1[#All],3),0),11,H87,12,I87,13,J87,14,K87,"N/A")} -> 13 | G87: {=_xlfn.SWITCH(ROUND(VLOOKUP(A87,Table1[#All],5),0),11,H87,12,I87,13,J87,14,K87,"N/A")} -> 14 | H87: =IF(OR('Raw Data'!H92=0,'Raw Data'!H92="Delete"),"",'Raw Data'!H92) -> 13 | I87: =IF(OR('Raw Data'!I92=0,'Raw Data'!I92="Delete"),"",'Raw Data'!I92) -> 14 | J87: =IF(OR('Raw Data'!J92=0,'Raw Data'!J92="Delete"),"",'Raw Data'!J92) | K87: =IF(OR('Raw Data'!K92=0,'Raw Data'!K92="Delete"),"",'Raw Data'!K92) | L87: =R87 -> Available | M87: =IF(A87="","",IF(OR(AWReleaseNum>=A87,AWReleaseNum=0),"Available","Not Supported")) -> Available | N87: =IF(A87="","",IF(TcRelease="Any","Available",IF(OR(AND(TcReleaseNum>=VLOOKUP(AWReleaseNum,MinVerInfo,3,FALSE),TcReleaseNum<=VLOOKUP(AWReleaseNum,MinVerInfo,4,FALSE)),AND(TcReleaseNum>=VLOOKUP(AWReleaseNum,MinVerInfo,5,FALSE),TcReleaseNum<=VLOOKUP(AWReleaseNum,MinVerInfo,6,FALSE))),"Available","Not Supported"))) -> Available | O87: =IF(TcReleaseNum<P87,"Not Supported","Available") -> Available | P87: {=_xlfn.SWITCH(TcBaseVer, 14, K87, 13, J87, 12, I87, 11, IFERROR(VLOOKUP(H87,Table2[#All],3,FALSE),"N/A"),0)} -> 0 | Q87: =IF(TcBaseVer=0,M87,IF(AND(N87="Available",M87="Available",O87="Available"),"Available",IF(M87="","","Not Supported"))) -> Available | R87: =IF(A87>=AWCurrentRel, "Future",Q87) -> Available | S87: =HYPERLINK(U87,T87) -> Not Available | T87: =IFERROR(VLOOKUP(CONCATENATE($B87,"_",$A87),Table4[#All],5,FALSE),"Not Available") -> Not Available | U87: =IFERROR(VLOOKUP(CONCATENATE(B87,"_",A87),Table4[#All],6,FALSE),"")
A88: =IF(OR('Raw Data'!A93=0,'Raw Data'!A93="Delete"),"",'Raw Data'!A93) -> 2.1 | B88: =IF(OR('Raw Data'!B93=0,'Raw Data'!B93="Delete"),"",'Raw Data'!B93) -> Develop | C88: =IF(OR('Raw Data'!C93=0,'Raw Data'!C93="Delete"),"",'Raw Data'!C93) -> Visualization | D88: =IF(OR('Raw Data'!D93=0,'Raw Data'!D93="Delete"),"",'Raw Data'!D93) -> Visualization - Usability | E88: =IF(OR('Raw Data'!E93=0,'Raw Data'!E93="Delete"),"",'Raw Data'!E93) -> Scaled for the enterprise | F88: {=_xlfn.SWITCH(ROUND(VLOOKUP(A88,Table1[#All],3),0),11,H88,12,I88,13,J88,14,K88,"N/A")} -> 13 | G88: {=_xlfn.SWITCH(ROUND(VLOOKUP(A88,Table1[#All],5),0),11,H88,12,I88,13,J88,14,K88,"N/A")} -> 14 | H88: =IF(OR('Raw Data'!H93=0,'Raw Data'!H93="Delete"),"",'Raw Data'!H93) -> 13 | I88: =IF(OR('Raw Data'!I93=0,'Raw Data'!I93="Delete"),"",'Raw Data'!I93) -> 14 | J88: =IF(OR('Raw Data'!J93=0,'Raw Data'!J93="Delete"),"",'Raw Data'!J93) | K88: =IF(OR('Raw Data'!K93=0,'Raw Data'!K93="Delete"),"",'Raw Data'!K93) | L88: =R88 -> Available | M88: =IF(A88="","",IF(OR(AWReleaseNum>=A88,AWReleaseNum=0),"Available","Not Supported")) -> Available | N88: =IF(A88="","",IF(TcRelease="Any","Available",IF(OR(AND(TcReleaseNum>=VLOOKUP(AWReleaseNum,MinVerInfo,3,FALSE),TcReleaseNum<=VLOOKUP(AWReleaseNum,MinVerInfo,4,FALSE)),AND(TcReleaseNum>=VLOOKUP(AWReleaseNum,MinVerInfo,5,FALSE),TcReleaseNum<=VLOOKUP(AWReleaseNum,MinVerInfo,6,FALSE))),"Available","Not Supported"))) -> Available | O88: =IF(TcReleaseNum<P88,"Not Supported","Available") -> Available | P88: {=_xlfn.SWITCH(TcBaseVer, 14, K88, 13, J88, 12, I88, 11, IFERROR(VLOOKUP(H88,Table2[#All],3,FALSE),"N/A"),0)} -> 0 | Q88: =IF(TcBaseVer=0,M88,IF(AND(N88="Available",M88="Available",O88="Available"),"Available",IF(M88="","","Not Supported"))) -> Available | R88: =IF(A88>=AWCurrentRel, "Future",Q88) -> Available | S88: =HYPERLINK(U88,T88) -> Not Available | T88: =IFERROR(VLOOKUP(CONCATENATE($B88,"_",$A88),Table4[#All],5,FALSE),"Not Available") -> Not Available | U88: =IFERROR(VLOOKUP(CONCATENATE(B88,"_",A88),Table4[#All],6,FALSE),"")
A89: =IF(OR('Raw Data'!A94=0,'Raw Data'!A94="Delete"),"",'Raw Data'!A94) -> 2.1 | B89: =IF(OR('Raw Data'!B94=0,'Raw Data'!B94="Delete"),"",'Raw Data'!B94) -> Develop | C89: =IF(OR('Raw Data'!C94=0,'Raw Data'!C94="Delete"),"",'Raw Data'!C94) -> Visualization | D89: =IF(OR('Raw Data'!D94=0,'Raw Data'!D94="Delete"),"",'Raw Data'!D94) -> Visualization - Usability | E89: =IF(OR('Raw Data'!E94=0,'Raw Data'!E94="Delete"),"",'Raw Data'!E94) -> Settings for many visualization features saved across work sessions | F89: {=_xlfn.SWITCH(ROUND(VLOOKUP(A89,Table1[#All],3),0),11,H89,12,I89,13,J89,14,K89,"N/A")} -> 13 | G89: {=_xlfn.SWITCH(ROUND(VLOOKUP(A89,Table1[#All],5),0),11,H89,12,I89,13,J89,14,K89,"N/A")} -> 14 | H89: =IF(OR('Raw Data'!H94=0,'Raw Data'!H94="Delete"),"",'Raw Data'!H94) -> 13 | I89: =IF(OR('Raw Data'!I94=0,'Raw Data'!I94="Delete"),"",'Raw Data'!I94) -> 14 | J89: =IF(OR('Raw Data'!J94=0,'Raw Data'!J94="Delete"),"",'Raw Data'!J94) | K89: =IF(OR('Raw Data'!K94=0,'Raw Data'!K94="Delete"),"",'Raw Data'!K94) | L89: =R89 -> Available | M89: =IF(A89="","",IF(OR(AWReleaseNum>=A89,AWReleaseNum=0),"Available","Not Supported")) -> Available | N89: =IF(A89="","",IF(TcRelease="Any","Available",IF(OR(AND(TcReleaseNum>=VLOOKUP(AWReleaseNum,MinVerInfo,3,FALSE),TcReleaseNum<=VLOOKUP(AWReleaseNum,MinVerInfo,4,FALSE)),AND(TcReleaseNum>=VLOOKUP(AWReleaseNum,MinVerInfo,5,FALSE),TcReleaseNum<=VLOOKUP(AWReleaseNum,MinVerInfo,6,FALSE))),"Available","Not Supported"))) -> Available | O89: =IF(TcReleaseNum<P89,"Not Supported","Available") -> Available | P89: {=_xlfn.SWITCH(TcBaseVer, 14, K89, 13, J89, 12, I89, 11, IFERROR(VLOOKUP(H89,Table2[#All],3,FALSE),"N/A"),0)} -> 0 | Q89: =IF(TcBaseVer=0,M89,IF(AND(N89="Available",M89="Available",O89="Available"),"Available",IF(M89="","","Not Supported"))) -> Available | R89: =IF(A89>=AWCurrentRel, "Future",Q89) -> Available | S89: =HYPERLINK(U89,T89) -> Not Available | T89: =IFERROR(VLOOKUP(CONCATENATE($B89,"_",$A89),Table4[#All],5,FALSE),"Not Available") -> Not Available | U89: =IFERROR(VLOOKUP(CONCATENATE(B89,"_",A89),Table4[#All],6,FALSE),"")
A90: =IF(OR('Raw Data'!A95=0,'Raw Data'!A95="Delete"),"",'Raw Data'!A95) -> 2.1 | B90: =IF(OR('Raw Data'!B95=0,'Raw Data'!B95="Delete"),"",'Raw Data'!B95) -> Develop | C90: =IF(OR('Raw Data'!C95=0,'Raw Data'!C95="Delete"),"",'Raw Data'!C95) -> Visualization | D90: =IF(OR('Raw Data'!D95=0,'Raw Data'!D95="Delete"),"",'Raw Data'!D95) -> Visualization - Usability | E90: =IF(OR('Raw Data'!E95=0,'Raw Data'!E95="Delete"),"",'Raw Data'!E95) -> Improved PMI and display control interaction | F90: {=_xlfn.SWITCH(ROUND(VLOOKUP(A90,Table1[#All],3),0),11,H90,12,I90,13,J90,14,K90,"N/A")} -> 13 | G90: {=_xlfn.SWITCH(ROUND(VLOOKUP(A90,Table1[#All],5),0),11,H90,12,I90,13,J90,14,K90,"N/A")} -> 14 | H90: =IF(OR('Raw Data'!H95=0,'Raw Data'!H95="Delete"),"",'Raw Data'!H95) -> 13 | I90: =IF(OR('Raw Data'!I95=0,'Raw Data'!I95="Delete"),"",'Raw Data'!I95) -> 14 | J90: =IF(OR('Raw Data'!J95=0,'Raw Data'!J95="Delete"),"",'Raw Data'!J95) | K90: =IF(OR('Raw Data'!K95=0,'Raw Data'!K95="Delete"),"",'Raw Data'!K95) | L90: =R90 -> Available | M90: =IF(A90="","",IF(OR(AWReleaseNum>=A90,AWReleaseNum=0),"Available","Not Supported")) -> Available | N90: =IF(A90="","",IF(TcRelease="Any","Available",IF(OR(AND(TcReleaseNum>=VLOOKUP(AWReleaseNum,MinVerInfo,3,FALSE),TcReleaseNum<=VLOOKUP(AWReleaseNum,MinVerInfo,4,FALSE)),AND(TcReleaseNum>=VLOOKUP(AWReleaseNum,MinVerInfo,5,FALSE),TcReleaseNum<=VLOOKUP(AWReleaseNum,MinVerInfo,6,FALSE))),"Available","Not Supported"))) -> Available | O90: =IF(TcReleaseNum<P90,"Not Supported","Available") -> Available | P90: {=_xlfn.SWITCH(TcBaseVer, 14, K90, 13, J90, 12, I90, 11, IFERROR(VLOOKUP(H90,Table2[#All],3,FALSE),"N/A"),0)} -> 0 | Q90: =IF(TcBaseVer=0,M90,IF(AND(N90="Available",M90="Available",O90="Available"),"Available",IF(M90="","","Not Supported"))) -> Available | R90: =IF(A90>=AWCurrentRel, "Future",Q90) -> Available | S90: =HYPERLINK(U90,T90) -> Not Available | T90: =IFERROR(VLOOKUP(CONCATENATE($B90,"_",$A90),Table4[#All],5,FALSE),"Not Available") -> Not Available | U90: =IFERROR(VLOOKUP(CONCATENATE(B90,"_",A90),Table4[#All],6,FALSE),"")
A91: =IF(OR('Raw Data'!A96=0,'Raw Data'!A96="Delete"),"",'Raw Data'!A96) -> 2.1 | B91: =IF(OR('Raw Data'!B96=0,'Raw Data'!B96="Delete"),"",'Raw Data'!B96) -> Develop | C91: =IF(OR('Raw Data'!C96=0,'Raw Data'!C96="Delete"),"",'Raw Data'!C96) -> Visualization | D91: =IF(OR('Raw Data'!D96=0,'Raw Data'!D96="Delete"),"",'Raw Data'!D96) -> Visualization - Usability | E91: =IF(OR('Raw Data'!E96=0,'Raw Data'!E96="Delete"),"",'Raw Data'!E96) -> Viewer navigation commands more readily accessible | F91: {=_xlfn.SWITCH(ROUND(VLOOKUP(A91,Table1[#All],3),0),11,H91,12,I91,13,J91,14,K91,"N/A")} -> 13 | G91: {=_xlfn.SWITCH(ROUND(VLOOKUP(A91,Table1[#All],5),0),11,H91,12,I91,13,J91,14,K91,"N/A")} -> 14 | H91: =IF(OR('Raw Data'!H96=0,'Raw Data'!H96="Delete"),"",'Raw Data'!H96) -> 13 | I91: =IF(OR('Raw Data'!I96=0,'Raw Data'!I96="Delete"),"",'Raw Data'!I96) -> 14 | J91: =IF(OR('Raw Data'!J96=0,'Raw Data'!J96="Delete"),"",'Raw Data'!J96) | K91: =IF(OR('Raw Data'!K96=0,'Raw Data'!K96="Delete"),"",'Raw Data'!K96) | L91: =R91 -> Available | M91: =IF(A91="","",IF(OR(AWReleaseNum>=A91,AWReleaseNum=0),"Available","Not Supported")) -> Available | N91: =IF(A91="","",IF(TcRelease="Any","Available",IF(OR(AND(TcReleaseNum>=VLOOKUP(AWReleaseNum,MinVerInfo,3,FALSE),TcReleaseNum<=VLOOKUP(AWReleaseNum,MinVerInfo,4,FALSE)),AND(TcReleaseNum>=VLOOKUP(AWReleaseNum,MinVerInfo,5,FALSE),TcReleaseNum<=VLOOKUP(AWReleaseNum,MinVerInfo,6,FALSE))),"Available","Not Supported"))) -> Available | O91: =IF(TcReleaseNum<P91,"Not Supported","Available") -> Available | P91: {=_xlfn.SWITCH(TcBaseVer, 14, K91, 13, J91, 12, I91, 11, IFERROR(VLOOKUP(H91,Table2[#All],3,FALSE),"N/A"),0)} -> 0 | Q91: =IF(TcBaseVer=0,M91,IF(AND(N91="Available",M91="Available",O91="Available"),"Available",IF(M91="","","Not Supported"))) -> Available | R91: =IF(A91>=AWCurrentRel, "Future",Q91) -> Available | S91: =HYPERLINK(U91,T91) -> Not Available | T91: =IFERROR(VLOOKUP(CONCATENATE($B91,"_",$A91),Table4[#All],5,FALSE),"Not Available") -> Not Available | U91: =IFERROR(VLOOKUP(CONCATENATE(B91,"_",A91),Table4[#All],6,FALSE),"")
A92: =IF(OR('Raw Data'!A1200=0,'Raw Data'!A1200="Delete"),"",'Raw Data'!A1200) -> 2.1 | B92: =IF(OR('Raw Data'!B1200=0,'Raw Data'!B1200="Delete"),"",'Raw Data'!B1200) -> Plan | C92: =IF(OR('Raw Data'!C1200=0,'Raw Data'!C1200="Delete"),"",'Raw Data'!C1200) -> Process | D92: =IF(OR('Raw Data'!D1200=0,'Raw Data'!D1200="Delete"),"",'Raw Data'!D1200) -> Workflow | E92: =IF(OR('Raw Data'!E1200=0,'Raw Data'!E1200="Delete"),"",'Raw Data'!E1200) -> Notifications on Inbox tile | F92: {=_xlfn.SWITCH(ROUND(VLOOKUP(A92,Table1[#All],3),0),11,H92,12,I92,13,J92,14,K92,"N/A")} -> 13 | G92: {=_xlfn.SWITCH(ROUND(VLOOKUP(A92,Table1[#All],5),0),11,H92,12,I92,13,J92,14,K92,"N/A")} -> 14 | H92: =IF(OR('Raw Data'!H1200=0,'Raw Data'!H1200="Delete"),"",'Raw Data'!H1200) -> 13 | I92: =IF(OR('Raw Data'!I1200=0,'Raw Data'!I1200="Delete"),"",'Raw Data'!I1200) -> 14 | J92: =IF(OR('Raw Data'!J1200=0,'Raw Data'!J1200="Delete"),"",'Raw Data'!J1200) | K92: =IF(OR('Raw Data'!K1200=0,'Raw Data'!K1200="Delete"),"",'Raw Data'!K1200) | L92: =R92 -> Available | M92: =IF(A92="","",IF(OR(AWReleaseNum>=A92,AWReleaseNum=0),"Available","Not Supported")) -> Available | N92: =IF(A92="","",IF(TcRelease="Any","Available",IF(OR(AND(TcReleaseNum>=VLOOKUP(AWReleaseNum,MinVerInfo,3,FALSE),TcReleaseNum<=VLOOKUP(AWReleaseNum,MinVerInfo,4,FALSE)),AND(TcReleaseNum>=VLOOKUP(AWReleaseNum,MinVerInfo,5,FALSE),TcReleaseNum<=VLOOKUP(AWReleaseNum,MinVerInfo,6,FALSE))),"Available","Not Supported"))) -> Available | O92: =IF(TcReleaseNum<P92,"Not Supported","Available") -> Available | P92: {=_xlfn.SWITCH(TcBaseVer, 14, K92, 13, J92, 12, I92, 11, IFERROR(VLOOKUP(H92,Table2[#All],3,FALSE),"N/A"),0)} -> 0 | Q92: =IF(TcBaseVer=0,M92,IF(AND(N92="Available",M92="Available",O92="Available"),"Available",IF(M92="","","Not Supported"))) -> Available | R92: =IF(A92>=AWCurrentRel, "Future",Q92) -> Available | S92: =HYPERLINK(U92,T92) -> Not Available | T92: =IFERROR(VLOOKUP(CONCATENATE($B92,"_",$A92),Table4[#All],5,FALSE),"Not Available") -> Not Available | U92: =IFERROR(VLOOKUP(CONCATENATE(B92,"_",A92),Table4[#All],6,FALSE),"")
A93: =IF(OR('Raw Data'!A1201=0,'Raw Data'!A1201="Delete"),"",'Raw Data'!A1201) -> 2.1 | B93: =IF(OR('Raw Data'!B1201=0,'Raw Data'!B1201="Delete"),"",'Raw Data'!B1201) -> Plan | C93: =IF(OR('Raw Data'!C1201=0,'Raw Data'!C1201="Delete"),"",'Raw Data'!C1201) -> Process | D93: =IF(OR('Raw Data'!D1201=0,'Raw Data'!D1201="Delete"),"",'Raw Data'!D1201) -> Workflow | E93: =IF(OR('Raw Data'!E1201=0,'Raw Data'!E1201="Delete"),"",'Raw Data'!E1201) -> Claim tasks from teams assignments | F93: {=_xlfn.SWITCH(ROUND(VLOOKUP(A93,Table1[#All],3),0),11,H93,12,I93,13,J93,14,K93,"N/A")} -> 13 | G93: {=_xlfn.SWITCH(ROUND(VLOOKUP(A93,Table1[#All],5),0),11,H93,12,I93,13,J93,14,K93,"N/A")} -> 14 | H93: =IF(OR('Raw Data'!H1201=0,'Raw Data'!H1201="Delete"),"",'Raw Data'!H1201) -> 13 | I93: =IF(OR('Raw Data'!I1201=0,'Raw Data'!I1201="Delete"),"",'Raw Data'!I1201) -> 14 | J93: =IF(OR('Raw Data'!J1201=0,'Raw Data'!J1201="Delete"),"",'Raw Data'!J1201) | K93: =IF(OR('Raw Data'!K1201=0,'Raw Data'!K1201="Delete"),"",'Raw Data'!K1201) | L93: =R93 -> Available | M93: =IF(A93="","",IF(OR(AWReleaseNum>=A93,AWReleaseNum=0),"Available","Not Supported")) -> Available | N93: =IF(A93="","",IF(TcRelease="Any","Available",IF(OR(AND(TcReleaseNum>=VLOOKUP(AWReleaseNum,MinVerInfo,3,FALSE),TcReleaseNum<=VLOOKUP(AWReleaseNum,MinVerInfo,4,FALSE)),AND(TcReleaseNum>=VLOOKUP(AWReleaseNum,MinVerInfo,5,FALSE),TcReleaseNum<=VLOOKUP(AWReleaseNum,MinVerInfo,6,FALSE))),"Available","Not Supported"))) -> Available | O93: =IF(TcReleaseNum<P93,"Not Supported","Available") -> Available | P93: {=_xlfn.SWITCH(TcBaseVer, 14, K93, 13, J93, 12, I93, 11, IFERROR(VLOOKUP(H93,Table2[#All],3,FALSE),"N/A"),0)} -> 0 | Q93: =IF(TcBaseVer=0,M93,IF(AND(N93="Available",M93="Available",O93="Available"),"Available",IF(M93="","","Not Supported"))) -> Available | R93: =IF(A93>=AWCurrentRel, "Future",Q93) -> Available | S93: =HYPERLINK(U93,T93) -> Not Available | T93: =IFERROR(VLOOKUP(CONCATENATE($B93,"_",$A93),Table4[#All],5,FALSE),"Not Available") -> Not Available | U93: =IFERROR(VLOOKUP(CONCATENATE(B93,"_",A93),Table4[#All],6,FALSE),"")
A94: =IF(OR('Raw Data'!A1202=0,'Raw Data'!A1202="Delete"),"",'Raw Data'!A1202) -> 2.1 | B94: =IF(OR('Raw Data'!B1202=0,'Raw Data'!B1202="Delete"),"",'Raw Data'!B1202) -> Plan | C94: =IF(OR('Raw Data'!C1202=0,'Raw Data'!C1202="Delete"),"",'Raw Data'!C1202) -> Process | D94: =IF(OR('Raw Data'!D1202=0,'Raw Data'!D1202="Delete"),"",'Raw Data'!D1202) -> Workflow | E94: =IF(OR('Raw Data'!E1202=0,'Raw Data'!E1202="Delete"),"",'Raw Data'!E1202) -> Find in Inbox | F94: {=_xlfn.SWITCH(ROUND(VLOOKUP(A94,Table1[#All],3),0),11,H94,12,I94,13,J94,14,K94,"N/A")} -> 13 | G94: {=_xlfn.SWITCH(ROUND(VLOOKUP(A94,Table1[#All],5),0),11,H94,12,I94,13,J94,14,K94,"N/A")} -> 14 | H94: =IF(OR('Raw Data'!H1202=0,'Raw Data'!H1202="Delete"),"",'Raw Data'!H1202) -> 13 | I94: =IF(OR('Raw Data'!I1202=0,'Raw Data'!I1202="Delete"),"",'Raw Data'!I1202) -> 14 | J94: =IF(OR('Raw Data'!J1202=0,'Raw Data'!J1202="Delete"),"",'Raw Data'!J1202) | K94: =IF(OR('Raw Data'!K1202=0,'Raw Data'!K1202="Delete"),"",'Raw Data'!K1202) | L94: =R94 -> Available | M94: =IF(A94="","",IF(OR(AWReleaseNum>=A94,AWReleaseNum=0),"Available","Not Supported")) -> Available | N94: =IF(A94="","",IF(TcRelease="Any","Available",IF(OR(AND(TcReleaseNum>=VLOOKUP(AWReleaseNum,MinVerInfo,3,FALSE),TcReleaseNum<=VLOOKUP(AWReleaseNum,MinVerInfo,4,FALSE)),AND(TcReleaseNum>=VLOOKUP(AWReleaseNum,MinVerInfo,5,FALSE),TcReleaseNum<=VLOOKUP(AWReleaseNum,MinVerInfo,6,FALSE))),"Available","Not Supported"))) -> Available | O94: =IF(TcReleaseNum<P94,"Not Supported","Available") -> Available | P94: {=_xlfn.SWITCH(TcBaseVer, 14, K94, 13, J94, 12, I94, 11, IFERROR(VLOOKUP(H94,Table2[#All],3,FALSE),"N/A"),0)} -> 0 | Q94: =IF(TcBaseVer=0,M94,IF(AND(N94="Available",M94="Available",O94="Available"),"Available",IF(M94="","","Not Supported"))) -> Available | R94: =IF(A94>=AWCurrentRel, "Future",Q94) -> Available | S94: =HYPERLINK(U94,T94) -> Not Available | T94: =IFERROR(VLOOKUP(CONCATENATE($B94,"_",$A94),Table4[#All],5,FALSE),"Not Available") -> Not Available | U94: =IFERROR(VLOOKUP(CONCATENATE(B94,"_",A94),Table4[#All],6,FALSE),"")
A95: =IF(OR('Raw Data'!A1203=0,'Raw Data'!A1203="Delete"),"",'Raw Data'!A1203) -> 2.1 | B95: =IF(OR('Raw Data'!B1203=0,'Raw Data'!B1203="Delete"),"",'Raw Data'!B1203) -> Plan | C95: =IF(OR('Raw Data'!C1203=0,'Raw Data'!C1203="Delete"),"",'Raw Data'!C1203) -> Process | D95: =IF(OR('Raw Data'!D1203=0,'Raw Data'!D1203="Delete"),"",'Raw Data'!D1203) -> Workflow | E95: =IF(OR('Raw Data'!E1203=0,'Raw Data'!E1203="Delete"),"",'Raw Data'!E1203) -> Filter tasks | F95: {=_xlfn.SWITCH(ROUND(VLOOKUP(A95,Table1[#All],3),0),11,H95,12,I95,13,J95,14,K95,"N/A")} -> 13 | G95: {=_xlfn.SWITCH(ROUND(VLOOKUP(A95,Table1[#All],5),0),11,H95,12,I95,13,J95,14,K95,"N/A")} -> 14 | H95: =IF(OR('Raw Data'!H1203=0,'Raw Data'!H1203="Delete"),"",'Raw Data'!H1203) -> 13 | I95: =IF(OR('Raw Data'!I1203=0,'Raw Data'!I1203="Delete"),"",'Raw Data'!I1203) -> 14 | J95: =IF(OR('Raw Data'!J1203=0,'Raw Data'!J1203="Delete"),"",'Raw Data'!J1203) | K95: =IF(OR('Raw Data'!K1203=0,'Raw Data'!K1203="Delete"),"",'Raw Data'!K1203) | L95: =R95 -> Available | M95: =IF(A95="","",IF(OR(AWReleaseNum>=A95,AWReleaseNum=0),"Available","Not Supported")) -> Available | N95: =IF(A95="","",IF(TcRelease="Any","Available",IF(OR(AND(TcReleaseNum>=VLOOKUP(AWReleaseNum,MinVerInfo,3,FALSE),TcReleaseNum<=VLOOKUP(AWReleaseNum,MinVerInfo,4,FALSE)),AND(TcReleaseNum>=VLOOKUP(AWReleaseNum,MinVerInfo,5,FALSE),TcReleaseNum<=VLOOKUP(AWReleaseNum,MinVerInfo,6,FALSE))),"Available","Not Supported"))) -> Available | O95: =IF(TcReleaseNum<P95,"Not Supported","Available") -> Available | P95: {=_xlfn.SWITCH(TcBaseVer, 14, K95, 13, J95, 12, I95, 11, IFERROR(VLOOKUP(H95,Table2[#All],3,FALSE),"N/A"),0)} -> 0 | Q95: =IF(TcBaseVer=0,M95,IF(AND(N95="Available",M95="Available",O95="Available"),"Available",IF(M95="","","Not Supported"))) -> Available | R95: =IF(A95>=AWCurrentRel, "Future",Q95) -> Available | S95: =HYPERLINK(U95,T95) -> Not Available | T95: =IFERROR(VLOOKUP(CONCATENATE($B95,"_",$A95),Table4[#All],5,FALSE),"Not Available") -> Not Available | U95: =IFERROR(VLOOKUP(CONCATENATE(B95,"_",A95),Table4[#All],6,FALSE),"")
A96: =IF(OR('Raw Data'!A1204=0,'Raw Data'!A1204="Delete"),"",'Raw Data'!A1204) -> 2.1 | B96: =IF(OR('Raw Data'!B1204=0,'Raw Data'!B1204="Delete"),"",'Raw Data'!B1204) -> Plan | C96: =IF(OR('Raw Data'!C1204=0,'Raw Data'!C1204="Delete"),"",'Raw Data'!C1204) -> Process | D96: =IF(OR('Raw Data'!D1204=0,'Raw Data'!D1204="Delete"),"",'Raw Data'!D1204) -> Workflow | E96: =IF(OR('Raw Data'!E1204=0,'Raw Data'!E1204="Delete"),"",'Raw Data'!E1204) -> Differentiate read and unread (new)tasks | F96: {=_xlfn.SWITCH(ROUND(VLOOKUP(A96,Table1[#All],3),0),11,H96,12,I96,13,J96,14,K96,"N/A")} -> 13 | G96: {=_xlfn.SWITCH(ROUND(VLOOKUP(A96,Table1[#All],5),0),11,H96,12,I96,13,J96,14,K96,"N/A")} -> 14 | H96: =IF(OR('Raw Data'!H1204=0,'Raw Data'!H1204="Delete"),"",'Raw Data'!H1204) -> 13 | I96: =IF(OR('Raw Data'!I1204=0,'Raw Data'!I1204="Delete"),"",'Raw Data'!I1204) -> 14 | J96: =IF(OR('Raw Data'!J1204=0,'Raw Data'!J1204="Delete"),"",'Raw Data'!J1204) | K96: =IF(OR('Raw Data'!K1204=0,'Raw Data'!K1204="Delete"),"",'Raw Data'!K1204) | L96: =R96 -> Available | M96: =IF(A96="","",IF(OR(AWReleaseNum>=A96,AWReleaseNum=0),"Available","Not Supported")) -> Available | N96: =IF(A96="","",IF(TcRelease="Any","Available",IF(OR(AND(TcReleaseNum>=VLOOKUP(AWReleaseNum,MinVerInfo,3,FALSE),TcReleaseNum<=VLOOKUP(AWReleaseNum,MinVerInfo,4,FALSE)),AND(TcReleaseNum>=VLOOKUP(AWReleaseNum,MinVerInfo,5,FALSE),TcReleaseNum<=VLOOKUP(AWReleaseNum,MinVerInfo,6,FALSE))),"Available","Not Supported"))) -> Available | O96: =IF(TcReleaseNum<P96,"Not Supported","Available") -> Available | P96: {=_xlfn.SWITCH(TcBaseVer, 14, K96, 13, J96, 12, I96, 11, IFERROR(VLOOKUP(H96,Table2[#All],3,FALSE),"N/A"),0)} -> 0 | Q96: =IF(TcBaseVer=0,M96,IF(AND(N96="Available",M96="Available",O96="Available"),"Available",IF(M96="","","Not Supported"))) -> Available | R96: =IF(A96>=AWCurrentRel, "Future",Q96) -> Available | S96: =HYPERLINK(U96,T96) -> Not Available | T96: =IFERROR(VLOOKUP(CONCATENATE($B96,"_",$A96),Table4[#All],5,FALSE),"Not Available") -> Not Available | U96: =IFERROR(VLOOKUP(CONCATENATE(B96,"_",A96),Table4[#All],6,FALSE),"")
A97: =IF(OR('Raw Data'!A1205=0,'Raw Data'!A1205="Delete"),"",'Raw Data'!A1205) -> 2.1 | B97: =IF(OR('Raw Data'!B1205=0,'Raw Data'!B1205="Delete"),"",'Raw Data'!B1205) -> Plan | C97: =IF(OR('Raw Data'!C1205=0,'Raw Data'!C1205="Delete"),"",'Raw Data'!C1205) -> Process | D97: =IF(OR('Raw Data'!D1205=0,'Raw Data'!D1205="Delete"),"",'Raw Data'!D1205) -> Workflow | E97: =IF(OR('Raw Data'!E1205=0,'Raw Data'!E1205="Delete"),"",'Raw Data'!E1205) -> Paging on inbox content for large task lists | F97: {=_xlfn.SWITCH(ROUND(VLOOKUP(A97,Table1[#All],3),0),11,H97,12,I97,13,J97,14,K97,"N/A")} -> 13 | G97: {=_xlfn.SWITCH(ROUND(VLOOKUP(A97,Table1[#All],5),0),11,H97,12,I97,13,J97,14,K97,"N/A")} -> 14 | H97: =IF(OR('Raw Data'!H1205=0,'Raw Data'!H1205="Delete"),"",'Raw Data'!H1205) -> 13 | I97: =IF(OR('Raw Data'!I1205=0,'Raw Data'!I1205="Delete"),"",'Raw Data'!I1205) -> 14 | J97: =IF(OR('Raw Data'!J1205=0,'Raw Data'!J1205="Delete"),"",'Raw Data'!J1205) | K97: =IF(OR('Raw Data'!K1205=0,'Raw Data'!K1205="Delete"),"",'Raw Data'!K1205) | L97: =R97 -> Available | M97: =IF(A97="","",IF(OR(AWReleaseNum>=A97,AWReleaseNum=0),"Available","Not Supported")) -> Available | N97: =IF(A97="","",IF(TcRelease="Any","Available",IF(OR(AND(TcReleaseNum>=VLOOKUP(AWReleaseNum,MinVerInfo,3,FALSE),TcReleaseNum<=VLOOKUP(AWReleaseNum,MinVerInfo,4,FALSE)),AND(TcReleaseNum>=VLOOKUP(AWReleaseNum,MinVerInfo,5,FALSE),TcReleaseNum<=VLOOKUP(AWReleaseNum,MinVerInfo,6,FALSE))),"Available","Not Supported"))) -> Available | O97: =IF(TcReleaseNum<P97,"Not Supported","Available") -> Available | P97: {=_xlfn.SWITCH(TcBaseVer, 14, K97, 13, J97, 12, I97, 11, IFERROR(VLOOKUP(H97,Table2[#All],3,FALSE),"N/A"),0)} -> 0 | Q97: =IF(TcBaseVer=0,M97,IF(AND(N97="Available",M97="Available",O97="Available"),"Available",IF(M97="","","Not Supported"))) -> Available | R97: =IF(A97>=AWCurrentRel, "Future",Q97) -> Available | S97: =HYPERLINK(U97,T97) -> Not Available | T97: =IFERROR(VLOOKUP(CONCATENATE($B97,"_",$A97),Table4[#All],5,FALSE),"Not Available") -> Not Available | U97: =IFERROR(VLOOKUP(CONCATENATE(B97,"_",A97),Table4[#All],6,FALSE),"")
A98: =IF(OR('Raw Data'!A1206=0,'Raw Data'!A1206="Delete"),"",'Raw Data'!A1206) -> 2.1 | B98: =IF(OR('Raw Data'!B1206=0,'Raw Data'!B1206="Delete"),"",'Raw Data'!B1206) -> Plan | C98: =IF(OR('Raw Data'!C1206=0,'Raw Data'!C1206="Delete"),"",'Raw Data'!C1206) -> Process | D98: =IF(OR('Raw Data'!D1206=0,'Raw Data'!D1206="Delete"),"",'Raw Data'!D1206) -> Workflow | E98: =IF(OR('Raw Data'!E1206=0,'Raw Data'!E1206="Delete"),"",'Raw Data'!E1206) -> Simplified signoffs tab | F98: {=_xlfn.SWITCH(ROUND(VLOOKUP(A98,Table1[#All],3),0),11,H98,12,I98,13,J98,14,K98,"N/A")} -> 13 | G98: {=_xlfn.SWITCH(ROUND(VLOOKUP(A98,Table1[#All],5),0),11,H98,12,I98,13,J98,14,K98,"N/A")} -> 14 | H98: =IF(OR('Raw Data'!H1206=0,'Raw Data'!H1206="Delete"),"",'Raw Data'!H1206) -> 13 | I98: =IF(OR('Raw Data'!I1206=0,'Raw Data'!I1206="Delete"),"",'Raw Data'!I1206) -> 14 | J98: =IF(OR('Raw Data'!J1206=0,'Raw Data'!J1206="Delete"),"",'Raw Data'!J1206) | K98: =IF(OR('Raw Data'!K1206=0,'Raw Data'!K1206="Delete"),"",'Raw Data'!K1206) | L98: =R98 -> Available | M98: =IF(A98="","",IF(OR(AWReleaseNum>=A98,AWReleaseNum=0),"Available","Not Supported")) -> Available | N98: =IF(A98="","",IF(TcRelease="Any","Available",IF(OR(AND(TcReleaseNum>=VLOOKUP(AWReleaseNum,MinVerInfo,3,FALSE),TcReleaseNum<=VLOOKUP(AWReleaseNum,MinVerInfo,4,FALSE)),AND(TcReleaseNum>=VLOOKUP(AWReleaseNum,MinVerInfo,5,FALSE),TcReleaseNum<=VLOOKUP(AWReleaseNum,MinVerInfo,6,FALSE))),"Available","Not Supported"))) -> Available | O98: =IF(TcReleaseNum<P98,"Not Supported","Available") -> Available | P98: {=_xlfn.SWITCH(TcBaseVer, 14, K98, 13, J98, 12, I98, 11, IFERROR(VLOOKUP(H98,Table2[#All],3,FALSE),"N/A"),0)} -> 0 | Q98: =IF(TcBaseVer=0,M98,IF(AND(N98="Available",M98="Available",O98="Available"),"Available",IF(M98="","","Not Supported"))) -> Available | R98: =IF(A98>=AWCurrentRel, "Future",Q98) -> Available | S98: =HYPERLINK(U98,T98) -> Not Available | T98: =IFERROR(VLOOKUP(CONCATENATE($B98,"_",$A98),Table4[#All],5,FALSE),"Not Available") -> Not Available | U98: =IFERROR(VLOOKUP(CONCATENATE(B98,"_",A98),Table4[#All],6,FALSE),"")
A99: =IF(OR('Raw Data'!A97=0,'Raw Data'!A97="Delete"),"",'Raw Data'!A97) -> 2.2 | B99: =IF(OR('Raw Data'!B97=0,'Raw Data'!B97="Delete"),"",'Raw Data'!B97) -> Foundation | C99: =IF(OR('Raw Data'!C97=0,'Raw Data'!C97="Delete"),"",'Raw Data'!C97) -> Usability | D99: =IF(OR('Raw Data'!D97=0,'Raw Data'!D97="Delete"),"",'Raw Data'!D97) -> Active Collaboration | E99: =IF(OR('Raw Data'!E97=0,'Raw Data'!E97="Delete"),"",'Raw Data'!E97) -> View and update your picture on your user profile | F99: {=_xlfn.SWITCH(ROUND(VLOOKUP(A99,Table1[#All],3),0),11,H99,12,I99,13,J99,14,K99,"N/A")} -> 13 | G99: {=_xlfn.SWITCH(ROUND(VLOOKUP(A99,Table1[#All],5),0),11,H99,12,I99,13,J99,14,K99,"N/A")} -> 14 | H99: =IF(OR('Raw Data'!H97=0,'Raw Data'!H97="Delete"),"",'Raw Data'!H97) -> 13 | I99: =IF(OR('Raw Data'!I97=0,'Raw Data'!I97="Delete"),"",'Raw Data'!I97) -> 14 | J99: =IF(OR('Raw Data'!J97=0,'Raw Data'!J97="Delete"),"",'Raw Data'!J97) | K99: =IF(OR('Raw Data'!K97=0,'Raw Data'!K97="Delete"),"",'Raw Data'!K97) | L99: =R99 -> Available | M99: =IF(A99="","",IF(OR(AWReleaseNum>=A99,AWReleaseNum=0),"Available","Not Supported")) -> Available | N99: =IF(A99="","",IF(TcRelease="Any","Available",IF(OR(AND(TcReleaseNum>=VLOOKUP(AWReleaseNum,MinVerInfo,3,FALSE),TcReleaseNum<=VLOOKUP(AWReleaseNum,MinVerInfo,4,FALSE)),AND(TcReleaseNum>=VLOOKUP(AWReleaseNum,MinVerInfo,5,FALSE),TcReleaseNum<=VLOOKUP(AWReleaseNum,MinVerInfo,6,FALSE))),"Available","Not Supported"))) -> Available | O99: =IF(TcReleaseNum<P99,"Not Supported","Available") -> Available | P99: {=_xlfn.SWITCH(TcBaseVer, 14, K99, 13, J99, 12, I99, 11, IFERROR(VLOOKUP(H99,Table2[#All],3,FALSE),"N/A"),0)} -> 0 | Q99: =IF(TcBaseVer=0,M99,IF(AND(N99="Available",M99="Available",O99="Available"),"Available",IF(M99="","","Not Supported"))) -> Available | R99: =IF(A99>=AWCurrentRel, "Future",Q99) -> Available | S99: =HYPERLINK(U99,T99) -> Not Available | T99: =IFERROR(VLOOKUP(CONCATENATE($B99,"_",$A99),Table4[#All],5,FALSE),"Not Available") -> Not Available | U99: =IFERROR(VLOOKUP(CONCATENATE(B99,"_",A99),Table4[#All],6,FALSE),"")
A100: =IF(OR('Raw Data'!A98=0,'Raw Data'!A98="Delete"),"",'Raw Data'!A98) -> 2.2 | B100: =IF(OR('Raw Data'!B98=0,'Raw Data'!B98="Delete"),"",'Raw Data'!B98) -> Foundation | C100: =IF(OR('Raw Data'!C98=0,'Raw Data'!C98="Delete"),"",'Raw Data'!C98) -> Usability | D100: =IF(OR('Raw Data'!D98=0,'Raw Data'!D98="Delete"),"",'Raw Data'!D98) -> Active Collaboration | E100: =IF(OR('Raw Data'!E98=0,'Raw Data'!E98="Delete"),"",'Raw Data'!E98) -> Comment and ask/answer questions | F100: {=_xlfn.SWITCH(ROUND(VLOOKUP(A100,Table1[#All],3),0),11,H100,12,I100,13,J100,14,K100,"N/A")} -> 13 | G100: {=_xlfn.SWITCH(ROUND(VLOOKUP(A100,Table1[#All],5),0),11,H100,12,I100,13,J100,14,K100,"N/A")} -> 14 | H100: =IF(OR('Raw Data'!H98=0,'Raw Data'!H98="Delete"),"",'Raw Data'!H98) -> 13 | I100: =IF(OR('Raw Data'!I98=0,'Raw Data'!I98="Delete"),"",'Raw Data'!I98) -> 14 | J100: =IF(OR('Raw Data'!J98=0,'Raw Data'!J98="Delete"),"",'Raw Data'!J98) | K100: =IF(OR('Raw Data'!K98=0,'Raw Data'!K98="Delete"),"",'Raw Data'!K98) | L100: =R100 -> Available | M100: =IF(A100="","",IF(OR(AWReleaseNum>=A100,AWReleaseNum=0),"Available","Not Supported")) -> Available | N100: =IF(A100="","",IF(TcRelease="Any","Available",IF(OR(AND(TcReleaseNum>=VLOOKUP(AWReleaseNum,MinVerInfo,3,FALSE),TcReleaseNum<=VLOOKUP(AWReleaseNum,MinVerInfo,4,FALSE)),AND(TcReleaseNum>=VLOOKUP(AWReleaseNum,MinVerInfo,5,FALSE),TcReleaseNum<=VLOOKUP(AWReleaseNum,MinVerInfo,6,FALSE))),"Available","Not Supported"))) -> Available | O100: =IF(TcReleaseNum<P100,"Not Supported","Available") -> Available | P100: {=_xlfn.SWITCH(TcBaseVer, 14, K100, 13, J100, 12, I100, 11, IFERROR(VLOOKUP(H100,Table2[#All],3,FALSE),"N/A"),0)} -> 0 | Q100: =IF(TcBaseVer=0,M100,IF(AND(N100="Available",M100="Available",O100="Available"),"Available",IF(M100="","","Not Supported"))) -> Available | R100: =IF(A100>=AWCurrentRel, "Future",Q100) -> Available | S100: =HYPERLINK(U100,T100) -> Not Available | T100: =IFERROR(VLOOKUP(CONCATENATE($B100,"_",$A100),Table4[#All],5,FALSE),"Not Available") -> Not Available | U100: =IFERROR(VLOOKUP(CONCATENATE(B100,"_",A100),Table4[#All],6,FALSE),"")
A101: =IF(OR('Raw Data'!A11=0,'Raw Data'!A11="Delete"),"",'Raw Data'!A11) -> 2.2 | B101: =IF(OR('Raw Data'!B11=0,'Raw Data'!B11="Delete"),"",'Raw Data'!B11) -> Plan | C101: =IF(OR('Raw Data'!C11=0,'Raw Data'!C11="Delete"),"",'Raw Data'!C11) -> Process | D101: =IF(OR('Raw Data'!D11=0,'Raw Data'!D11="Delete"),"",'Raw Data'!D11) -> Change Management | E101: =IF(OR('Raw Data'!E11=0,'Raw Data'!E11="Delete"),"",'Raw Data'!E11) -> Derive changes | F101: {=_xlfn.SWITCH(ROUND(VLOOKUP(A101,Table1[#All],3),0),11,H101,12,I101,13,J101,14,K101,"N/A")} -> 13 | G101: {=_xlfn.SWITCH(ROUND(VLOOKUP(A101,Table1[#All],5),0),11,H101,12,I101,13,J101,14,K101,"N/A")} -> 14 | H101: =IF(OR('Raw Data'!H11=0,'Raw Data'!H11="Delete"),"",'Raw Data'!H11) -> 13 | I101: =IF(OR('Raw Data'!I11=0,'Raw Data'!I11="Delete"),"",'Raw Data'!I11) -> 14 | J101: =IF(OR('Raw Data'!J11=0,'Raw Data'!J11="Delete"),"",'Raw Data'!J11) | K101: =IF(OR('Raw Data'!K11=0,'Raw Data'!K11="Delete"),"",'Raw Data'!K11) | L101: =R101 -> Available | M101: =IF(A101="","",IF(OR(AWReleaseNum>=A101,AWReleaseNum=0),"Available","Not Supported")) -> Available | N101: =IF(A101="","",IF(TcRelease="Any","Available",IF(OR(AND(TcReleaseNum>=VLOOKUP(AWReleaseNum,MinVerInfo,3,FALSE),TcReleaseNum<=VLOOKUP(AWReleaseNum,MinVerInfo,4,FALSE)),AND(TcReleaseNum>=VLOOKUP(AWReleaseNum,MinVerInfo,5,FALSE),TcReleaseNum<=VLOOKUP(AWReleaseNum,MinVerInfo,6,FALSE))),"Available","Not Supported"))) -> Available | O101: =IF(TcReleaseNum<P101,"Not Supported","Available") -> Available | P101: {=_xlfn.SWITCH(TcBaseVer, 14, K101, 13, J101, 12, I101, 11, IFERROR(VLOOKUP(H101,Table2[#All],3,FALSE),"N/A"),0)} -> 0 | Q101: =IF(TcBaseVer=0,M101,IF(AND(N101="Available",M101="Available",O101="Available"),"Available",IF(M101="","","Not Supported"))) -> Available | R101: =IF(A101>=AWCurrentRel, "Future",Q101) -> Available | S101: =HYPERLINK(U101,T101) -> Not Available | T101: =IFERROR(VLOOKUP(CONCATENATE($B101,"_",$A101),Table4[#All],5,FALSE),"Not Available") -> Not Available | U101: =IFERROR(VLOOKUP(CONCATENATE(B101,"_",A101),Table4[#All],6,FALSE),"")
A102: =IF(OR('Raw Data'!A110=0,'Raw Data'!A110="Delete"),"",'Raw Data'!A110) -> 2.2 | B102: =IF(OR('Raw Data'!B110=0,'Raw Data'!B110="Delete"),"",'Raw Data'!B110) -> Foundation | C102: =IF(OR('Raw Data'!C110=0,'Raw Data'!C110="Delete"),"",'Raw Data'!C110) -> Deployability | D102: =IF(OR('Raw Data'!D110=0,'Raw Data'!D110="Delete"),"",'Raw Data'!D110) -> Deployability | E102: =IF(OR('Raw Data'!E110=0,'Raw Data'!E110="Delete"),"",'Raw Data'!E110) -> Search indexing infrastructure updates | F102: {=_xlfn.SWITCH(ROUND(VLOOKUP(A102,Table1[#All],3),0),11,H102,12,I102,13,J102,14,K102,"N/A")} -> 13 | G102: {=_xlfn.SWITCH(ROUND(VLOOKUP(A102,Table1[#All],5),0),11,H102,12,I102,13,J102,14,K102,"N/A")} -> 14 | H102: =IF(OR('Raw Data'!H110=0,'Raw Data'!H110="Delete"),"",'Raw Data'!H110) -> 13 | I102: =IF(OR('Raw Data'!I110=0,'Raw Data'!I110="Delete"),"",'Raw Data'!I110) -> 14 | J102: =IF(OR('Raw Data'!J110=0,'Raw Data'!J110="Delete"),"",'Raw Data'!J110) | K102: =IF(OR('Raw Data'!K110=0,'Raw Data'!K110="Delete"),"",'Raw Data'!K110) | L102: =R102 -> Available | M102: =IF(A102="","",IF(OR(AWReleaseNum>=A102,AWReleaseNum=0),"Available","Not Supported")) -> Available | N102: =IF(A102="","",IF(TcRelease="Any","Available",IF(OR(AND(TcReleaseNum>=VLOOKUP(AWReleaseNum,MinVerInfo,3,FALSE),TcReleaseNum<=VLOOKUP(AWReleaseNum,MinVerInfo,4,FALSE)),AND(TcReleaseNum>=VLOOKUP(AWReleaseNum,MinVerInfo,5,FALSE),TcReleaseNum<=VLOOKUP(AWReleaseNum,MinVerInfo,6,FALSE))),"Available","Not Supported"))) -> Available | O102: =IF(TcReleaseNum<P102,"Not Supported","Available") -> Available | P102: {=_xlfn.SWITCH(TcBaseVer, 14, K102, 13, J102, 12, I102, 11, IFERROR(VLOOKUP(H102,Table2[#All],3,FALSE),"N/A"),0)} -> 0 | Q102: =IF(TcBaseVer=0,M102,IF(AND(N102="Available",M102="Available",O102="Available"),"Available",IF(M102="","","Not Supported"))) -> Available | R102: =IF(A102>=AWCurrentRel, "Future",Q102) -> Available | S102: =HYPERLINK(U102,T102) -> Not Available | T102: =IFERROR(VLOOKUP(CONCATENATE($B102,"_",$A102),Table4[#All],5,FALSE),"Not Available") -> Not Available | U102: =IFERROR(VLOOKUP(CONCATENATE(B102,"_",A102),Table4[#All],6,FALSE),"")
A103: =IF(OR('Raw Data'!A111=0,'Raw Data'!A111="Delete"),"",'Raw Data'!A111) -> 2.2 | B103: =IF(OR('Raw Data'!B111=0,'Raw Data'!B111="Delete"),"",'Raw Data'!B111) -> Foundation | C103: =IF(OR('Raw Data'!C111=0,'Raw Data'!C111="Delete"),"",'Raw Data'!C111) -> Deployability | D103: =IF(OR('Raw Data'!D111=0,'Raw Data'!D111="Delete"),"",'Raw Data'!D111) -> Deployability | E103: =IF(OR('Raw Data'!E111=0,'Raw Data'!E111="Delete"),"",'Raw Data'!E111) -> JMX tooling for monitoring VisServers health and load | F103: {=_xlfn.SWITCH(ROUND(VLOOKUP(A103,Table1[#All],3),0),11,H103,12,I103,13,J103,14,K103,"N/A")} -> 13 | G103: {=_xlfn.SWITCH(ROUND(VLOOKUP(A103,Table1[#All],5),0),11,H103,12,I103,13,J103,14,K103,"N/A")} -> 14 | H103: =IF(OR('Raw Data'!H111=0,'Raw Data'!H111="Delete"),"",'Raw Data'!H111) -> 13 | I103: =IF(OR('Raw Data'!I111=0,'Raw Data'!I111="Delete"),"",'Raw Data'!I111) -> 14 | J103: =IF(OR('Raw Data'!J111=0,'Raw Data'!J111="Delete"),"",'Raw Data'!J111) | K103: =IF(OR('Raw Data'!K111=0,'Raw Data'!K111="Delete"),"",'Raw Data'!K111) | L103: =R103 -> Available | M103: =IF(A103="","",IF(OR(AWReleaseNum>=A103,AWReleaseNum=0),"Available","Not Supported")) -> Available | N103: =IF(A103="","",IF(TcRelease="Any","Available",IF(OR(AND(TcReleaseNum>=VLOOKUP(AWReleaseNum,MinVerInfo,3,FALSE),TcReleaseNum<=VLOOKUP(AWReleaseNum,MinVerInfo,4,FALSE)),AND(TcReleaseNum>=VLOOKUP(AWReleaseNum,MinVerInfo,5,FALSE),TcReleaseNum<=VLOOKUP(AWReleaseNum,MinVerInfo,6,FALSE))),"Available","Not Supported"))) -> Available | O103: =IF(TcReleaseNum<P103,"Not Supported","Available") -> Available | P103: {=_xlfn.SWITCH(TcBaseVer, 14, K103, 13, J103, 12, I103, 11, IFERROR(VLOOKUP(H103,Table2[#All],3,FALSE),"N/A"),0)} -> 0 | Q103: =IF(TcBaseVer=0,M103,IF(AND(N103="Available",M103="Available",O103="Available"),"Available",IF(M103="","","Not Supported"))) -> Available | R103: =IF(A103>=AWCurrentRel, "Future",Q103) -> Available | S103: =HYPERLINK(U103,T103) -> Not Available | T103: =IFERROR(VLOOKUP(CONCATENATE($B103,"_",$A103),Table4[#All],5,FALSE),"Not Available") -> Not Available | U103: =IFERROR(VLOOKUP(CONCATENATE(B103,"_",A103),Table4[#All],6,FALSE),"")
A104: =IF(OR('Raw Data'!A112=0,'Raw Data'!A112="Delete"),"",'Raw Data'!A112) -> 2.2 | B104: =IF(OR('Raw Data'!B112=0,'Raw Data'!B112="Delete"),"",'Raw Data'!B112) -> Foundation | C104: =IF(OR('Raw Data'!C112=0,'Raw Data'!C112="Delete"),"",'Raw Data'!C112) -> Deployability | D104: =IF(OR('Raw Data'!D112=0,'Raw Data'!D112="Delete"),"",'Raw Data'!D112) -> Deployability | E104: =IF(OR('Raw Data'!E112=0,'Raw Data'!E112="Delete"),"",'Raw Data'!E112) -> Install – Feature selection and documentation updates | F104: {=_xlfn.SWITCH(ROUND(VLOOKUP(A104,Table1[#All],3),0),11,H104,12,I104,13,J104,14,K104,"N/A")} -> 13 | G104: {=_xlfn.SWITCH(ROUND(VLOOKUP(A104,Table1[#All],5),0),11,H104,12,I104,13,J104,14,K104,"N/A")} -> 14 | H104: =IF(OR('Raw Data'!H112=0,'Raw Data'!H112="Delete"),"",'Raw Data'!H112) -> 13 | I104: =IF(OR('Raw Data'!I112=0,'Raw Data'!I112="Delete"),"",'Raw Data'!I112) -> 14 | J104: =IF(OR('Raw Data'!J112=0,'Raw Data'!J112="Delete"),"",'Raw Data'!J112) | K104: =IF(OR('Raw Data'!K112=0,'Raw Data'!K112="Delete"),"",'Raw Data'!K112) | L104: =R104 -> Available | M104: =IF(A104="","",IF(OR(AWReleaseNum>=A104,AWReleaseNum=0),"Available","Not Supported")) -> Available | N104: =IF(A104="","",IF(TcRelease="Any","Available",IF(OR(AND(TcReleaseNum>=VLOOKUP(AWReleaseNum,MinVerInfo,3,FALSE),TcReleaseNum<=VLOOKUP(AWReleaseNum,MinVerInfo,4,FALSE)),AND(TcReleaseNum>=VLOOKUP(AWReleaseNum,MinVerInfo,5,FALSE),TcReleaseNum<=VLOOKUP(AWReleaseNum,MinVerInfo,6,FALSE))),"Available","Not Supported"))) -> Available | O104: =IF(TcReleaseNum<P104,"Not Supported","Available") -> Available | P104: {=_xlfn.SWITCH(TcBaseVer, 14, K104, 13, J104, 12, I104, 11, IFERROR(VLOOKUP(H104,Table2[#All],3,FALSE),"N/A"),0)} -> 0 | Q104: =IF(TcBaseVer=0,M104,IF(AND(N104="Available",M104="Available",O104="Available"),"Available",IF(M104="","","Not Supported"))) -> Available | R104: =IF(A104>=AWCurrentRel, "Future",Q104) -> Available | S104: =HYPERLINK(U104,T104) -> Not Available | T104: =IFERROR(VLOOKUP(CONCATENATE($B104,"_",$A104),Table4[#All],5,FALSE),"Not Available") -> Not Available | U104: =IFERROR(VLOOKUP(CONCATENATE(B104,"_",A104),Table4[#All],6,FALSE),"")
A105: =IF(OR('Raw Data'!A113=0,'Raw Data'!A113="Delete"),"",'Raw Data'!A113) -> 2.2 | B105: =IF(OR('Raw Data'!B113=0,'Raw Data'!B113="Delete"),"",'Raw Data'!B113) -> Foundation | C105: =IF(OR('Raw Data'!C113=0,'Raw Data'!C113="Delete"),"",'Raw Data'!C113) -> Deployability | D105: =IF(OR('Raw Data'!D113=0,'Raw Data'!D113="Delete"),"",'Raw Data'!D113) -> Deployability | E105: =IF(OR('Raw Data'!E113=0,'Raw Data'!E113="Delete"),"",'Raw Data'!E113) -> All 13 languages PL supports | F105: {=_xlfn.SWITCH(ROUND(VLOOKUP(A105,Table1[#All],3),0),11,H105,12,I105,13,J105,14,K105,"N/A")} -> 13 | G105: {=_xlfn.SWITCH(ROUND(VLOOKUP(A105,Table1[#All],5),0),11,H105,12,I105,13,J105,14,K105,"N/A")} -> 14 | H105: =IF(OR('Raw Data'!H113=0,'Raw Data'!H113="Delete"),"",'Raw Data'!H113) -> 13 | I105: =IF(OR('Raw Data'!I113=0,'Raw Data'!I113="Delete"),"",'Raw Data'!I113) -> 14 | J105: =IF(OR('Raw Data'!J113=0,'Raw Data'!J113="Delete"),"",'Raw Data'!J113) | K105: =IF(OR('Raw Data'!K113=0,'Raw Data'!K113="Delete"),"",'Raw Data'!K113) | L105: =R105 -> Available | M105: =IF(A105="","",IF(OR(AWReleaseNum>=A105,AWReleaseNum=0),"Available","Not Supported")) -> Available | N105: =IF(A105="","",IF(TcRelease="Any","Available",IF(OR(AND(TcReleaseNum>=VLOOKUP(AWReleaseNum,MinVerInfo,3,FALSE),TcReleaseNum<=VLOOKUP(AWReleaseNum,MinVerInfo,4,FALSE)),AND(TcReleaseNum>=VLOOKUP(AWReleaseNum,MinVerInfo,5,FALSE),TcReleaseNum<=VLOOKUP(AWReleaseNum,MinVerInfo,6,FALSE))),"Available","Not Supported"))) -> Available | O105: =IF(TcReleaseNum<P105,"Not Supported","Available") -> Available | P105: {=_xlfn.SWITCH(TcBaseVer, 14, K105, 13, J105, 12, I105, 11, IFERROR(VLOOKUP(H105,Table2[#All],3,FALSE),"N/A"),0)} -> 0 | Q105: =IF(TcBaseVer=0,M105,IF(AND(N105="Available",M105="Available",O105="Available"),"Available",IF(M105="","","Not Supported"))) -> Available | R105: =IF(A105>=AWCurrentRel, "Future",Q105) -> Available | S105: =HYPERLINK(U105,T105) -> Not Available | T105: =IFERROR(VLOOKUP(CONCATENATE($B105,"_",$A105),Table4[#All],5,FALSE),"Not Available") -> Not Available | U105: =IFERROR(VLOOKUP(CONCATENATE(B105,"_",A105),Table4[#All],6,FALSE),"")
A106: =IF(OR('Raw Data'!A114=0,'Raw Data'!A114="Delete"),"",'Raw Data'!A114) -> 2.2 | B106: =IF(OR('Raw Data'!B114=0,'Raw Data'!B114="Delete"),"",'Raw Data'!B114) -> Develop | C106: =IF(OR('Raw Data'!C114=0,'Raw Data'!C114="Delete"),"",'Raw Data'!C114) -> Documents | D106: =IF(OR('Raw Data'!D114=0,'Raw Data'!D114="Delete"),"",'Raw Data'!D114) -> Document Management | E106: =IF(OR('Raw Data'!E114=0,'Raw Data'!E114="Delete"),"",'Raw Data'!E114) -> Open/save and upload edited file | F106: {=_xlfn.SWITCH(ROUND(VLOOKUP(A106,Table1[#All],3),0),11,H106,12,I106,13,J106,14,K106,"N/A")} -> 13 | G106: {=_xlfn.SWITCH(ROUND(VLOOKUP(A106,Table1[#All],5),0),11,H106,12,I106,13,J106,14,K106,"N/A")} -> 14 | H106: =IF(OR('Raw Data'!H114=0,'Raw Data'!H114="Delete"),"",'Raw Data'!H114) -> 13 | I106: =IF(OR('Raw Data'!I114=0,'Raw Data'!I114="Delete"),"",'Raw Data'!I114) -> 14 | J106: =IF(OR('Raw Data'!J114=0,'Raw Data'!J114="Delete"),"",'Raw Data'!J114) | K106: =IF(OR('Raw Data'!K114=0,'Raw Data'!K114="Delete"),"",'Raw Data'!K114) | L106: =R106 -> Available | M106: =IF(A106="","",IF(OR(AWReleaseNum>=A106,AWReleaseNum=0),"Available","Not Supported")) -> Available | N106: =IF(A106="","",IF(TcRelease="Any","Available",IF(OR(AND(TcReleaseNum>=VLOOKUP(AWReleaseNum,MinVerInfo,3,FALSE),TcReleaseNum<=VLOOKUP(AWReleaseNum,MinVerInfo,4,FALSE)),AND(TcReleaseNum>=VLOOKUP(AWReleaseNum,MinVerInfo,5,FALSE),TcReleaseNum<=VLOOKUP(AWReleaseNum,MinVerInfo,6,FALSE))),"Available","Not Supported"))) -> Available | O106: =IF(TcReleaseNum<P106,"Not Supported","Available") -> Available | P106: {=_xlfn.SWITCH(TcBaseVer, 14, K106, 13, J106, 12, I106, 11, IFERROR(VLOOKUP(H106,Table2[#All],3,FALSE),"N/A"),0)} -> 0 | Q106: =IF(TcBaseVer=0,M106,IF(AND(N106="Available",M106="Available",O106="Available"),"Available",IF(M106="","","Not Supported"))) -> Available | R106: =IF(A106>=AWCurrentRel, "Future",Q106) -> Available | S106: =HYPERLINK(U106,T106) -> Not Available | T106: =IFERROR(VLOOKUP(CONCATENATE($B106,"_",$A106),Table4[#All],5,FALSE),"Not Available") -> Not Available | U106: =IFERROR(VLOOKUP(CONCATENATE(B106,"_",A106),Table4[#All],6,FALSE),"")
A107: =IF(OR('Raw Data'!A115=0,'Raw Data'!A115="Delete"),"",'Raw Data'!A115) -> 2.2 | B107: =IF(OR('Raw Data'!B115=0,'Raw Data'!B115="Delete"),"",'Raw Data'!B115) -> Develop | C107: =IF(OR('Raw Data'!C115=0,'Raw Data'!C115="Delete"),"",'Raw Data'!C115) -> Documents | D107: =IF(OR('Raw Data'!D115=0,'Raw Data'!D115="Delete"),"",'Raw Data'!D115) -> Document Management | E107: =IF(OR('Raw Data'!E115=0,'Raw Data'!E115="Delete"),"",'Raw Data'!E115) -> Create Office documents using Templates and IRDC | F107: {=_xlfn.SWITCH(ROUND(VLOOKUP(A107,Table1[#All],3),0),11,H107,12,I107,13,J107,14,K107,"N/A")} -> 13 | G107: {=_xlfn.SWITCH(ROUND(VLOOKUP(A107,Table1[#All],5),0),11,H107,12,I107,13,J107,14,K107,"N/A")} -> 14 | H107: =IF(OR('Raw Data'!H115=0,'Raw Data'!H115="Delete"),"",'Raw Data'!H115) -> 13 | I107: =IF(OR('Raw Data'!I115=0,'Raw Data'!I115="Delete"),"",'Raw Data'!I115) -> 14 | J107: =IF(OR('Raw Data'!J115=0,'Raw Data'!J115="Delete"),"",'Raw Data'!J115) | K107: =IF(OR('Raw Data'!K115=0,'Raw Data'!K115="Delete"),"",'Raw Data'!K115) | L107: =R107 -> Available | M107: =IF(A107="","",IF(OR(AWReleaseNum>=A107,AWReleaseNum=0),"Available","Not Supported")) -> Available | N107: =IF(A107="","",IF(TcRelease="Any","Available",IF(OR(AND(TcReleaseNum>=VLOOKUP(AWReleaseNum,MinVerInfo,3,FALSE),TcReleaseNum<=VLOOKUP(AWReleaseNum,MinVerInfo,4,FALSE)),AND(TcReleaseNum>=VLOOKUP(AWReleaseNum,MinVerInfo,5,FALSE),TcReleaseNum<=VLOOKUP(AWReleaseNum,MinVerInfo,6,FALSE))),"Available","Not Supported"))) -> Available | O107: =IF(TcReleaseNum<P107,"Not Supported","Available") -> Available | P107: {=_xlfn.SWITCH(TcBaseVer, 14, K107, 13, J107, 12, I107, 11, IFERROR(VLOOKUP(H107,Table2[#All],3,FALSE),"N/A"),0)} -> 0 | Q107: =IF(TcBaseVer=0,M107,IF(AND(N107="Available",M107="Available",O107="Available"),"Available",IF(M107="","","Not Supported"))) -> Available | R107: =IF(A107>=AWCurrentRel, "Future",Q107) -> Available | S107: =HYPERLINK(U107,T107) -> Not Available | T107: =IFERROR(VLOOKUP(CONCATENATE($B107,"_",$A107),Table4[#All],5,FALSE),"Not Available") -> Not Available | U107: =IFERROR(VLOOKUP(CONCATENATE(B107,"_",A107),Table4[#All],6,FALSE),"")
A108: =IF(OR('Raw Data'!A116=0,'Raw Data'!A116="Delete"),"",'Raw Data'!A116) -> 2.2 | B108: =IF(OR('Raw Data'!B116=0,'Raw Data'!B116="Delete"),"",'Raw Data'!B116) -> Develop | C108: =IF(OR('Raw Data'!C116=0,'Raw Data'!C116="Delete"),"",'Raw Data'!C116) -> Documents | D108: =IF(OR('Raw Data'!D116=0,'Raw Data'!D116="Delete"),"",'Raw Data'!D116) -> Document Management | E108: =IF(OR('Raw Data'!E116=0,'Raw Data'!E116="Delete"),"",'Raw Data'!E116) -> Document view and markup component | F108: {=_xlfn.SWITCH(ROUND(VLOOKUP(A108,Table1[#All],3),0),11,H108,12,I108,13,J108,14,K108,"N/A")} -> 13 | G108: {=_xlfn.SWITCH(ROUND(VLOOKUP(A108,Table1[#All],5),0),11,H108,12,I108,13,J108,14,K108,"N/A")} -> 14 | H108: =IF(OR('Raw Data'!H116=0,'Raw Data'!H116="Delete"),"",'Raw Data'!H116) -> 13 | I108: =IF(OR('Raw Data'!I116=0,'Raw Data'!I116="Delete"),"",'Raw Data'!I116) -> 14 | J108: =IF(OR('Raw Data'!J116=0,'Raw Data'!J116="Delete"),"",'Raw Data'!J116) | K108: =IF(OR('Raw Data'!K116=0,'Raw Data'!K116="Delete"),"",'Raw Data'!K116) | L108: =R108 -> Available | M108: =IF(A108="","",IF(OR(AWReleaseNum>=A108,AWReleaseNum=0),"Available","Not Supported")) -> Available | N108: =IF(A108="","",IF(TcRelease="Any","Available",IF(OR(AND(TcReleaseNum>=VLOOKUP(AWReleaseNum,MinVerInfo,3,FALSE),TcReleaseNum<=VLOOKUP(AWReleaseNum,MinVerInfo,4,FALSE)),AND(TcReleaseNum>=VLOOKUP(AWReleaseNum,MinVerInfo,5,FALSE),TcReleaseNum<=VLOOKUP(AWReleaseNum,MinVerInfo,6,FALSE))),"Available","Not Supported"))) -> Available | O108: =IF(TcReleaseNum<P108,"Not Supported","Available") -> Available | P108: {=_xlfn.SWITCH(TcBaseVer, 14, K108, 13, J108, 12, I108, 11, IFERROR(VLOOKUP(H108,Table2[#All],3,FALSE),"N/A"),0)} -> 0 | Q108: =IF(TcBaseVer=0,M108,IF(AND(N108="Available",M108="Available",O108="Available"),"Available",IF(M108="","","Not Supported"))) -> Available | R108: =IF(A108>=AWCurrentRel, "Future",Q108) -> Available | S108: =HYPERLINK(U108,T108) -> Not Available | T108: =IFERROR(VLOOKUP(CONCATENATE($B108,"_",$A108),Table4[#All],5,FALSE),"Not Available") -> Not Available | U108: =IFERROR(VLOOKUP(CONCATENATE(B108,"_",A108),Table4[#All],6,FALSE),"")
A109: =IF(OR('Raw Data'!A117=0,'Raw Data'!A117="Delete"),"",'Raw Data'!A117) -> 2.2 | B109: =IF(OR('Raw Data'!B117=0,'Raw Data'!B117="Delete"),"",'Raw Data'!B117) -> Develop | C109: =IF(OR('Raw Data'!C117=0,'Raw Data'!C117="Delete"),"",'Raw Data'!C117) -> Documents | D109: =IF(OR('Raw Data'!D117=0,'Raw Data'!D117="Delete"),"",'Raw Data'!D117) -> Document Management | E109: =IF(OR('Raw Data'!E117=0,'Raw Data'!E117="Delete"),"",'Raw Data'!E117) -> Image capture and markup for 3D models | F109: {=_xlfn.SWITCH(ROUND(VLOOKUP(A109,Table1[#All],3),0),11,H109,12,I109,13,J109,14,K109,"N/A")} -> 13 | G109: {=_xlfn.SWITCH(ROUND(VLOOKUP(A109,Table1[#All],5),0),11,H109,12,I109,13,J109,14,K109,"N/A")} -> 14 | H109: =IF(OR('Raw Data'!H117=0,'Raw Data'!H117="Delete"),"",'Raw Data'!H117) -> 13 | I109: =IF(OR('Raw Data'!I117=0,'Raw Data'!I117="Delete"),"",'Raw Data'!I117) -> 14 | J109: =IF(OR('Raw Data'!J117=0,'Raw Data'!J117="Delete"),"",'Raw Data'!J117) | K109: =IF(OR('Raw Data'!K117=0,'Raw Data'!K117="Delete"),"",'Raw Data'!K117) | L109: =R109 -> Available | M109: =IF(A109="","",IF(OR(AWReleaseNum>=A109,AWReleaseNum=0),"Available","Not Supported")) -> Available | N109: =IF(A109="","",IF(TcRelease="Any","Available",IF(OR(AND(TcReleaseNum>=VLOOKUP(AWReleaseNum,MinVerInfo,3,FALSE),TcReleaseNum<=VLOOKUP(AWReleaseNum,MinVerInfo,4,FALSE)),AND(TcReleaseNum>=VLOOKUP(AWReleaseNum,MinVerInfo,5,FALSE),TcReleaseNum<=VLOOKUP(AWReleaseNum,MinVerInfo,6,FALSE))),"Available","Not Supported"))) -> Available | O109: =IF(TcReleaseNum<P109,"Not Supported","Available") -> Available | P109: {=_xlfn.SWITCH(TcBaseVer, 14, K109, 13, J109, 12, I109, 11, IFERROR(VLOOKUP(H109,Table2[#All],3,FALSE),"N/A"),0)} -> 0 | Q109: =IF(TcBaseVer=0,M109,IF(AND(N109="Available",M109="Available",O109="Available"),"Available",IF(M109="","","Not Supported"))) -> Available | R109: =IF(A109>=AWCurrentRel, "Future",Q109) -> Available | S109: =HYPERLINK(U109,T109) -> Not Available | T109: =IFERROR(VLOOKUP(CONCATENATE($B109,"_",$A109),Table4[#All],5,FALSE),"Not Available") -> Not Available | U109: =IFERROR(VLOOKUP(CONCATENATE(B109,"_",A109),Table4[#All],6,FALSE),"")
A110: =IF(OR('Raw Data'!A118=0,'Raw Data'!A118="Delete"),"",'Raw Data'!A118) -> 2.2 | B110: =IF(OR('Raw Data'!B118=0,'Raw Data'!B118="Delete"),"",'Raw Data'!B118) -> Develop | C110: =IF(OR('Raw Data'!C118=0,'Raw Data'!C118="Delete"),"",'Raw Data'!C118) -> Documents | D110: =IF(OR('Raw Data'!D118=0,'Raw Data'!D118="Delete"),"",'Raw Data'!D118) -> Document Management | E110: =IF(OR('Raw Data'!E118=0,'Raw Data'!E118="Delete"),"",'Raw Data'!E118) -> New markup tools including freehand tool | F110: {=_xlfn.SWITCH(ROUND(VLOOKUP(A110,Table1[#All],3),0),11,H110,12,I110,13,J110,14,K110,"N/A")} -> 13 | G110: {=_xlfn.SWITCH(ROUND(VLOOKUP(A110,Table1[#All],5),0),11,H110,12,I110,13,J110,14,K110,"N/A")} -> 14 | H110: =IF(OR('Raw Data'!H118=0,'Raw Data'!H118="Delete"),"",'Raw Data'!H118) -> 13 | I110: =IF(OR('Raw Data'!I118=0,'Raw Data'!I118="Delete"),"",'Raw Data'!I118) -> 14 | J110: =IF(OR('Raw Data'!J118=0,'Raw Data'!J118="Delete"),"",'Raw Data'!J118) | K110: =IF(OR('Raw Data'!K118=0,'Raw Data'!K118="Delete"),"",'Raw Data'!K118) | L110: =R110 -> Available | M110: =IF(A110="","",IF(OR(AWReleaseNum>=A110,AWReleaseNum=0),"Available","Not Supported")) -> Available | N110: =IF(A110="","",IF(TcRelease="Any","Available",IF(OR(AND(TcReleaseNum>=VLOOKUP(AWReleaseNum,MinVerInfo,3,FALSE),TcReleaseNum<=VLOOKUP(AWReleaseNum,MinVerInfo,4,FALSE)),AND(TcReleaseNum>=VLOOKUP(AWReleaseNum,MinVerInfo,5,FALSE),TcReleaseNum<=VLOOKUP(AWReleaseNum,MinVerInfo,6,FALSE))),"Available","Not Supported"))) -> Available | O110: =IF(TcReleaseNum<P110,"Not Supported","Available") -> Available | P110: {=_xlfn.SWITCH(TcBaseVer, 14, K110, 13, J110, 12, I110, 11, IFERROR(VLOOKUP(H110,Table2[#All],3,FALSE),"N/A"),0)} -> 0 | Q110: =IF(TcBaseVer=0,M110,IF(AND(N110="Available",M110="Available",O110="Available"),"Available",IF(M110="","","Not Supported"))) -> Available | R110: =IF(A110>=AWCurrentRel, "Future",Q110) -> Available | S110: =HYPERLINK(U110,T110) -> Not Available | T110: =IFERROR(VLOOKUP(CONCATENATE($B110,"_",$A110),Table4[#All],5,FALSE),"Not Available") -> Not Available | U110: =IFERROR(VLOOKUP(CONCATENATE(B110,"_",A110),Table4[#All],6,FALSE),"")
A111: =IF(OR('Raw Data'!A119=0,'Raw Data'!A119="Delete"),"",'Raw Data'!A119) -> 2.2 | B111: =IF(OR('Raw Data'!B119=0,'Raw Data'!B119="Delete"),"",'Raw Data'!B119) -> Plan | C111: =IF(OR('Raw Data'!C119=0,'Raw Data'!C119="Delete"),"",'Raw Data'!C119) -> Systems | D111: =IF(OR('Raw Data'!D119=0,'Raw Data'!D119="Delete"),"",'Raw Data'!D119) -> MBSE - System Architecture, Functional & Systems Modeling | E111: =IF(OR('Raw Data'!E119=0,'Raw Data'!E119="Delete"),"",'Raw Data'!E119) -> Add from outside context where needed | F111: {=_xlfn.SWITCH(ROUND(VLOOKUP(A111,Table1[#All],3),0),11,H111,12,I111,13,J111,14,K111,"N/A")} -> 13 | G111: {=_xlfn.SWITCH(ROUND(VLOOKUP(A111,Table1[#All],5),0),11,H111,12,I111,13,J111,14,K111,"N/A")} -> 14 | H111: =IF(OR('Raw Data'!H119=0,'Raw Data'!H119="Delete"),"",'Raw Data'!H119) -> 13 | I111: =IF(OR('Raw Data'!I119=0,'Raw Data'!I119="Delete"),"",'Raw Data'!I119) -> 14 | J111: =IF(OR('Raw Data'!J119=0,'Raw Data'!J119="Delete"),"",'Raw Data'!J119) | K111: =IF(OR('Raw Data'!K119=0,'Raw Data'!K119="Delete"),"",'Raw Data'!K119) | L111: =R111 -> Available | M111: =IF(A111="","",IF(OR(AWReleaseNum>=A111,AWReleaseNum=0),"Available","Not Supported")) -> Available | N111: =IF(A111="","",IF(TcRelease="Any","Available",IF(OR(AND(TcReleaseNum>=VLOOKUP(AWReleaseNum,MinVerInfo,3,FALSE),TcReleaseNum<=VLOOKUP(AWReleaseNum,MinVerInfo,4,FALSE)),AND(TcReleaseNum>=VLOOKUP(AWReleaseNum,MinVerInfo,5,FALSE),TcReleaseNum<=VLOOKUP(AWReleaseNum,MinVerInfo,6,FALSE))),"Available","Not Supported"))) -> Available | O111: =IF(TcReleaseNum<P111,"Not Supported","Available") -> Available | P111: {=_xlfn.SWITCH(TcBaseVer, 14, K111, 13, J111, 12, I111, 11, IFERROR(VLOOKUP(H111,Table2[#All],3,FALSE),"N/A"),0)} -> 0 | Q111: =IF(TcBaseVer=0,M111,IF(AND(N111="Available",M111="Available",O111="Available"),"Available",IF(M111="","","Not Supported"))) -> Available | R111: =IF(A111>=AWCurrentRel, "Future",Q111) -> Available | S111: =HYPERLINK(U111,T111) -> Not Available | T111: =IFERROR(VLOOKUP(CONCATENATE($B111,"_",$A111),Table4[#All],5,FALSE),"Not Available") -> Not Available | U111: =IFERROR(VLOOKUP(CONCATENATE(B111,"_",A111),Table4[#All],6,FALSE),"")
A112: =IF(OR('Raw Data'!A120=0,'Raw Data'!A120="Delete"),"",'Raw Data'!A120) -> 2.2 | B112: =IF(OR('Raw Data'!B120=0,'Raw Data'!B120="Delete"),"",'Raw Data'!B120) -> Plan | C112: =IF(OR('Raw Data'!C120=0,'Raw Data'!C120="Delete"),"",'Raw Data'!C120) -> Systems | D112: =IF(OR('Raw Data'!D120=0,'Raw Data'!D120="Delete"),"",'Raw Data'!D120) -> MBSE - System Architecture, Functional & Systems Modeling | E112: =IF(OR('Raw Data'!E120=0,'Raw Data'!E120="Delete"),"",'Raw Data'!E120) -> Configured diagram display | F112: {=_xlfn.SWITCH(ROUND(VLOOKUP(A112,Table1[#All],3),0),11,H112,12,I112,13,J112,14,K112,"N/A")} -> 13 | G112: {=_xlfn.SWITCH(ROUND(VLOOKUP(A112,Table1[#All],5),0),11,H112,12,I112,13,J112,14,K112,"N/A")} -> 14 | H112: =IF(OR('Raw Data'!H120=0,'Raw Data'!H120="Delete"),"",'Raw Data'!H120) -> 13 | I112: =IF(OR('Raw Data'!I120=0,'Raw Data'!I120="Delete"),"",'Raw Data'!I120) -> 14 | J112: =IF(OR('Raw Data'!J120=0,'Raw Data'!J120="Delete"),"",'Raw Data'!J120) | K112: =IF(OR('Raw Data'!K120=0,'Raw Data'!K120="Delete"),"",'Raw Data'!K120) | L112: =R112 -> Available | M112: =IF(A112="","",IF(OR(AWReleaseNum>=A112,AWReleaseNum=0),"Available","Not Supported")) -> Available | N112: =IF(A112="","",IF(TcRelease="Any","Available",IF(OR(AND(TcReleaseNum>=VLOOKUP(AWReleaseNum,MinVerInfo,3,FALSE),TcReleaseNum<=VLOOKUP(AWReleaseNum,MinVerInfo,4,FALSE)),AND(TcReleaseNum>=VLOOKUP(AWReleaseNum,MinVerInfo,5,FALSE),TcReleaseNum<=VLOOKUP(AWReleaseNum,MinVerInfo,6,FALSE))),"Available","Not Supported"))) -> Available | O112: =IF(TcReleaseNum<P112,"Not Supported","Available") -> Available | P112: {=_xlfn.SWITCH(TcBaseVer, 14, K112, 13, J112, 12, I112, 11, IFERROR(VLOOKUP(H112,Table2[#All],3,FALSE),"N/A"),0)} -> 0 | Q112: =IF(TcBaseVer=0,M112,IF(AND(N112="Available",M112="Available",O112="Available"),"Available",IF(M112="","","Not Supported"))) -> Available | R112: =IF(A112>=AWCurrentRel, "Future",Q112) -> Available | S112: =HYPERLINK(U112,T112) -> Not Available | T112: =IFERROR(VLOOKUP(CONCATENATE($B112,"_",$A112),Table4[#All],5,FALSE),"Not Available") -> Not Available | U112: =IFERROR(VLOOKUP(CONCATENATE(B112,"_",A112),Table4[#All],6,FALSE),"")
A113: =IF(OR('Raw Data'!A121=0,'Raw Data'!A121="Delete"),"",'Raw Data'!A121) -> 2.2 | B113: =IF(OR('Raw Data'!B121=0,'Raw Data'!B121="Delete"),"",'Raw Data'!B121) -> Plan | C113: =IF(OR('Raw Data'!C121=0,'Raw Data'!C121="Delete"),"",'Raw Data'!C121) -> Systems | D113: =IF(OR('Raw Data'!D121=0,'Raw Data'!D121="Delete"),"",'Raw Data'!D121) -> MBSE - System Architecture, Functional & Systems Modeling | E113: =IF(OR('Raw Data'!E121=0,'Raw Data'!E121="Delete"),"",'Raw Data'!E121) -> Context specific RFLP navigation | F113: {=_xlfn.SWITCH(ROUND(VLOOKUP(A113,Table1[#All],3),0),11,H113,12,I113,13,J113,14,K113,"N/A")} -> 13 | G113: {=_xlfn.SWITCH(ROUND(VLOOKUP(A113,Table1[#All],5),0),11,H113,12,I113,13,J113,14,K113,"N/A")} -> 14 | H113: =IF(OR('Raw Data'!H121=0,'Raw Data'!H121="Delete"),"",'Raw Data'!H121) -> 13 | I113: =IF(OR('Raw Data'!I121=0,'Raw Data'!I121="Delete"),"",'Raw Data'!I121) -> 14 | J113: =IF(OR('Raw Data'!J121=0,'Raw Data'!J121="Delete"),"",'Raw Data'!J121) | K113: =IF(OR('Raw Data'!K121=0,'Raw Data'!K121="Delete"),"",'Raw Data'!K121) | L113: =R113 -> Available | M113: =IF(A113="","",IF(OR(AWReleaseNum>=A113,AWReleaseNum=0),"Available","Not Supported")) -> Available | N113: =IF(A113="","",IF(TcRelease="Any","Available",IF(OR(AND(TcReleaseNum>=VLOOKUP(AWReleaseNum,MinVerInfo,3,FALSE),TcReleaseNum<=VLOOKUP(AWReleaseNum,MinVerInfo,4,FALSE)),AND(TcReleaseNum>=VLOOKUP(AWReleaseNum,MinVerInfo,5,FALSE),TcReleaseNum<=VLOOKUP(AWReleaseNum,MinVerInfo,6,FALSE))),"Available","Not Supported"))) -> Available | O113: =IF(TcReleaseNum<P113,"Not Supported","Available") -> Available | P113: {=_xlfn.SWITCH(TcBaseVer, 14, K113, 13, J113, 12, I113, 11, IFERROR(VLOOKUP(H113,Table2[#All],3,FALSE),"N/A"),0)} -> 0 | Q113: =IF(TcBaseVer=0,M113,IF(AND(N113="Available",M113="Available",O113="Available"),"Available",IF(M113="","","Not Supported"))) -> Available | R113: =IF(A113>=AWCurrentRel, "Future",Q113) -> Available | S113: =HYPERLINK(U113,T113) -> Not Available | T113: =IFERROR(VLOOKUP(CONCATENATE($B113,"_",$A113),Table4[#All],5,FALSE),"Not Available") -> Not Available | U113: =IFERROR(VLOOKUP(CONCATENATE(B113,"_",A113),Table4[#All],6,FALSE),"")
... A126: =IF(OR('Raw Data'!A134=0,'Raw Data'!A134="Delete"),"",'Raw Data'!A134) -> 2.2 | B126: =IF(OR('Raw Data'!B134=0,'Raw Data'!B134="Delete"),"",'Raw Data'!B134) -> Foundation | C126: =IF(OR('Raw Data'!C134=0,'Raw Data'!C134="Delete"),"",'Raw Data'!C134) -> Usability | D126: =IF(OR('Raw Data'!D134=0,'Raw Data'!D134="Delete"),"",'Raw Data'!D134) -> Platform - Active Workspace Framework - Usability | E126: =IF(OR('Raw Data'!E134=0,'Raw Data'!E134="Delete"),"",'Raw Data'!E134) -> Open button default action | F126: {=_xlfn.SWITCH(ROUND(VLOOKUP(A126,Table1[#All],3),0),11,H126,12,I126,13,J126,14,K126,"N/A")} -> 13 | G126: {=_xlfn.SWITCH(ROUND(VLOOKUP(A126,Table1[#All],5),0),11,H126,12,I126,13,J126,14,K126,"N/A")} -> 14 | H126: =IF(OR('Raw Data'!H134=0,'Raw Data'!H134="Delete"),"",'Raw Data'!H134) -> 13 | I126: =IF(OR('Raw Data'!I134=0,'Raw Data'!I134="Delete"),"",'Raw Data'!I134) -> 14 | J126: =IF(OR('Raw Data'!J134=0,'Raw Data'!J134="Delete"),"",'Raw Data'!J134) | K126: =IF(OR('Raw Data'!K134=0,'Raw Data'!K134="Delete"),"",'Raw Data'!K134) | L126: =R126 -> Available | M126: =IF(A126="","",IF(OR(AWReleaseNum>=A126,AWReleaseNum=0),"Available","Not Supported")) -> Available | N126: =IF(A126="","",IF(TcRelease="Any","Available",IF(OR(AND(TcReleaseNum>=VLOOKUP(AWReleaseNum,MinVerInfo,3,FALSE),TcReleaseNum<=VLOOKUP(AWReleaseNum,MinVerInfo,4,FALSE)),AND(TcReleaseNum>=VLOOKUP(AWReleaseNum,MinVerInfo,5,FALSE),TcReleaseNum<=VLOOKUP(AWReleaseNum,MinVerInfo,6,FALSE))),"Available","Not Supported"))) -> Available | O126: =IF(TcReleaseNum<P126,"Not Supported","Available") -> Available | P126: {=_xlfn.SWITCH(TcBaseVer, 14, K126, 13, J126, 12, I126, 11, IFERROR(VLOOKUP(H126,Table2[#All],3,FALSE),"N/A"),0)} -> 0 | Q126: =IF(TcBaseVer=0,M126,IF(AND(N126="Available",M126="Available",O126="Available"),"Available",IF(M126="","","Not Supported"))) -> Available | R126: =IF(A126>=AWCurrentRel, "Future",Q126) -> Available | S126: =HYPERLINK(U126,T126) -> Not Available | T126: =IFERROR(VLOOKUP(CONCATENATE($B126,"_",$A126),Table4[#All],5,FALSE),"Not Available") -> Not Available | U126: =IFERROR(VLOOKUP(CONCATENATE(B126,"_",A126),Table4[#All],6,FALSE),"")
A127: =IF(OR('Raw Data'!A105=0,'Raw Data'!A105="Delete"),"",'Raw Data'!A105) -> 2.2 | B127: =IF(OR('Raw Data'!B105=0,'Raw Data'!B105="Delete"),"",'Raw Data'!B105) -> Deliver | C127: =IF(OR('Raw Data'!C105=0,'Raw Data'!C105="Delete"),"",'Raw Data'!C105) -> Analytics | D127: =IF(OR('Raw Data'!D105=0,'Raw Data'!D105="Delete"),"",'Raw Data'!D105) -> Search and Analytics - Reporting and Analytics | E127: =IF(OR('Raw Data'!E105=0,'Raw Data'!E105="Delete"),"",'Raw Data'!E105) -> Integrated access to report builder reports (prerelease) | F127: {=_xlfn.SWITCH(ROUND(VLOOKUP(A127,Table1[#All],3),0),11,H127,12,I127,13,J127,14,K127,"N/A")} -> 13 | G127: {=_xlfn.SWITCH(ROUND(VLOOKUP(A127,Table1[#All],5),0),11,H127,12,I127,13,J127,14,K127,"N/A")} -> 14 | H127: =IF(OR('Raw Data'!H105=0,'Raw Data'!H105="Delete"),"",'Raw Data'!H105) -> 13 | I127: =IF(OR('Raw Data'!I105=0,'Raw Data'!I105="Delete"),"",'Raw Data'!I105) -> 14 | J127: =IF(OR('Raw Data'!J105=0,'Raw Data'!J105="Delete"),"",'Raw Data'!J105) | K127: =IF(OR('Raw Data'!K105=0,'Raw Data'!K105="Delete"),"",'Raw Data'!K105) | L127: =R127 -> Available | M127: =IF(A127="","",IF(OR(AWReleaseNum>=A127,AWReleaseNum=0),"Available","Not Supported")) -> Available | N127: =IF(A127="","",IF(TcRelease="Any","Available",IF(OR(AND(TcReleaseNum>=VLOOKUP(AWReleaseNum,MinVerInfo,3,FALSE),TcReleaseNum<=VLOOKUP(AWReleaseNum,MinVerInfo,4,FALSE)),AND(TcReleaseNum>=VLOOKUP(AWReleaseNum,MinVerInfo,5,FALSE),TcReleaseNum<=VLOOKUP(AWReleaseNum,MinVerInfo,6,FALSE))),"Available","Not Supported"))) -> Available | O127: =IF(TcReleaseNum<P127,"Not Supported","Available") -> Available | P127: {=_xlfn.SWITCH(TcBaseVer, 14, K127, 13, J127, 12, I127, 11, IFERROR(VLOOKUP(H127,Table2[#All],3,FALSE),"N/A"),0)} -> 0 | Q127: =IF(TcBaseVer=0,M127,IF(AND(N127="Available",M127="Available",O127="Available"),"Available",IF(M127="","","Not Supported"))) -> Available | R127: =IF(A127>=AWCurrentRel, "Future",Q127) -> Available | S127: =HYPERLINK(U127,T127) -> Not Available | T127: =IFERROR(VLOOKUP(CONCATENATE($B127,"_",$A127),Table4[#All],5,FALSE),"Not Available") -> Not Available | U127: =IFERROR(VLOOKUP(CONCATENATE(B127,"_",A127),Table4[#All],6,FALSE),"")
